{"_id":"65a9186d3bbe53cfea10d3fe","createdBy":"6099504c693d8c00155df91f","deleted":false,"parentDocument":{"_id":"65a918503bbe53cfea107478","metadata":{"userGroup":[],"docType":{"showInFluidsPortal":false,"showInTyrePortal":false,"_id":"613771844b25a79f6947d0d8","showInHandbookPortal":false},"reference":"","validFrom":"2024-01-18T12:23:44.680Z","applicabilities":[{"vinRanges":[{"start":"974407","end":"999470"}],"modelYears":[{"start":2020,"end":2020}],"products":["HB6"],"chassisStart":"","chassisEnd":"","markets":[],"inverse":false,"engineNumberRanges":[]}],"negativeApplicabilities":[]}},"id":"4718602123","title":"Service Torque Wrench Settings","content":[{"node":"title","body":[{"node":"text","body":"Service Torque Wrench Settings"}]},{"node":"textmodule","body":[{"node":"title","body":[{"node":"text","body":"Service Torques - HA6 HB6"}]},{"node":"text","body":"\r\n"},{"node":"table-container","body":[{"node":"table","body":[{"node":"tbody","body":[{"node":"tr","body":[{"node":"td","body":[{"node":"p","body":[{"node":"text","body":"Oil Filter"}]}]},{"node":"td","body":[{"node":"p","body":[{"node":"variable","body":[{"node":"text","body":"10 Nm"}]}],"type":"p_table_c"}]},{"node":"td","body":[{"node":"p","body":[{"node":"variable","body":[{"node":"text","body":"Apply clean engine oil to the seal(s)"}]}],"type":"p_table_l"}]}]},{"node":"text","body":" \r\n"},{"node":"tr","body":[{"node":"td","body":[{"node":"p","body":[{"node":"text","body":"Sump Plug"}]}]},{"node":"td","body":[{"node":"p","body":[{"node":"variable","body":[{"node":"text","body":"25 Nm"}]}],"type":"p_table_c"}]},{"node":"td","body":[{"node":"p","body":[{"node":"variable","body":[{"node":"text","body":"Fit new sealing washer(s)"}]}],"type":"p_table_l"}]}]},{"node":"text","body":" \r\n"},{"node":"tr","body":[{"node":"td","body":[{"node":"p","body":[{"node":"text","body":"Upper Airbox Fixings"}]}]},{"node":"td","body":[{"node":"p","body":[{"node":"variable","body":[{"node":"text","body":"1.5 Nm"}]}],"type":"p_table_c"}]},{"node":"td","body":[]}]},{"node":"text","body":" \r\n"},{"node":"tr","body":[{"node":"td","body":[{"node":"p","body":[{"node":"text","body":"Spark Plugs"}]}]},{"node":"td","body":[{"node":"p","body":[{"node":"variable","body":[{"node":"text","body":"12 Nm"}]}],"type":"p_table_c"}]},{"node":"td","body":[]}]},{"node":"text","body":" \r\n"},{"node":"tr","body":[{"node":"td","body":[{"node":"p","body":[{"node":"text","body":"Camshaft Cover"}]}]},{"node":"td","body":[{"node":"p","body":[{"node":"variable","body":[{"node":"text","body":"12 Nm"}]}],"type":"p_table_c"}]},{"node":"td","body":[{"node":"p","body":[{"node":"text","body":"See "},{"node":"link","body":[{"node":"text","body":"Camshaft Cover - Installation"}],"target-id":"4600658955-1","target-base-id":"4600658955"}],"type":"p_table_l"},{"node":"text","body":" \r\n"},{"node":"p","body":[{"node":"variable","body":[{"node":"text","body":"Apply clean engine oil to the seal(s)"}]}],"type":"p_table_l"}]}]},{"node":"text","body":" \r\n"},{"node":"tr","body":[{"node":"td","body":[{"node":"p","body":[{"node":"text","body":"Front Wheel Spindle"}]}]},{"node":"td","body":[{"node":"p","body":[{"node":"variable","body":[{"node":"text","body":"65 Nm"}]}],"type":"p_table_c"}]},{"node":"td","body":[]}]},{"node":"text","body":" \r\n"},{"node":"tr","body":[{"node":"td","body":[{"node":"p","body":[{"node":"text","body":"Front Wheel Spindle Pinch Bolts"}]}]},{"node":"td","body":[{"node":"p","body":[{"node":"variable","body":[{"node":"text","body":"19 Nm"}]}],"type":"p_table_c"}]},{"node":"td","body":[]}]},{"node":"text","body":" \r\n"},{"node":"tr","body":[{"node":"td","body":[{"node":"p","body":[{"node":"text","body":"Upper Yoke Centre Nut"}]}]},{"node":"td","body":[{"node":"p","body":[{"node":"variable","body":[{"node":"text","body":"90 Nm"}]}],"type":"p_table_c"}]},{"node":"td","body":[]}]},{"node":"text","body":" \r\n"},{"node":"tr","body":[{"node":"td","body":[{"node":"p","body":[{"node":"text","body":"Swinging Arm Spindle Nut"}]}]},{"node":"td","body":[{"node":"p","body":[{"node":"variable","body":[{"node":"text","body":"110 Nm"}]}],"type":"p_table_c"}]},{"node":"td","body":[]}]},{"node":"text","body":" \r\n"},{"node":"tr","body":[{"node":"td","body":[{"node":"p","body":[{"node":"text","body":"Front Brake Master Cylinder Reservoir Cap"}]}]},{"node":"td","body":[{"node":"p","body":[{"node":"variable","body":[{"node":"text","body":"0.7 Nm"}]}],"type":"p_table_c"}]},{"node":"td","body":[]}]},{"node":"text","body":" \r\n"},{"node":"tr","body":[{"node":"td","body":[{"node":"p","body":[{"node":"text","body":"Front Brake Master Cylinder Bleed Screw"}]}]},{"node":"td","body":[{"node":"p","body":[{"node":"variable","body":[{"node":"text","body":"14 Nm"}]}],"type":"p_table_c"}]},{"node":"td","body":[]}]},{"node":"text","body":" \r\n"},{"node":"tr","body":[{"node":"td","body":[{"node":"p","body":[{"node":"text","body":"Front Brake Hose to Caliper"}]}]},{"node":"td","body":[{"node":"p","body":[{"node":"variable","body":[{"node":"text","body":"25 Nm"}]}],"type":"p_table_c"}]},{"node":"td","body":[{"node":"p","body":[{"node":"variable","body":[{"node":"text","body":"Fit new sealing washer(s)"}]}],"type":"p_table_l"}]}]},{"node":"text","body":" \r\n"},{"node":"tr","body":[{"node":"td","body":[{"node":"p","body":[{"node":"text","body":"Front Brake Hose to Master Cylinder"}]}]},{"node":"td","body":[{"node":"p","body":[{"node":"variable","body":[{"node":"text","body":"25 Nm"}]}],"type":"p_table_c"}]},{"node":"td","body":[{"node":"p","body":[{"node":"variable","body":[{"node":"text","body":"Fit new sealing washer(s)"}]}],"type":"p_table_l"}]}]},{"node":"text","body":" \r\n"},{"node":"tr","body":[{"node":"td","body":[{"node":"p","body":[{"node":"text","body":"Front Brake Caliper"}]}]},{"node":"td","body":[{"node":"p","body":[{"node":"variable","body":[{"node":"text","body":"55 Nm"}]}],"type":"p_table_c"}]},{"node":"td","body":[]}]},{"node":"text","body":" \r\n"},{"node":"tr","body":[{"node":"td","body":[{"node":"p","body":[{"node":"text","body":"Front Brake Caliper Bleed Screw"}]}]},{"node":"td","body":[{"node":"p","body":[{"node":"variable","body":[{"node":"text","body":"8 Nm"}]}],"type":"p_table_c"}]},{"node":"td","body":[]}]},{"node":"text","body":" \r\n"},{"node":"tr","body":[{"node":"td","body":[{"node":"p","body":[{"node":"text","body":"Rear Brake Master Cylinder Reservoir"}]}]},{"node":"td","body":[{"node":"p","body":[{"node":"variable","body":[{"node":"text","body":"6 Nm"}]}],"type":"p_table_c"}]},{"node":"td","body":[{"node":"p","body":[{"node":"variable","body":[{"node":"text","body":"Fit new fixing(s) if loosened or removed"}]}],"type":"p_table_l"}]}]},{"node":"text","body":" \r\n"},{"node":"tr","body":[{"node":"td","body":[{"node":"p","body":[{"node":"text","body":"Rear Brake Hose to Master Cylinder"}]}]},{"node":"td","body":[{"node":"p","body":[{"node":"variable","body":[{"node":"text","body":"25 Nm"}]}],"type":"p_table_c"}]},{"node":"td","body":[{"node":"p","body":[{"node":"variable","body":[{"node":"text","body":"Fit new sealing washer(s)"}]}],"type":"p_table_l"}]}]},{"node":"text","body":" \r\n"},{"node":"tr","body":[{"node":"td","body":[{"node":"p","body":[{"node":"text","body":"Rear Brake Master Cylinder to Control Plate"}]}]},{"node":"td","body":[{"node":"p","body":[{"node":"variable","body":[{"node":"text","body":"16 Nm"}]}],"type":"p_table_c"}]},{"node":"td","body":[]}]},{"node":"text","body":" \r\n"},{"node":"tr","body":[{"node":"td","body":[{"node":"p","body":[{"node":"text","body":"Rear Brake Pad Retaining Pins"}]}]},{"node":"td","body":[{"node":"p","body":[{"node":"variable","body":[{"node":"text","body":"18 Nm"}]}],"type":"p_table_c"}]},{"node":"td","body":[]}]},{"node":"text","body":" \r\n"},{"node":"tr","body":[{"node":"td","body":[{"node":"p","body":[{"node":"text","body":"Rear Brake Caliper Bleed Screw"}]}]},{"node":"td","body":[{"node":"p","body":[{"node":"variable","body":[{"node":"text","body":"14 Nm"}]}],"type":"p_table_c"}]},{"node":"td","body":[]}]},{"node":"text","body":" \r\n"},{"node":"tr","body":[{"node":"td","body":[{"node":"p","body":[{"node":"text","body":"Fuel Tank to Frame (Rear Fixing) "}]}]},{"node":"td","body":[{"node":"p","body":[{"node":"variable","body":[{"node":"text","body":"8 Nm"}]}],"type":"p_table_c"}]},{"node":"td","body":[]}]},{"node":"text","body":" \r\n"},{"node":"tr","body":[{"node":"td","body":[{"node":"p","body":[{"node":"text","body":"Fuel Tank to Frame (Front Fixing) "}]}]},{"node":"td","body":[{"node":"p","body":[{"node":"variable","body":[{"node":"text","body":"9 Nm"}]}],"type":"p_table_c"}]},{"node":"td","body":[]}]},{"node":"text","body":" \r\n"},{"node":"tr","body":[{"node":"td","body":[{"node":"p","body":[{"node":"text","body":"Rider's Seat"}]}]},{"node":"td","body":[{"node":"p","body":[{"node":"variable","body":[{"node":"text","body":"9 Nm"}]}],"type":"p_table_c"}]},{"node":"td","body":[]}]},{"node":"text","body":" \r\n"},{"node":"tr","body":[{"node":"td","body":[{"node":"p","body":[{"node":"text","body":"Battery Terminals"}]}]},{"node":"td","body":[{"node":"p","body":[{"node":"variable","body":[{"node":"text","body":"4.5 Nm"}]}],"type":"p_table_c"}]},{"node":"td","body":[]}]}]}],"widths":"33.33 33.33 33.33","widthType":"fixed","type":"fixed"}],"type":"framed"}],"metadata":{"MarketsTaxonomyLink":"All"},"type":"TextModule"}],"ancestors":["1342166155"],"parent":"1342166155","lastUpdate":"2019-11-21T17:52:03.000Z","metadata":{"markets":["All"],"_id":"65a9186d3bbe53cfea10d3ff"},"search":["Service Torque Wrench Settings","Oil Filter","10 Nm","Apply clean engine oil to the seal(s)","Sump Plug","25 Nm","Fit new sealing washer(s)","Upper Airbox Fixings","1.5 Nm","Spark Plugs","12 Nm","Camshaft Cover","12 Nm","See ","Camshaft Cover - Installation","Apply clean engine oil to the seal(s)","Front Wheel Spindle","65 Nm","Front Wheel Spindle Pinch Bolts","19 Nm","Upper Yoke Centre Nut","90 Nm","Swinging Arm Spindle Nut","110 Nm","Front Brake Master Cylinder Reservoir Cap","0.7 Nm","Front Brake Master Cylinder Bleed Screw","14 Nm","Front Brake Hose to Caliper","25 Nm","Fit new sealing washer(s)","Front Brake Hose to Master Cylinder","25 Nm","Fit new sealing washer(s)","Front Brake Caliper","55 Nm","Front Brake Caliper Bleed Screw","8 Nm","Rear Brake Master Cylinder Reservoir","6 Nm","Fit new fixing(s) if loosened or removed","Rear Brake Hose to Master Cylinder","25 Nm","Fit new sealing washer(s)","Rear Brake Master Cylinder to Control Plate","16 Nm","Rear Brake Pad Retaining Pins","18 Nm","Rear Brake Caliper Bleed Screw","14 Nm","Fuel Tank to Frame (Rear Fixing) ","8 Nm","Fuel Tank to Frame (Front Fixing) ","9 Nm","Rider's Seat","9 Nm","Battery Terminals","4.5 Nm"],"viewCount":0,"infoType":"InfoType07","views":[],"createdAt":"2024-01-18T12:24:13.613Z","updatedAt":"2024-01-18T12:24:13.613Z","__v":0}