{"_id":"65c772758dab24d43a9e6549","createdBy":"6099504c693d8c00155df91f","deleted":false,"parentDocument":{"_id":"65c772738dab24d43a9e5f1b","metadata":{"userGroup":[],"docType":{"showInFluidsPortal":false,"showInTyrePortal":false,"_id":"613771844b25a79f6947d0d8","showInHandbookPortal":false},"reference":"","validFrom":"2024-02-10T12:56:13.668Z","applicabilities":[{"vinRanges":[{"start":"A00001","end":"zzzzzz"}],"modelYears":[{"start":2024,"end":9999}],"products":["TD1"],"chassisStart":"","chassisEnd":"","markets":[],"inverse":false,"engineNumberRanges":[]}],"negativeApplicabilities":[]}},"id":"190144267","title":"Force","content":[{"node":"title","body":[{"node":"text","body":"Force"}]},{"node":"p","body":[{"node":"text","body":"Common sense should dictate how much force is necessary in assembly and disassembly. If a part seems especially difficult to remove or install, stop and examine what may be causing the problem. Never lever a component as this will cause damage both to the component itself and to the surface being levered against."}]},{"node":"p","body":[{"node":"text","body":"Whenever tapping to aid removal of an item is necessary, tap lightly using a hide or plastic faced mallet."}]}],"ancestors":["1342003339"],"parent":"1342003339","lastUpdate":"2023-11-14T13:29:27.000Z","metadata":{"markets":["All"],"_id":"65c772758dab24d43a9e654a"},"search":["Force","Common sense should dictate how much force is necessary in assembly and disassembly. If a part seems especially difficult to remove or install, stop and examine what may be causing the problem. Never lever a component as this will cause damage both to the component itself and to the surface being levered against.","Whenever tapping to aid removal of an item is necessary, tap lightly using a hide or plastic faced mallet."],"viewCount":0,"infoType":"InfoType02","views":[],"createdAt":"2024-02-10T12:56:21.343Z","updatedAt":"2024-02-10T12:56:21.343Z","__v":0}