{"_id":"65c7647a8dab24d43a9b2371","createdBy":"6099504c693d8c00155df91f","deleted":false,"parentDocument":{"_id":"65c764748dab24d43a9b0a77","metadata":{"userGroup":[],"docType":{"showInFluidsPortal":false,"showInTyrePortal":false,"_id":"613771844b25a79f6947d0d8","showInHandbookPortal":false},"reference":"","validFrom":"2024-02-10T11:56:31.898Z","applicabilities":[{"vinRanges":[{"start":"A00029","end":"zzzzzz"}],"modelYears":[{"start":2024,"end":9999}],"products":["TH1"],"chassisStart":"","chassisEnd":"","markets":[],"inverse":false,"engineNumberRanges":[]}],"negativeApplicabilities":[]}},"id":"8679837707","title":"Camshaft - Installation and Timing","content":[{"node":"title","body":[{"node":"text","body":"Camshaft - Installation and Timing"}]},{"node":"safety","body":[{"node":"text","body":"\r\n"},{"node":"consequence","body":[{"node":"text","body":"Never fit the camshafts without correctly setting the camshaft timing using the service tools and timing procedure described below. Severe engine damage will result from incorrect valve timing adjustment."}]},{"node":"text","body":" "}],"severity":"caution","type":"general"},{"node":"procedural-instructions","body":[{"node":"instructions","body":[{"node":"instruction","body":[{"node":"text","body":"Check that "},{"node":"variable","body":[{"node":"text","body":"Service Tool 37104427"}]},{"node":"text","body":" is installed, the TDC indicator is still aligned and that the crankshaft cannot rotate."}]},{"node":"text","body":" \r\n"},{"node":"image-container","body":[{"node":"img","body":[],"href":"8953279883__Web.svg","id":"8953279883","name":"TDC Indicator_TP0050","type":"svg"},{"node":"text","body":" \r\n"},{"node":"table-container","body":[{"node":"table","body":[{"node":"tbody","body":[{"node":"tr","body":[{"node":"td","body":[{"node":"ol","body":[{"node":"li","body":[{"node":"p","body":[{"node":"text","body":"Plug"}],"type":"p_table_l"}]},{"node":"text","body":" \r\n"},{"node":"li","body":[{"node":"p","body":[{"node":"text","body":"Pointer"}],"type":"p_table_l"}]},{"node":"text","body":" \r\n"},{"node":"li","body":[{"node":"p","body":[{"node":"text","body":"TDC indicator"}],"type":"p_table_l"}]}],"type":"1"}]},{"node":"text","body":" "}]},{"node":"text","body":" "}]}],"widths":"100","widthType":"fixed","type":"fixed"}],"type":"legend"}],"type":"img_fixed_column"},{"node":"text","body":" \r\n"},{"node":"instruction","body":[{"node":"text","body":"Thoroughly clean the camshafts and journals."}]},{"node":"text","body":" \r\n"},{"node":"instruction","body":[{"node":"text","body":"Make sure that the valve shims are installed in their original positions."}]},{"node":"text","body":" \r\n"},{"node":"instruction","body":[{"node":"text","body":"Make sure the cam followers are in their correct operating positions touching the valve shims."}]},{"node":"text","body":" \r\n"},{"node":"instruction","body":[{"node":"text","body":"Lubricate the camshafts with clean engine oil before fitting to the cylinder head."}]},{"node":"text","body":" \r\n"},{"node":"safety","body":[{"node":"text","body":"\r\n"},{"node":"consequence","body":[{"node":"text","body":"Make sure that the camshafts are correctly identified (inlet and exhaust) and are also correctly located over their respective valve banks."}]}],"severity":"notice","type":"notice"},{"node":"text","body":" \r\n"},{"node":"instruction","body":[{"node":"text","body":"Refit the exhaust camshaft to the cylinder head, hooking the camshaft drive chain over the sprocket as you do so. Make sure that the camshaft drive chain is taught between the crankshaft sprocket and the front edge of the exhaust cam sprocket."}]},{"node":"text","body":" \r\n"},{"node":"image-container","body":[{"node":"img","body":[],"href":"8955252235__Web.svg","id":"8955252235","name":"Exhaust Camshaft_TP0023","type":"svg"},{"node":"text","body":" \r\n"},{"node":"table-container","body":[{"node":"table","body":[{"node":"tbody","body":[{"node":"tr","body":[{"node":"td","body":[{"node":"ol","body":[{"node":"li","body":[{"node":"p","body":[{"node":"text","body":"Camshaft drive chain"}],"type":"p_table_l"}]},{"node":"text","body":"\r\n"},{"node":"li","body":[{"node":"p","body":[{"node":"text","body":"Exhaust camshaft and sprocket assembly"}],"type":"p_table_l"}]},{"node":"text","body":" "}],"type":"1"}]},{"node":"text","body":" "}]},{"node":"text","body":" "}]}],"widths":"100","widthType":"fixed","type":"fixed"}],"type":"legend"}],"type":"img_fixed_column"},{"node":"text","body":" \r\n"},{"node":"instruction","body":[{"node":"text","body":"Make sure there is no slack between the crankshaft and exhaust sprocket when the alignment marks on the camshaft sprocket align with the cylinder head top face."}]},{"node":"text","body":" \r\n"},{"node":"image-container","body":[{"node":"img","body":[],"href":"8954792075__Web.svg","id":"8954792075","name":"Camshaft TDC aligment marks_TP0018","type":"svg"},{"node":"text","body":" \r\n"},{"node":"table-container","body":[{"node":"table","body":[{"node":"tbody","body":[{"node":"tr","body":[{"node":"td","body":[{"node":"ol","body":[{"node":"li","body":[{"node":"p","body":[{"node":"text","body":"Alignment marks"}],"type":"p_table_l"}]},{"node":"text","body":" \r\n"},{"node":"li","body":[{"node":"p","body":[{"node":"text","body":"Cylinder head top face"}],"type":"p_table_l"}]},{"node":"text","body":" \r\n"},{"node":"li","body":[{"node":"p","body":[{"node":"text","body":"Camshaft sprockets"}],"type":"p_table_l"}]}],"type":"1"}]},{"node":"text","body":" "}]},{"node":"text","body":" "}]}],"widths":"100","widthType":"fixed","type":"fixed"}],"type":"legend"}],"type":"img_fixed_column"},{"node":"text","body":" \r\n"},{"node":"instruction","body":[{"node":"text","body":"Refit the inlet camshaft to the cylinder head, hooking the chain over the sprocket as you do so."}]},{"node":"text","body":" \r\n"},{"node":"instruction","body":[{"node":"text","body":"Make sure there is no slack between the exhaust sprocket and the inlet sprocket when the alignment marks on the camshaft sprockets align with the cylinder head top face."}]},{"node":"text","body":" \r\n"},{"node":"instruction","body":[{"node":"text","body":"Check that the chain is correctly located around the crankshaft, and both camshaft sprockets."}]},{"node":"text","body":" \r\n"},{"node":"safety","body":[{"node":"text","body":"\r\n"},{"node":"consequence","body":[{"node":"text","body":"Severe engine damage will result from incorrect valve timing adjustment."}]},{"node":"text","body":" "}],"severity":"caution","type":"general"},{"node":"text","body":" \r\n"},{"node":"instruction","body":[{"node":"text","body":"Assemble the camshaft ladder and chain guide in the same location and orientation as before removal. "}]},{"node":"text","body":" \r\n"},{"node":"image-container","body":[{"node":"img","body":[],"href":"8955159947__Web.svg","id":"8955159947","name":"Camshaft Ladder_TP0020","type":"svg"},{"node":"text","body":" \r\n"},{"node":"table-container","body":[{"node":"table","body":[{"node":"tbody","body":[{"node":"tr","body":[{"node":"td","body":[{"node":"ol","body":[{"node":"li","body":[{"node":"p","body":[{"node":"text","body":"Fixings"}],"type":"p_table_l"}]},{"node":"text","body":" \r\n"},{"node":"li","body":[{"node":"p","body":[{"node":"text","body":"Camshaft ladder"}],"type":"p_table_l"}]},{"node":"text","body":" \r\n"},{"node":"li","body":[{"node":"p","body":[{"node":"text","body":"Camshaft chain guide"}],"type":"p_table_l"}]}],"type":"1"}]},{"node":"text","body":" "}]},{"node":"text","body":" "}]}],"widths":"100","widthType":"fixed","type":"fixed"}],"type":"legend"}],"type":"img_fixed_column"},{"node":"text","body":" \r\n"},{"node":"instruction","body":[{"node":"text","body":"Install and tighten the camshaft ladder fixings until finger tight."}]},{"node":"text","body":" \r\n"},{"node":"instruction","body":[{"node":"text","body":"Gradually tighten the fixings in the sequence shown below to "},{"node":"variable","body":[{"node":"text","body":"8 Nm"}]}]},{"node":"text","body":" \r\n"},{"node":"image-container","body":[{"node":"img","body":[],"href":"8977671563__Web.svg","id":"8977671563","name":"Camshaft Ladder Torque Sequence_TP0041","type":"svg"},{"node":"text","body":" \r\n"},{"node":"table-container","body":[{"node":"table","body":[{"node":"tbody","body":[{"node":"tr","body":[{"node":"td","body":[{"node":"p","body":[{"node":"text","body":"Camshaft Cover Fixings Tightening Sequence"}],"type":"p_table_l"}]},{"node":"text","body":" "}]},{"node":"text","body":" "}]}],"widths":"100","widthType":"fixed","type":"fixed"}],"type":"legend"}],"type":"img_fixed_column"}]}]},{"node":"procedural-instructions","body":[{"node":"instructions","body":[{"node":"instruction","body":[{"node":"text","body":"Refit the timing chain tensioner, incorporating a new gasket and O-ring (see "},{"node":"link","body":[{"node":"text","body":"Camshaft Drive Chain Tensioner - Installation"}],"target-id":"9007208201969291-2","target-base-id":"8947228299"},{"node":"text","body":")."}]},{"node":"text","body":" \r\n"},{"node":"instruction","body":[{"node":"text","body":"Remove the crankshaft locking tool."}]},{"node":"text","body":" \r\n"},{"node":"instruction","body":[{"node":"text","body":"Use the nut on the crankshaft to rotate the crankshaft clockwise 2 complete turns. Stop rotation when the piston is at Top Dead Centre (TDC), that is when the alignment mark on the alternator rotor aligns with the pointer on the crankcase."}]},{"node":"text","body":" \r\n"},{"node":"image-container","body":[{"node":"img","body":[],"href":"8953279883__Web.svg","id":"8953279883","name":"TDC Indicator_TP0050","type":"svg"},{"node":"text","body":" \r\n"},{"node":"table-container","body":[{"node":"table","body":[{"node":"tbody","body":[{"node":"tr","body":[{"node":"td","body":[{"node":"ol","body":[{"node":"li","body":[{"node":"p","body":[{"node":"text","body":"Plug"}],"type":"p_table_l"}]},{"node":"text","body":" \r\n"},{"node":"li","body":[{"node":"p","body":[{"node":"text","body":"Pointer"}],"type":"p_table_l"}]},{"node":"text","body":" \r\n"},{"node":"li","body":[{"node":"p","body":[{"node":"text","body":"TDC indicator"}],"type":"p_table_l"}]}],"type":"1"}]},{"node":"text","body":" "}]},{"node":"text","body":" "}]}],"widths":"100","widthType":"fixed","type":"fixed"}],"type":"legend"}],"type":"img_fixed_column"},{"node":"text","body":" \r\n"},{"node":"instruction","body":[{"node":"text","body":"If installed, remove the blanking screw that covers the hole for the crankshaft locking tool in the crankcase."}]},{"node":"text","body":" \r\n"},{"node":"image-container","body":[{"node":"img","body":[],"href":"8969084811__Web.svg","id":"8969084811","name":"Crankshaft Locking Pin Blanking Plug_TP0021","type":"svg"},{"node":"text","body":" \r\n"},{"node":"table-container","body":[{"node":"table","body":[{"node":"tbody","body":[{"node":"tr","body":[{"node":"td","body":[{"node":"ol","body":[{"node":"li","body":[{"node":"p","body":[{"node":"text","body":"Crankcase hole"}],"type":"p_table_l"}]},{"node":"text","body":" \r\n"},{"node":"li","body":[{"node":"p","body":[{"node":"text","body":"Blanking screw"}],"type":"p_table_l"}]},{"node":"text","body":" "}],"type":"1"}]},{"node":"text","body":" "}]},{"node":"text","body":" "}]}],"widths":"100","widthType":"fixed","type":"fixed"}],"type":"legend"}],"type":"img_fixed_column"},{"node":"text","body":" \r\n"},{"node":"instruction","body":[{"node":"text","body":"Insert "},{"node":"variable","body":[{"node":"text","body":"Service Tool 37104427"}]},{"node":"text","body":" into the timing holes in the crankcase and crankshaft."}]},{"node":"text","body":" \r\n"},{"node":"instruction","body":[{"node":"text","body":"Check the valve clearances (see "},{"node":"link","body":[{"node":"text","body":"Valve Clearance Measurement"}],"target-id":"8953126411-2","target-base-id":"8953126411"},{"node":"text","body":"). Adjust as necessary (see "},{"node":"link","body":[{"node":"text","body":"Valve Clearance Adjustment"}],"target-id":"8953121291-2","target-base-id":"8953121291"},{"node":"text","body":")."}]},{"node":"text","body":" \r\n"},{"node":"instruction","body":[{"node":"text","body":"Remove "},{"node":"variable","body":[{"node":"text","body":"Service Tool 37104427"}]},{"node":"text","body":"."}]},{"node":"text","body":" \r\n"},{"node":"instruction","body":[{"node":"text","body":"Fit the blanking screw and tighten to "},{"node":"variable","body":[{"node":"text","body":"11 Nm"}]},{"node":"text","body":"."}]},{"node":"text","body":" \r\n"},{"node":"instruction","body":[{"node":"text","body":"Fit a new O-ring onto the breather tube for the inlet camshaft."}]},{"node":"text","body":" \r\n"},{"node":"instruction","body":[{"node":"text","body":"Install the breather tube into the end of the inlet camshaft."}]},{"node":"text","body":" \r\n"},{"node":"image-container","body":[{"node":"img","body":[],"href":"8955167371__Web.svg","id":"8955167371","name":"Cylinder Head Breather Tube_TP017","type":"svg"},{"node":"text","body":" \r\n"},{"node":"table-container","body":[{"node":"table","body":[{"node":"tbody","body":[{"node":"tr","body":[{"node":"td","body":[{"node":"ol","body":[{"node":"li","body":[{"node":"p","body":[{"node":"text","body":"Fixing"}],"type":"p_table_l"}]},{"node":"text","body":" \r\n"},{"node":"li","body":[{"node":"p","body":[{"node":"text","body":"Breather tube"}],"type":"p_table_l"}]},{"node":"text","body":" \r\n"},{"node":"li","body":[{"node":"p","body":[{"node":"text","body":"Inlet camshaft"}],"type":"p_table_l"}]},{"node":"text","body":" \r\n"},{"node":"li","body":[{"node":"p","body":[{"node":"text","body":"O-ring"}],"type":"p_table_l"}]}],"type":"1"}]},{"node":"text","body":" "}]},{"node":"text","body":" "}]}],"widths":"100","widthType":"fixed","type":"fixed"}],"type":"legend"}],"type":"img_fixed_column"},{"node":"text","body":" \r\n"},{"node":"instruction","body":[{"node":"text","body":"Install the fixing that attaches the breather tube to the cylinder head and tighten to "},{"node":"variable","body":[{"node":"text","body":"10 Nm"}]},{"node":"text","body":"."}]},{"node":"text","body":" \r\n"},{"node":"instruction","body":[{"node":"text","body":"Fit new O-rings into the opening for the spark plug sleeve."}]},{"node":"text","body":" \r\n"},{"node":"image-container","body":[{"node":"img","body":[],"href":"8980497163__Web.svg","id":"8980497163","name":"Spark Plug Sleeve O-Rings_TP0027","type":"svg"},{"node":"text","body":" \r\n"},{"node":"table-container","body":[{"node":"table","body":[{"node":"tbody","body":[{"node":"tr","body":[{"node":"td","body":[{"node":"ol","body":[{"node":"li","body":[{"node":"p","body":[{"node":"text","body":"O-Rings"}],"type":"p_table_l"}]},{"node":"text","body":" "}],"type":"1"}]},{"node":"text","body":" "}]},{"node":"text","body":" "}]}],"widths":"100","widthType":"fixed","type":"fixed"}],"type":"legend"}],"type":"img_fixed_column"},{"node":"text","body":" \r\n"},{"node":"instruction","body":[{"node":"text","body":"Fit the spark plug sleeve."}]},{"node":"text","body":" \r\n"},{"node":"image-container","body":[{"node":"img","body":[],"href":"8955081099__Web.svg","id":"8955081099","name":"Spark Plug Sleeve_TP0026","type":"svg"},{"node":"text","body":" \r\n"},{"node":"table-container","body":[{"node":"table","body":[{"node":"tbody","body":[{"node":"tr","body":[{"node":"td","body":[{"node":"ol","body":[{"node":"li","body":[{"node":"p","body":[{"node":"text","body":"Spark plug sleeve"}],"type":"p_table_l"}]}],"type":"1"}]},{"node":"text","body":" "}]},{"node":"text","body":" "}]}],"widths":"100","widthType":"fixed","type":"fixed"}],"type":"legend"}],"type":"img_fixed_column"},{"node":"text","body":" \r\n"},{"node":"instruction","body":[{"node":"text","body":"Refit the camshaft cover (see "},{"node":"link","body":[{"node":"text","body":"Camshaft Cover - Installation"}],"target-id":"9007207934298763-2","target-base-id":"8679557771"},{"node":"text","body":")."}]},{"node":"text","body":" \r\n"},{"node":"instruction","body":[{"node":"text","body":"Install the spark plug and tighten to "},{"node":"variable","body":[{"node":"text","body":"17 Nm"}]},{"node":"text","body":"."}]},{"node":"text","body":" "}]}]},{"node":"textmodule","body":[{"node":"title","body":[{"node":"text","body":"Perform the following operations"}]},{"node":"text","body":"\r\n"},{"node":"p","body":[{"node":"text","body":"Perform the following operations:"}]},{"node":"text","body":"\r\n"}],"metadata":{"Publication":"SM","MarketsTaxonomyLink":"All"},"type":"TextModule"},{"node":"ul","body":[{"node":"li","body":[{"node":"p","body":[{"node":"link","body":[{"node":"text","body":"Clutch Cover - Installation"}],"target-id":"8679724555-2","target-base-id":"8679724555"}]}]},{"node":"text","body":" \r\n"},{"node":"li","body":[{"node":"p","body":[{"node":"link","body":[{"node":"text","body":"Engine Front Left Cover - Installation"}],"target-id":"8679735563-2","target-base-id":"8679735563"}]}]}],"type":"disc"},{"node":"image","body":[],"type":"svg"},{"node":"image","body":[],"type":"svg"},{"node":"image","body":[],"type":"svg"},{"node":"image","body":[],"type":"svg"},{"node":"image","body":[],"type":"svg"},{"node":"image","body":[],"type":"svg"},{"node":"image","body":[],"type":"svg"},{"node":"image","body":[],"type":"svg"},{"node":"image","body":[],"type":"svg"}],"ancestors":["1342193291"],"parent":"1342193291","lastUpdate":"2023-11-13T10:41:25.000Z","metadata":{"markets":["All"],"_id":"65c7647a8dab24d43a9b2372"},"search":["Camshaft - Installation and Timing","Never fit the camshafts without correctly setting the camshaft timing using the service tools and timing procedure described below. Severe engine damage will result from incorrect valve timing adjustment.","Check that ","Service Tool 37104427"," is installed, the TDC indicator is still aligned and that the crankshaft cannot rotate.","Plug","Pointer","TDC indicator","Thoroughly clean the camshafts and journals.","Make sure that the valve shims are installed in their original positions.","Make sure the cam followers are in their correct operating positions touching the valve shims.","Lubricate the camshafts with clean engine oil before fitting to the cylinder head.","Make sure that the camshafts are correctly identified (inlet and exhaust) and are also correctly located over their respective valve banks.","Refit the exhaust camshaft to the cylinder head, hooking the camshaft drive chain over the sprocket as you do so. Make sure that the camshaft drive chain is taught between the crankshaft sprocket and the front edge of the exhaust cam sprocket.","Camshaft drive chain","Exhaust camshaft and sprocket assembly","Make sure there is no slack between the crankshaft and exhaust sprocket when the alignment marks on the camshaft sprocket align with the cylinder head top face.","Alignment marks","Cylinder head top face","Camshaft sprockets","Refit the inlet camshaft to the cylinder head, hooking the chain over the sprocket as you do so.","Make sure there is no slack between the exhaust sprocket and the inlet sprocket when the alignment marks on the camshaft sprockets align with the cylinder head top face.","Check that the chain is correctly located around the crankshaft, and both camshaft sprockets.","Severe engine damage will result from incorrect valve timing adjustment.","Assemble the camshaft ladder and chain guide in the same location and orientation as before removal. ","Fixings","Camshaft ladder","Camshaft chain guide","Install and tighten the camshaft ladder fixings until finger tight.","Gradually tighten the fixings in the sequence shown below to ","8 Nm","Camshaft Cover Fixings Tightening Sequence","Refit the timing chain tensioner, incorporating a new gasket and O-ring (see ","Camshaft Drive Chain Tensioner - Installation",").","Remove the crankshaft locking tool.","Use the nut on the crankshaft to rotate the crankshaft clockwise 2 complete turns. Stop rotation when the piston is at Top Dead Centre (TDC), that is when the alignment mark on the alternator rotor aligns with the pointer on the crankcase.","Plug","Pointer","TDC indicator","If installed, remove the blanking screw that covers the hole for the crankshaft locking tool in the crankcase.","Crankcase hole","Blanking screw","Insert ","Service Tool 37104427"," into the timing holes in the crankcase and crankshaft.","Check the valve clearances (see ","Valve Clearance Measurement","). Adjust as necessary (see ","Valve Clearance Adjustment",").","Remove ","Service Tool 37104427",".","Fit the blanking screw and tighten to ","11 Nm",".","Fit a new O-ring onto the breather tube for the inlet camshaft.","Install the breather tube into the end of the inlet camshaft.","Fixing","Breather tube","Inlet camshaft","O-ring","Install the fixing that attaches the breather tube to the cylinder head and tighten to ","10 Nm",".","Fit new O-rings into the opening for the spark plug sleeve.","O-Rings","Fit the spark plug sleeve.","Spark plug sleeve","Refit the camshaft cover (see ","Camshaft Cover - Installation",").","Install the spark plug and tighten to ","17 Nm",".","Perform the following operations:","Clutch Cover - Installation","Engine Front Left Cover - Installation"],"viewCount":9,"infoType":"InfoType02","views":[{"createdBy":"638abb7817b2aed68a1ba967","createdAt":"2024-02-14T19:29:53.177Z","_id":"65dd58d1e919dffe562343f9"},{"createdBy":"638abb7817b2aed68a1ba967","createdAt":"2024-01-19T19:39:35.666Z","_id":"65de89b16cc2da9200f27b65"},{"createdBy":"65df8587c85ec2286f23f847","createdAt":"2024-02-14T19:29:53.177Z","_id":"65df8659e919dffe564247ea"},{"createdBy":"65c35fe2c20ee76207fed5df","createdAt":"2024-02-14T22:45:46.509Z","_id":"65e5a008c85ec2286f65fd8f"},{"createdBy":"65c35fe2c20ee76207fed5df","createdAt":"2024-01-18T14:47:25.427Z","_id":"65e850688dab24d43afe57a8"},{"createdBy":"65cf87b8c85ec2286f6975b4","createdAt":"2024-03-07T11:20:57.558Z","_id":"65f2ee07128aa1fbe1840378"},{"createdBy":"61811987bc37e0d7a13702fd","createdAt":"2024-03-07T11:20:06.306Z","_id":"65f42aca80382e44e4259744"},{"createdBy":"61811987bc37e0d7a13702fd","createdAt":"2024-03-07T11:20:57.573Z","_id":"65f42b4bfb41b50912b595dd"},{"createdBy":"61811987bc37e0d7a13702fd","createdAt":"2024-03-07T11:20:57.558Z","_id":"65f42fb5128aa1fbe1927bc4"}],"createdAt":"2024-02-10T11:56:42.190Z","updatedAt":"2024-03-15T11:23:33.181Z","__v":0,"updatedBy":"61811987bc37e0d7a13702fd"}