{"_id":"65dcbb0cc85ec2286ffa012c","createdBy":"6099504c693d8c00155df91f","deleted":false,"parentDocument":{"_id":"65dcbb0cc85ec2286ffa0124","metadata":{"userGroup":[],"docType":{"showInFluidsPortal":false,"showInTyrePortal":false,"_id":"6152ea55c46320dedacd58a8","showInHandbookPortal":false},"reference":"","validFrom":"2024-02-26T00:00:00.000Z","applicabilities":[{"vinRanges":[],"modelYears":[],"products":["TD1"],"chassisStart":"","chassisEnd":"","markets":[],"inverse":false,"engineNumberRanges":[]}],"negativeApplicabilities":[]}},"id":"9312710283","title":"Service Data Sheet","content":[{"node":"title","body":[{"node":"text","body":"Service Data Sheet"}]},{"node":"p","body":[{"node":"text","body":"This Service Data Sheet is a quick reference guide for motorcycle service."}]},{"node":"textmodule","body":[{"node":"title","body":[{"node":"text","body":"Warning - Refer to Service Manual for Service Data"}]},{"node":"text","body":"\r\n"},{"node":"safety","body":[{"node":"text","body":"\r\n"},{"node":"consequence","body":[{"node":"text","body":"Always refer to the Service Manual for detailed data related to routine maintenance and adjustment."}]},{"node":"text","body":" \r\n"},{"node":"consequence","body":[{"node":"text","body":"Incorrect maintenance or adjustment may cause one or more parts of the motorcycle to malfunction. "}]},{"node":"text","body":" \r\n"},{"node":"consequence","body":[{"node":"text","body":"A malfunctioning motorcycle may lead to loss of motorcycle control which could result in serious injury or death."}]}],"severity":"warning","type":"general"}],"metadata":{"MarketsTaxonomyLink":"All"},"type":"TextModule"},{"node":"textmodule","body":[{"node":"title","body":[{"node":"text","body":"Scheduled Maintenance - Specifications - T*1"}]},{"node":"text","body":"\r\n"},{"node":"subheading","body":[{"node":"text","body":"Brakes"}]},{"node":"text","body":" \r\n"},{"node":"table-container","body":[{"node":"table","body":[{"node":"tbody","body":[{"node":"tr","body":[{"node":"td","body":[{"node":"p","body":[{"node":"variable","body":[{"node":"text","body":"Front brake disc maximum run-out"}]}]}]},{"node":"td","body":[{"node":"p","body":[{"node":"variable","body":[{"node":"text","body":"0.25 mm"}]}]}]}]},{"node":"text","body":" \r\n"},{"node":"tr","body":[{"node":"td","body":[{"node":"p","body":[{"node":"variable","body":[{"node":"text","body":"Rear brake disc maximum run-out"}]}]}]},{"node":"td","body":[{"node":"p","body":[{"node":"variable","body":[{"node":"text","body":"0.25 mm"}]}]}]}]},{"node":"text","body":" \r\n"},{"node":"tr","body":[{"node":"td","body":[{"node":"p","body":[{"node":"variable","body":[{"node":"text","body":"Front brake disc thickness - service limit"}]}]}]},{"node":"td","body":[{"node":"p","body":[{"node":"variable","body":[{"node":"text","body":"4.5 mm"}]}]}]}]},{"node":"text","body":" \r\n"},{"node":"tr","body":[{"node":"td","body":[{"node":"p","body":[{"node":"variable","body":[{"node":"text","body":"Rear brake disc thickness - service limit"}]}]}]},{"node":"td","body":[{"node":"p","body":[{"node":"variable","body":[{"node":"text","body":"4.0 mm"}]}]}]}]},{"node":"text","body":" \r\n"},{"node":"tr","body":[{"node":"td","body":[{"node":"p","body":[{"node":"variable","body":[{"node":"text","body":"Recommended brake fluid"}]}]}]},{"node":"td","body":[{"node":"p","body":[{"node":"variable","body":[{"node":"text","body":"Triumph Performance DOT 4 brake fluid"}]}]}]}]},{"node":"text","body":" \r\n"},{"node":"tr","body":[{"node":"td","body":[{"node":"p","body":[{"node":"variable","body":[{"node":"text","body":"Front brake pad lining minimum thickness"}]}]}]},{"node":"td","body":[{"node":"p","body":[{"node":"variable","body":[{"node":"text","body":"1 mm"}]}]}]}]},{"node":"text","body":" \r\n"},{"node":"tr","body":[{"node":"td","body":[{"node":"p","body":[{"node":"variable","body":[{"node":"text","body":"Rear brake pad lining minimum thickness"}]}]}]},{"node":"td","body":[{"node":"p","body":[{"node":"variable","body":[{"node":"text","body":"0.8 mm "}]}]}]}]},{"node":"text","body":" "}]}],"widths":"35 65","widthType":"fixed","type":"fixed"}],"type":"framed"},{"node":"text","body":" \r\n"},{"node":"subheading","body":[{"node":"text","body":"Cooling System"}]},{"node":"text","body":" \r\n"},{"node":"table-container","body":[{"node":"table","body":[{"node":"tbody","body":[{"node":"tr","body":[{"node":"td","body":[{"node":"p","body":[{"node":"variable","body":[{"node":"text","body":"Cooling System Capacity"}]}]}]},{"node":"td","body":[{"node":"p","body":[{"node":"variable","body":[{"node":"text","body":"1.2 liters"}]}]}]}]},{"node":"text","body":" "}]}],"widths":"35 65","widthType":"fixed","type":"fixed"}],"type":"framed"},{"node":"text","body":" \r\n"},{"node":"subheading","body":[{"node":"text","body":"Engine"}]},{"node":"text","body":" \r\n"},{"node":"table-container","body":[{"node":"table","body":[{"node":"tbody","body":[{"node":"tr","body":[{"node":"td","body":[{"node":"p","body":[{"node":"variable","body":[{"node":"text","body":"Valve gap (clearance)"}]}]}]},{"node":"td","body":[{"node":"p","body":[{"node":"variable","body":[{"node":"text","body":"Inlet: 0.07 - 0.13"}]}]}]}]},{"node":"text","body":" \r\n"},{"node":"tr","body":[{"node":"td","body":[{"node":"p","body":[{"node":"variable","body":[{"node":"text","body":"Valve gap (clearance)"}]}]}]},{"node":"td","body":[{"node":"p","body":[{"node":"variable","body":[{"node":"text","body":"Exhaust: 0.12 - 0.18"}]}]}]}]},{"node":"text","body":" "}]}],"widths":"35 65","widthType":"fixed","type":"fixed"}],"type":"framed"},{"node":"text","body":" \r\n"},{"node":"subheading","body":[{"node":"text","body":"Final Drive"}]},{"node":"text","body":" \r\n"},{"node":"table-container","body":[{"node":"table","body":[{"node":"tbody","body":[{"node":"tr","body":[{"node":"td","body":[{"node":"p","body":[{"node":"variable","body":[{"node":"text","body":"Final drive type"}]}]}]},{"node":"td","body":[{"node":"p","body":[{"node":"variable","body":[{"node":"text","body":"Chain"}]}]}]}]},{"node":"text","body":" \r\n"},{"node":"tr","body":[{"node":"td","body":[{"node":"p","body":[{"node":"variable","body":[{"node":"text","body":"Chain length (20 links)"}]}]}]},{"node":"td","body":[{"node":"p","body":[{"node":"variable","body":[{"node":"text","body":"323.7 mm"}]}]}]}]},{"node":"text","body":" \r\n"},{"node":"tr","body":[{"node":"td","body":[{"node":"p","body":[{"node":"variable","body":[{"node":"text","body":"Chain adjustment"}]}]}]},{"node":"td","body":[{"node":"p","body":[{"node":"variable","body":[{"node":"text","body":"20-25 mm"}]}]}]}]},{"node":"text","body":" \r\n"},{"node":"tr","body":[{"node":"td","body":[{"node":"p","body":[{"node":"variable","body":[{"node":"text","body":"Chain lubrication"}]}]}]},{"node":"td","body":[{"node":"p","body":[{"node":"variable","body":[{"node":"text","body":"Triumph Performance chain lubricant"}]}]}]}]},{"node":"text","body":" "}]}],"widths":"35 65","widthType":"fixed","type":"fixed"}],"type":"framed"},{"node":"text","body":" \r\n"},{"node":"subheading","body":[{"node":"text","body":"Fuel System and Engine Management"}]},{"node":"text","body":" \r\n"},{"node":"table-container","body":[{"node":"table","body":[{"node":"tbody","body":[{"node":"tr","body":[{"node":"td","body":[{"node":"p","body":[{"node":"variable","body":[{"node":"text","body":"Spark plug type"}]}]}]},{"node":"td","body":[{"node":"p","body":[{"node":"variable","body":[{"node":"text","body":"Bosch VR6NEU"}]}]}]}]},{"node":"text","body":" \r\n"},{"node":"tr","body":[{"node":"td","body":[{"node":"p","body":[{"node":"variable","body":[{"node":"text","body":"Spark plug gap"}]}]}]},{"node":"td","body":[{"node":"p","body":[{"node":"variable","body":[{"node":"text","body":"0.9 mm +0.00/-0.1mm"}]}]}]}]},{"node":"text","body":" "}]}],"widths":"35 65","widthType":"fixed","type":"fixed"}],"type":"framed"},{"node":"text","body":" \r\n"},{"node":"subheading","body":[{"node":"text","body":"General"}]},{"node":"text","body":" \r\n"},{"node":"table-container","body":[{"node":"table","body":[{"node":"tbody","body":[{"node":"tr","body":[{"node":"td","body":[{"node":"p","body":[{"node":"variable","body":[{"node":"text","body":"Bank angle indicator length - service limit"}]}]}]},{"node":"td","body":[{"node":"p","body":[{"node":"variable","body":[{"node":"text","body":"5 mm"}]}]}]}]},{"node":"text","body":" "}]}],"widths":"35 65","widthType":"fixed","type":"fixed"}],"type":"framed"},{"node":"text","body":" \r\n"},{"node":"subheading","body":[{"node":"text","body":"Lubrication"}]},{"node":"text","body":" \r\n"},{"node":"table-container","body":[{"node":"table","body":[{"node":"tbody","body":[{"node":"tr","body":[{"node":"td","body":[{"node":"p","body":[{"node":"variable","body":[{"node":"text","body":"Engine oil viscosity"}]},{"node":"text","body":" and "},{"node":"variable","body":[{"node":"text","body":"Recommended oil approval rating"}]}]}]},{"node":"td","body":[{"node":"p","body":[{"node":"variable","body":[{"node":"text","body":"10W/50"}]},{"node":"text","body":", "},{"node":"variable","body":[{"node":"text","body":"API SN (or higher) and JASO MA2"}]}]}]}]},{"node":"text","body":" \r\n"},{"node":"tr","body":[{"node":"td","body":[{"node":"p","body":[{"node":"variable","body":[{"node":"text","body":"Engine oil type"}]}]}]},{"node":"td","body":[{"node":"p","body":[{"node":"variable","body":[{"node":"text","body":"Fully synthetic, Triumph Performance fully synthetic engine oil is recommended"}]}]}]}]},{"node":"text","body":" \r\n"},{"node":"tr","body":[{"node":"td","body":[{"node":"p","body":[{"node":"variable","body":[{"node":"text","body":"Oil Capacity (wet fill including oil filter)"}]}]}]},{"node":"td","body":[{"node":"p","body":[{"node":"variable","body":[{"node":"text","body":"2 litres"}]}]}]}]},{"node":"text","body":" "}]}],"widths":"35 65","widthType":"fixed","type":"fixed"}],"type":"framed"},{"node":"text","body":" \r\n"},{"node":"subheading","body":[{"node":"text","body":"Steering and Suspension"}]},{"node":"text","body":" \r\n"},{"node":"table-container","body":[{"node":"table","body":[{"node":"tbody","body":[{"node":"tr","body":[{"node":"td","body":[{"node":"p","body":[{"node":"variable","body":[{"node":"text","body":"Fork oil grade"}]}]}]},{"node":"td","body":[{"node":"p","body":[{"node":"variable","body":[{"node":"text","body":"2F (ETL Grade)"}]}]}]}]},{"node":"text","body":" \r\n"},{"node":"tr","body":[{"node":"td","body":[{"node":"p","body":[{"node":"variable","body":[{"node":"text","body":"Fork oil volume (Triumph Markets)"}]}]}]},{"node":"td","body":[{"node":"p","body":[{"node":"variable","body":[{"node":"text","body":"MIN 477 ml to MAX 487 ml"}]}]}]}]},{"node":"text","body":" \r\n"},{"node":"tr","body":[{"node":"td","body":[{"node":"p","body":[{"node":"variable","body":[{"node":"text","body":"Fork pull through"}]}]}]},{"node":"td","body":[{"node":"p","body":[{"node":"variable","body":[{"node":"text","body":"39.1 mm"}]}]}]}]},{"node":"text","body":" "}]}],"widths":"35 65","widthType":"fixed","type":"fixed"}],"type":"framed"},{"node":"text","body":" \r\n"},{"node":"subheading","body":[{"node":"text","body":"Wheels and Tyres"}]},{"node":"text","body":" \r\n"},{"node":"table-container","body":[{"node":"table","body":[{"node":"tbody","body":[{"node":"tr","body":[{"node":"td","body":[{"node":"p","body":[{"node":"variable","body":[{"node":"text","body":"Front tyre pressure"}]}]}]},{"node":"td","body":[{"node":"p","body":[{"node":"variable","body":[{"node":"text","body":"2.28 bar (228 kpa/33.0 lb/in²)"}]}]}]}]},{"node":"text","body":" \r\n"},{"node":"tr","body":[{"node":"td","body":[{"node":"p","body":[{"node":"variable","body":[{"node":"text","body":"Rear tyre pressure"}]}]}]},{"node":"td","body":[{"node":"p","body":[{"node":"variable","body":[{"node":"text","body":"1.79 bar (179 kpa/26.0 lb/in²)"}]}]}]}]},{"node":"text","body":" "}]}],"widths":"35 65","widthType":"fixed","type":"fixed"}],"type":"framed"}],"metadata":{"MarketsTaxonomyLink":"All"},"type":"TextModule"},{"node":"textmodule","body":[{"node":"title","body":[{"node":"text","body":"Scheduled Maintenance - Torques - T*1"}]},{"node":"text","body":"\r\n"},{"node":"subheading","body":[{"node":"text","body":"Brakes"}]},{"node":"text","body":" \r\n"},{"node":"table-container","body":[{"node":"table","body":[{"node":"tbody","body":[{"node":"tr","body":[{"node":"td","body":[{"node":"p","body":[{"node":"variable","body":[{"node":"text","body":"Front caliper bleed screw"}]}]}]},{"node":"td","body":[{"node":"p","body":[{"node":"variable","body":[{"node":"text","body":"8.5 Nm"}]}],"type":"p_table_c"}]},{"node":"td","body":[]}]},{"node":"text","body":" \r\n"},{"node":"tr","body":[{"node":"td","body":[{"node":"p","body":[{"node":"variable","body":[{"node":"text","body":"Front Brake caliper hose union"}]}]}]},{"node":"td","body":[{"node":"p","body":[{"node":"variable","body":[{"node":"text","body":"24.5 Nm"}]}],"type":"p_table_c"}]},{"node":"td","body":[{"node":"p","body":[{"node":"variable","body":[{"node":"text","body":"Fit new sealing washer(s)"}]}]}]}]},{"node":"text","body":" \r\n"},{"node":"tr","body":[{"node":"td","body":[{"node":"p","body":[{"node":"variable","body":[{"node":"text","body":"Brake disc to wheel"}]}]}]},{"node":"td","body":[{"node":"p","body":[{"node":"variable","body":[{"node":"text","body":"30 Nm"}]}],"type":"p_table_c"}]},{"node":"td","body":[{"node":"p","body":[{"node":"text","body":"See Front Brake Caliper - Installation"}]}]}]},{"node":"text","body":" \r\n"},{"node":"tr","body":[{"node":"td","body":[{"node":"p","body":[{"node":"variable","body":[{"node":"text","body":"Front brake caliper to front fork (Stage 1)"}]}]}]},{"node":"td","body":[{"node":"p","body":[{"node":"variable","body":[{"node":"text","body":"15 Nm"}]}],"type":"p_table_c"}]},{"node":"td","body":[{"node":"p","body":[{"node":"text","body":"See Front Brake Caliper - Installation"}]}]}]},{"node":"text","body":" \r\n"},{"node":"tr","body":[{"node":"td","body":[{"node":"p","body":[{"node":"variable","body":[{"node":"text","body":"Rear brake caliper bleed screw"}]}]}]},{"node":"td","body":[{"node":"p","body":[{"node":"variable","body":[{"node":"text","body":"14 Nm"}]}],"type":"p_table_c"}]},{"node":"td","body":[]}]},{"node":"text","body":" \r\n"},{"node":"tr","body":[{"node":"td","body":[{"node":"p","body":[{"node":"variable","body":[{"node":"text","body":"Rear brake caliper hose union"}]}]}]},{"node":"td","body":[{"node":"p","body":[{"node":"variable","body":[{"node":"text","body":"24.5 Nm"}]}],"type":"p_table_c"}]},{"node":"td","body":[{"node":"p","body":[{"node":"variable","body":[{"node":"text","body":"Fit new sealing washer(s)"}]}]},{"node":"text","body":" \r\n"},{"node":"p","body":[{"node":"text","body":"See Rear Brake Caliper - Installation"}]}]}]},{"node":"text","body":" "}]}],"widths":"33.33 20 46.66","widthType":"fixed","type":"fixed"}],"type":"framed"},{"node":"text","body":" \r\n"},{"node":"subheading","body":[{"node":"text","body":"Cooling System"}]},{"node":"text","body":" \r\n"},{"node":"table-container","body":[{"node":"table","body":[{"node":"tbody","body":[{"node":"tr","body":[{"node":"td","body":[{"node":"p","body":[{"node":"variable","body":[{"node":"text","body":"Coolant bleed screw in radiator"}]}]}]},{"node":"td","body":[{"node":"p","body":[{"node":"variable","body":[{"node":"text","body":"2.2 Nm"}]}],"type":"p_table_c"}]},{"node":"td","body":[{"node":"p","body":[{"node":"variable","body":[{"node":"text","body":"Fit new sealing washer(s)"}]}]}]}]},{"node":"text","body":" \r\n"},{"node":"tr","body":[{"node":"td","body":[{"node":"p","body":[{"node":"variable","body":[{"node":"text","body":"Coolant pump drain screw"}]}]}]},{"node":"td","body":[{"node":"p","body":[{"node":"variable","body":[{"node":"text","body":"10.8 Nm"}]}],"type":"p_table_c"}]},{"node":"td","body":[{"node":"p","body":[{"node":"variable","body":[{"node":"text","body":"Fit new sealing washer(s)"}]}]}]}]}]}],"widths":"33.33 33.33 33.33","widthType":"fixed","type":"fixed"}],"type":"framed"},{"node":"text","body":" \r\n"},{"node":"subheading","body":[{"node":"text","body":"Electrical"}]},{"node":"text","body":" \r\n"},{"node":"table-container","body":[{"node":"table","body":[{"node":"tbody","body":[{"node":"tr","body":[{"node":"td","body":[{"node":"p","body":[{"node":"variable","body":[{"node":"text","body":"Battery terminal fixings"}]}]}]},{"node":"td","body":[{"node":"p","body":[{"node":"variable","body":[{"node":"text","body":"4.5 Nm"}]}],"type":"p_table_c"}]},{"node":"td","body":[]}]},{"node":"text","body":" "}]}],"widths":"33.33 20 46.66","widthType":"fixed","type":"fixed"}],"type":"framed"},{"node":"text","body":" \r\n"},{"node":"subheading","body":[{"node":"text","body":"Engine"}]},{"node":"text","body":" \r\n"},{"node":"table-container","body":[{"node":"table","body":[{"node":"tbody","body":[{"node":"tr","body":[{"node":"td","body":[{"node":"p","body":[{"node":"variable","body":[{"node":"text","body":"Camshaft cover"}]}]}]},{"node":"td","body":[{"node":"p","body":[{"node":"variable","body":[{"node":"text","body":"11 Nm"}]}],"type":"p_table_c"}]},{"node":"td","body":[{"node":"p","body":[{"node":"text","body":"For tightening sequence, see Camshaft Cover - Installation"}]}]}]},{"node":"text","body":" \r\n"},{"node":"tr","body":[{"node":"td","body":[{"node":"p","body":[{"node":"variable","body":[{"node":"text","body":"Clutch lever pivot bolt lock nut"}]}]}]},{"node":"td","body":[{"node":"p","body":[{"node":"variable","body":[{"node":"text","body":"1.8 Nm"}]}],"type":"p_table_c"}]},{"node":"td","body":[]}]},{"node":"text","body":" \r\n"},{"node":"tr","body":[{"node":"td","body":[{"node":"p","body":[{"node":"variable","body":[{"node":"text","body":"Clutch lever pivot bolt"}]}]}]},{"node":"td","body":[{"node":"p","body":[{"node":"variable","body":[{"node":"text","body":"3.5 Nm"}]}],"type":"p_table_c"}]},{"node":"td","body":[]}]},{"node":"text","body":" \r\n"},{"node":"tr","body":[{"node":"td","body":[{"node":"p","body":[{"node":"variable","body":[{"node":"text","body":"Front left cover finisher"}]}]}]},{"node":"td","body":[{"node":"p","body":[{"node":"variable","body":[{"node":"text","body":"7 Nm"}]}],"type":"p_table_c"}]},{"node":"td","body":[{"node":"p","body":[{"node":"text","body":"For tightening sequence, see Crankshaft End Cover - Installation"}]}]}]},{"node":"text","body":" \r\n"},{"node":"tr","body":[{"node":"td","body":[{"node":"p","body":[{"node":"variable","body":[{"node":"text","body":"Front left cover to crankcase"}]}]}]},{"node":"td","body":[{"node":"p","body":[{"node":"variable","body":[{"node":"text","body":"11 Nm"}]}],"type":"p_table_c"}]},{"node":"td","body":[]}]},{"node":"text","body":" "}]}],"widths":"33.33 20 46.66","widthType":"fixed","type":"fixed"}],"type":"framed"},{"node":"text","body":" \r\n"},{"node":"subheading","body":[{"node":"text","body":"Final Drive"}]},{"node":"text","body":" \r\n"},{"node":"table-container","body":[{"node":"table","body":[{"node":"tbody","body":[{"node":"tr","body":[{"node":"td","body":[{"node":"p","body":[{"node":"variable","body":[{"node":"text","body":"Chain rubbing strip to swinging arm"}]}]}]},{"node":"td","body":[{"node":"p","body":[{"node":"variable","body":[{"node":"text","body":"8.8 Nm"}]}],"type":"p_table_c"}]},{"node":"td","body":[]}]},{"node":"text","body":" \r\n"},{"node":"tr","body":[{"node":"td","body":[{"node":"p","body":[{"node":"variable","body":[{"node":"text","body":"Drive chain adjuster locknut"}]}]}]},{"node":"td","body":[{"node":"p","body":[{"node":"variable","body":[{"node":"text","body":"11 Nm"}]}],"type":"p_table_c"}]},{"node":"td","body":[]}]},{"node":"text","body":" \r\n"},{"node":"tr","body":[{"node":"td","body":[{"node":"p","body":[{"node":"variable","body":[{"node":"text","body":"Chain guard"}]}]}]},{"node":"td","body":[{"node":"p","body":[{"node":"variable","body":[{"node":"text","body":"9 Nm"}]}],"type":"p_table_c"}]},{"node":"td","body":[]}]},{"node":"text","body":" "}]}],"widths":"33.33 20 46.66","widthType":"fixed","type":"fixed"}],"type":"framed"},{"node":"text","body":" \r\n"},{"node":"subheading","body":[{"node":"text","body":"Fuel System and Engine Management"}]},{"node":"text","body":" \r\n"},{"node":"table-container","body":[{"node":"table","body":[{"node":"tbody","body":[{"node":"tr","body":[{"node":"td","body":[{"node":"p","body":[{"node":"variable","body":[{"node":"text","body":"TMAP sensor"}]}]}]},{"node":"td","body":[{"node":"p","body":[{"node":"variable","body":[{"node":"text","body":"5 Nm"}]}],"type":"p_table_c"}]},{"node":"td","body":[]}]},{"node":"text","body":" \r\n"},{"node":"tr","body":[{"node":"td","body":[{"node":"p","body":[{"node":"variable","body":[{"node":"text","body":"Air filter cover"}]}]}]},{"node":"td","body":[{"node":"p","body":[{"node":"variable","body":[{"node":"text","body":"2.7 Nm"}]}],"type":"p_table_c"}]},{"node":"td","body":[]}]},{"node":"text","body":" \r\n"},{"node":"tr","body":[{"node":"td","body":[{"node":"p","body":[{"node":"variable","body":[{"node":"text","body":"Purge valve to bracket"}]}]}]},{"node":"td","body":[{"node":"p","body":[{"node":"variable","body":[{"node":"text","body":"9 Nm"}]}],"type":"p_table_c"}]},{"node":"td","body":[]}]},{"node":"text","body":" \r\n"},{"node":"tr","body":[{"node":"td","body":[{"node":"p","body":[{"node":"variable","body":[{"node":"text","body":"Oxygen sensor"}]}]}]},{"node":"td","body":[{"node":"p","body":[{"node":"variable","body":[{"node":"text","body":"17 Nm"}]}],"type":"p_table_c"}]},{"node":"td","body":[]}]},{"node":"text","body":" \r\n"},{"node":"tr","body":[{"node":"td","body":[{"node":"p","body":[{"node":"variable","body":[{"node":"text","body":"Fuel tank to frame rear fixing"}]}]}]},{"node":"td","body":[{"node":"p","body":[{"node":"variable","body":[{"node":"text","body":"11 Nm"}]}],"type":"p_table_c"}]},{"node":"td","body":[]}]},{"node":"text","body":" \r\n"},{"node":"tr","body":[{"node":"td","body":[{"node":"p","body":[{"node":"variable","body":[{"node":"text","body":"MAP sensor"}]}]}]},{"node":"td","body":[{"node":"p","body":[{"node":"variable","body":[{"node":"text","body":"5 Nm"}]}],"type":"p_table_c"}]},{"node":"td","body":[]}]},{"node":"text","body":" \r\n"},{"node":"tr","body":[{"node":"td","body":[{"node":"p","body":[{"node":"variable","body":[{"node":"text","body":"Spark plug"}]}]}]},{"node":"td","body":[{"node":"p","body":[{"node":"variable","body":[{"node":"text","body":"17 Nm"}]}],"type":"p_table_c"}]},{"node":"td","body":[]}]},{"node":"text","body":" "}]}],"widths":"33.33 20 46.66","widthType":"fixed","type":"fixed"}],"type":"framed"},{"node":"text","body":" \r\n"},{"node":"subheading","body":[{"node":"text","body":"General"}]},{"node":"text","body":" \r\n"},{"node":"textmodule","body":[{"node":"title","body":[{"node":"text","body":"Mudguards - TD1"}]},{"node":"text","body":"\r\n"},{"node":"table-container","body":[{"node":"table","body":[{"node":"tbody","body":[{"node":"tr","body":[{"node":"td","body":[{"node":"p","body":[{"node":"variable","body":[{"node":"text","body":"Front mudguard fork protector to front fork bracket"}]}]}]},{"node":"td","body":[{"node":"p","body":[{"node":"variable","body":[{"node":"text","body":"4.5 Nm"}]}],"type":"p_table_c"}]}]},{"node":"text","body":" \r\n"},{"node":"tr","body":[{"node":"td","body":[{"node":"p","body":[{"node":"variable","body":[{"node":"text","body":"Front mudguard rear brace to fork protector assembly"}]}]}]},{"node":"td","body":[{"node":"p","body":[{"node":"variable","body":[{"node":"text","body":"6 Nm"}]}],"type":"p_table_c"}]}]},{"node":"text","body":" \r\n"},{"node":"tr","body":[{"node":"td","body":[{"node":"p","body":[{"node":"variable","body":[{"node":"text","body":"Front mudguard to front brace (left and right)"}]}]}]},{"node":"td","body":[{"node":"p","body":[{"node":"variable","body":[{"node":"text","body":"3.5 Nm"}]}],"type":"p_table_c"}]}]},{"node":"text","body":" "}]}],"widths":"50 50","widthType":"fixed","type":"fixed"}],"type":"framed"}],"metadata":{"ModelsTaxonomyLink":"TD1","MarketsTaxonomyLink":"All"},"type":"TextModule"},{"node":"text","body":" \r\n \r\n"},{"node":"subheading","body":[{"node":"text","body":"Lubrication"}]},{"node":"text","body":" \r\n"},{"node":"table-container","body":[{"node":"table","body":[{"node":"tbody","body":[{"node":"tr","body":[{"node":"td","body":[{"node":"p","body":[{"node":"variable","body":[{"node":"text","body":"Evacuation strainer plug"}]}]}]},{"node":"td","body":[{"node":"p","body":[{"node":"variable","body":[{"node":"text","body":"10 Nm"}]}],"type":"p_table_c"}]},{"node":"td","body":[{"node":"p","body":[{"node":"variable","body":[{"node":"text","body":"Fit new O-ring"}]}]}]}]},{"node":"text","body":" \r\n"},{"node":"tr","body":[{"node":"td","body":[{"node":"p","body":[{"node":"variable","body":[{"node":"text","body":"Oil filter cover fixings"}]}]}]},{"node":"td","body":[{"node":"p","body":[{"node":"variable","body":[{"node":"text","body":"11 Nm"}]}],"type":"p_table_c"}]},{"node":"td","body":[{"node":"p","body":[{"node":"variable","body":[{"node":"text","body":"Fit new O-ring"}]}]}]}]},{"node":"text","body":" \r\n"},{"node":"tr","body":[{"node":"td","body":[{"node":"p","body":[{"node":"variable","body":[{"node":"text","body":"Engine oil drain plug (strainer)"}]}]}]},{"node":"td","body":[{"node":"p","body":[{"node":"variable","body":[{"node":"text","body":"13 Nm"}]}],"type":"p_table_c"}]},{"node":"td","body":[{"node":"p","body":[{"node":"variable","body":[{"node":"text","body":"Fit new O-ring"}]}]}]}]},{"node":"text","body":" "}]}],"widths":"33.33 20 46.66","widthType":"fixed","type":"fixed"}],"type":"framed"},{"node":"text","body":" \r\n"},{"node":"subheading","body":[{"node":"text","body":"Steering and Suspension"}]},{"node":"text","body":" \r\n \r\n"},{"node":"subheading","body":[{"node":"text","body":"Wheels and Tyres"}]},{"node":"text","body":" \r\n"},{"node":"table-container","body":[{"node":"table","body":[{"node":"tbody","body":[{"node":"tr","body":[{"node":"td","body":[{"node":"p","body":[{"node":"variable","body":[{"node":"text","body":"Front wheel spindle bolt"}]}]}]},{"node":"td","body":[{"node":"p","body":[{"node":"variable","body":[{"node":"text","body":"54 Nm"}]}],"type":"p_table_c"}]},{"node":"td","body":[]}]},{"node":"text","body":" \r\n"},{"node":"tr","body":[{"node":"td","body":[{"node":"p","body":[{"node":"variable","body":[{"node":"text","body":"Fork to wheel spindle pinch bolts"}]}]}]},{"node":"td","body":[{"node":"p","body":[{"node":"variable","body":[{"node":"text","body":"12 Nm"}]}],"type":"p_table_c"}]},{"node":"td","body":[]}]},{"node":"text","body":" \r\n"},{"node":"tr","body":[{"node":"td","body":[{"node":"p","body":[{"node":"variable","body":[{"node":"text","body":"Rear wheel spindle lock nut"}]}]}]},{"node":"td","body":[{"node":"p","body":[{"node":"variable","body":[{"node":"text","body":"98 Nm"}]}],"type":"p_table_c"}]},{"node":"td","body":[{"node":"p","body":[{"node":"text","body":"Hold the spindle, tighten the nut"}]}]}]},{"node":"text","body":" "}]}],"widths":"33.33 20 46.66","widthType":"fixed","type":"fixed"}],"type":"framed"}],"metadata":{"MarketsTaxonomyLink":"All"},"type":"TextModule"}],"ancestors":[],"parent":null,"lastUpdate":"2024-02-12T09:41:10.000Z","metadata":{"markets":["All"],"_id":"65dcbb0cc85ec2286ffa012d"},"search":["Service Data Sheet","This Service Data Sheet is a quick reference guide for motorcycle service.","Always refer to the Service Manual for detailed data related to routine maintenance and adjustment.","Incorrect maintenance or adjustment may cause one or more parts of the motorcycle to malfunction. ","A malfunctioning motorcycle may lead to loss of motorcycle control which could result in serious injury or death.","Brakes","Front brake disc maximum run-out","0.25 mm","Rear brake disc maximum run-out","0.25 mm","Front brake disc thickness - service limit","4.5 mm","Rear brake disc thickness - service limit","4.0 mm","Recommended brake fluid","Triumph Performance DOT 4 brake fluid","Front brake pad lining minimum thickness","1 mm","Rear brake pad lining minimum thickness","0.8 mm ","Cooling System","Cooling System Capacity","1.2 liters","Engine","Valve gap (clearance)","Inlet: 0.07 - 0.13","Valve gap (clearance)","Exhaust: 0.12 - 0.18","Final Drive","Final drive type","Chain","Chain length (20 links)","323.7 mm","Chain adjustment","20-25 mm","Chain lubrication","Triumph Performance chain lubricant","Fuel System and Engine Management","Spark plug type","Bosch VR6NEU","Spark plug gap","0.9 mm +0.00/-0.1mm","General","Bank angle indicator length - service limit","5 mm","Lubrication","Engine oil viscosity"," and ","Recommended oil approval rating","10W/50",", ","API SN (or higher) and JASO MA2","Engine oil type","Fully synthetic, Triumph Performance fully synthetic engine oil is recommended","Oil Capacity (wet fill including oil filter)","2 litres","Steering and Suspension","Fork oil grade","2F (ETL Grade)","Fork oil volume (Triumph Markets)","MIN 477 ml to MAX 487 ml","Fork pull through","39.1 mm","Wheels and Tyres","Front tyre pressure","2.28 bar (228 kpa/33.0 lb/in²)","Rear tyre pressure","1.79 bar (179 kpa/26.0 lb/in²)","Brakes","Front caliper bleed screw","8.5 Nm","Front Brake caliper hose union","24.5 Nm","Fit new sealing washer(s)","Brake disc to wheel","30 Nm","See Front Brake Caliper - Installation","Front brake caliper to front fork (Stage 1)","15 Nm","See Front Brake Caliper - Installation","Rear brake caliper bleed screw","14 Nm","Rear brake caliper hose union","24.5 Nm","Fit new sealing washer(s)","See Rear Brake Caliper - Installation","Cooling System","Coolant bleed screw in radiator","2.2 Nm","Fit new sealing washer(s)","Coolant pump drain screw","10.8 Nm","Fit new sealing washer(s)","Electrical","Battery terminal fixings","4.5 Nm","Engine","Camshaft cover","11 Nm","For tightening sequence, see Camshaft Cover - Installation","Clutch lever pivot bolt lock nut","1.8 Nm","Clutch lever pivot bolt","3.5 Nm","Front left cover finisher","7 Nm","For tightening sequence, see Crankshaft End Cover - Installation","Front left cover to crankcase","11 Nm","Final Drive","Chain rubbing strip to swinging arm","8.8 Nm","Drive chain adjuster locknut","11 Nm","Chain guard","9 Nm","Fuel System and Engine Management","TMAP sensor","5 Nm","Air filter cover","2.7 Nm","Purge valve to bracket","9 Nm","Oxygen sensor","17 Nm","Fuel tank to frame rear fixing","11 Nm","MAP sensor","5 Nm","Spark plug","17 Nm","General","Front mudguard fork protector to front fork bracket","4.5 Nm","Front mudguard rear brace to fork protector assembly","6 Nm","Front mudguard to front brace (left and right)","3.5 Nm","Lubrication","Evacuation strainer plug","10 Nm","Fit new O-ring","Oil filter cover fixings","11 Nm","Fit new O-ring","Engine oil drain plug (strainer)","13 Nm","Fit new O-ring","Steering and Suspension","Wheels and Tyres","Front wheel spindle bolt","54 Nm","Fork to wheel spindle pinch bolts","12 Nm","Rear wheel spindle lock nut","98 Nm","Hold the spindle, tighten the nut"],"viewCount":26,"infoType":"InfoType04","views":[{"createdBy":"638abb7817b2aed68a1ba967","createdAt":"2024-01-18T14:47:25.059Z","_id":"65dd46f84e7861d9b795998f"},{"createdBy":"65b915516cc2da92004919a0","createdAt":"2024-02-14T19:29:53.177Z","_id":"65de4349e919dffe56329567"},{"createdBy":"65a4fed1c48c0387320763fd","createdAt":"2024-01-18T14:47:25.427Z","_id":"65defe828dab24d43a8b70d2"},{"createdBy":"65a0dc5467492b96b32b479e","createdAt":"2024-01-18T23:18:14.877Z","_id":"65e02fe2c20ee762071cacf9"},{"createdBy":"65a4eba3a1ab9d9d227dc444","createdAt":"2024-02-05T17:31:52.169Z","_id":"65e1878e3baf3f48858a9851"},{"createdBy":"65add6df6cc2da9200e52797","createdAt":"2024-02-14T22:45:46.509Z","_id":"65e6c5acc85ec2286f73a5c1"},{"createdBy":"65d40d74c85ec2286f93be11","createdAt":"2024-02-14T19:29:53.177Z","_id":"65e7a6fae919dffe56a449a8"},{"createdBy":"65b2a2e9c20ee7620779c2ed","createdAt":"2024-01-19T17:36:36.155Z","_id":"65e88ab3df0ba9fe7ec1ab73"},{"createdBy":"65bd6b504e7861d9b7708271","createdAt":"2024-01-18T23:18:14.877Z","_id":"65e8c596c20ee7620788966d"},{"createdBy":"65d70ab46cc2da9200a2bcf7","createdAt":"2024-03-07T11:20:57.573Z","_id":"65eaf2d9fb41b509124d0d40"},{"createdBy":"65a14f4c71f5d4e1770ce5b8","createdAt":"2024-03-07T11:20:57.650Z","_id":"65eaf9fd05c55dfddbb4b24e"},{"createdBy":"65a14f4c71f5d4e1770ce5b8","createdAt":"2024-03-07T11:20:57.537Z","_id":"65eaff9a1de51b84d4eb4de8"},{"createdBy":"65a7a379a1ab9d9d22993737","createdAt":"2024-03-07T11:20:57.558Z","_id":"65eb1b1f128aa1fbe12cdcf9"},{"createdBy":"65b00807df0ba9fe7e91f379","createdAt":"2024-03-07T11:20:57.573Z","_id":"65eb8224fb41b509125b66a2"},{"createdBy":"65b00807df0ba9fe7e91f379","createdAt":"2024-03-07T11:20:57.650Z","_id":"65ecb6b305c55dfddbca430a"},{"createdBy":"638abb7817b2aed68a1ba967","createdAt":"2024-03-07T11:20:57.650Z","_id":"65ee4fbe05c55dfddbd08b4f"},{"createdBy":"638abb7817b2aed68a1ba967","createdAt":"2024-03-07T11:20:06.332Z","_id":"65ee50a7673a4618e725df44"},{"createdBy":"638abb7817b2aed68a1ba967","createdAt":"2024-03-07T11:20:06.332Z","_id":"65ee5d97673a4618e7267987"},{"createdBy":"65c0c7555ac2160b661e011e","createdAt":"2024-03-07T11:20:57.558Z","_id":"65ef1173128aa1fbe14e52e7"},{"createdBy":"65cddb0d8dab24d43adc165b","createdAt":"2024-03-07T11:20:06.306Z","_id":"65f025dc80382e44e4cf51df"},{"createdBy":"65ba7aeb0cf8b137266ca3f4","createdAt":"2024-03-07T11:20:06.359Z","_id":"65f0cd753766ec727308f82e"},{"createdBy":"65b145ba0cf8b13726184dd0","createdAt":"2024-03-07T11:20:57.537Z","_id":"65f345431de51b84d44ffb51"},{"createdBy":"65b145ba0cf8b13726184dd0","createdAt":"2024-03-07T11:20:57.558Z","_id":"65f34566128aa1fbe1891e1e"},{"createdBy":"65c0c7555ac2160b661e011e","createdAt":"2024-03-07T11:20:06.359Z","_id":"65f89ecc3766ec72737634d1"},{"createdBy":"65c0c7555ac2160b661e011e","createdAt":"2024-03-07T11:20:06.332Z","_id":"65f89ed7673a4618e7ae6c3f"},{"createdBy":"65a27d6467492b96b3397db7","createdAt":"2024-03-07T11:20:06.306Z","_id":"65f9a05080382e44e46af7d3"}],"createdAt":"2024-02-26T16:23:40.454Z","updatedAt":"2024-03-19T14:25:20.933Z","__v":0,"updatedBy":"65a27d6467492b96b3397db7"}