{"_id":"668e4e3d9772673c902ee71a","createdBy":"6099504c693d8c00155df91f","deleted":false,"parentDocument":{"_id":"668e4e279772673c902eb03f","metadata":{"userGroup":[],"docType":{"showInFluidsPortal":false,"showInTyrePortal":false,"_id":"613771844b25a79f6947d0d8","showInHandbookPortal":false},"reference":"","validFrom":"2024-07-09T23:00:00.000Z","applicabilities":[{"vinRanges":[{"start":"AV5527","end":"zzzzzz"}],"engineNumberRanges":[],"modelYears":[{"start":2022,"end":9999}],"products":["PS1"],"markets":[]}],"negativeApplicabilities":[]}},"id":"6145228811","title":"Keyless Ignition Keys","content":[{"node":"title","body":[{"node":"text","body":"Keyless Ignition Keys"}]},{"node":"textmodule","body":[{"node":"title","body":[{"node":"text","body":"Keyless Ignition Keys PB1; PJ1; PJZ; PM1; PR1; PRB; PRC; PS1; PSB; PSC; PWC; PX1; PXB; PXC; PY1; PYB; PYC"}]},{"node":"text","body":"\r\n"},{"node":"p","body":[{"node":"text","body":"The keyless ignition system allows the motorcycle to be started without the use of a mechanical key. There are two keys supplied with the motorcycle. One smart key and one passive key."}]},{"node":"text","body":" \r\n"},{"node":"p","body":[{"node":"text","body":"To turn the motorcycle on, make sure a key is positioned in range of the LF antenna as described below and press either the Power button or Engine Start button on the Engine Start/Stop switch."}]},{"node":"text","body":" \r\n"},{"node":"safety","body":[{"node":"text","body":"\r\n"},{"node":"consequence","body":[{"node":"text","body":"All keys supplied are locked to the keyless ECM. They cannot be used with any other motorcycle or keyless ECM."}]},{"node":"text","body":" \r\n"},{"node":"consequence","body":[{"node":"text","body":"If all keys are lost, misplaced or damaged, then the keyless ECM will need to be replaced. "}]},{"node":"text","body":" \r\n"},{"node":"consequence","body":[{"node":"text","body":"To avoid unnecessary cost and time, make sure that all spare keys are kept in a secure location. "}]},{"node":"text","body":" "}],"severity":"caution","type":"general"},{"node":"text","body":" \r\n"},{"node":"safety","body":[{"node":"text","body":"\r\n"},{"node":"consequence","body":[{"node":"text","body":"An additional smart key can be purchased from your Triumph dealer. However, only three keys can be programmed to the motorcycle. This can be a combination of smart keys and passive keys. "}]},{"node":"text","body":" "}],"severity":"note","type":"notice"},{"node":"text","body":" \r\n"},{"node":"subheading","body":[{"node":"text","body":"Smart Key Operation"}]},{"node":"text","body":" \r\n"},{"node":"p","body":[{"node":"text","body":"The smart key has two modes, active mode and passive mode."}]},{"node":"text","body":" \r\n"},{"node":"p","body":[{"node":"text","body":"A short press on the smart key button shows the current status of the key. The smart key LED will flash:"}]},{"node":"text","body":" \r\n"},{"node":"ul","body":[{"node":"li","body":[{"node":"p","body":[{"node":"text","body":"Green when the key is in active mode."}]}]},{"node":"text","body":" \r\n"},{"node":"li","body":[{"node":"p","body":[{"node":"text","body":"Red when the key is in passive mode."}]}]}],"type":"dash"},{"node":"text","body":" \r\n"},{"node":"p","body":[{"node":"text","body":"To switch modes, press and hold the smart key button until the LED changes colour from green to red or vice versa."}]},{"node":"text","body":" \r\n"},{"node":"p","body":[{"node":"text","body":"In active mode, the smart key must be within (one metre/three feet) of the LF antenna to allow the motorcycle to be powered on and started. If the smart key is out of range of the LF antenna then it will be unresponsive and the keyless ignition cannot be activated."}]},{"node":"text","body":" \r\n"},{"node":"p","body":[{"node":"text","body":"In passive mode (or if the smart key battery is flat) the smart key must be held against the rear LF antenna to allow the motorcycle to be powered on and started (see "},{"node":"link","body":[{"node":"text","body":"Keyless Ignition and Immobiliser Components Location"}],"target-id":"18014404655175435-2","target-base-id":"6145693451"},{"node":"text","body":")."}]},{"node":"text","body":" \r\n"},{"node":"image-container","body":[{"node":"img","body":[],"href":"6145429899__Web.svg","id":"6145429899","name":"Smart-Key_P Series_ckdx_1","type":"svg"},{"node":"text","body":" \r\n"},{"node":"table-container","body":[{"node":"table","body":[{"node":"tbody","body":[{"node":"tr","body":[{"node":"td","body":[{"node":"p","body":[{"node":"text","body":"Smart Key"}],"type":"p_table_l"}]},{"node":"text","body":" "}]},{"node":"text","body":" "}]}],"widths":"100","widthType":"fixed","type":"fixed"}],"type":"legend"}],"type":"img_fixed_column"},{"node":"text","body":" \r\n"},{"node":"subheading","body":[{"node":"text","body":"Passive Key Operation"}]},{"node":"text","body":" \r\n"},{"node":"p","body":[{"node":"text","body":"Passive keys must be held against the rear LF antenna to allow the motorcycle to be powered on and started."}]},{"node":"text","body":" \r\n"},{"node":"image-container","body":[{"node":"img","body":[],"href":"6145435659__Web.svg","id":"6145435659","name":"Passive-Key_P_Series_ckdx_2","type":"svg"},{"node":"text","body":" \r\n"},{"node":"table-container","body":[{"node":"table","body":[{"node":"tbody","body":[{"node":"tr","body":[{"node":"td","body":[{"node":"p","body":[{"node":"text","body":"Passive Key"}],"type":"p_table_l"}]},{"node":"text","body":" "}]},{"node":"text","body":" "}]}],"widths":"100","widthType":"fixed","type":"fixed"}],"type":"legend"}],"type":"img_fixed_column"},{"node":"text","body":" "},{"node":"image","body":[],"type":"svg"},{"node":"image","body":[],"type":"svg"}],"metadata":{"ModelsTaxonomyLink":"PWC; PYB; PXB; PSB; PRB; PJZ; PYC; PXC; PSC; PRC; PY1; PX1; PS1; PR1; PM1; PJ1; PB1","MarketsTaxonomyLink":"All"},"type":"TextModule"},{"node":"image","body":[],"type":"svg"},{"node":"image","body":[],"type":"svg"}],"ancestors":["6213660555","6568470923"],"parent":"6568470923","lastUpdate":"2022-01-20T11:59:50.000Z","metadata":{"markets":["All"],"_id":"668e4e3d9772673c902ee71b"},"search":["Keyless Ignition Keys","The keyless ignition system allows the motorcycle to be started without the use of a mechanical key. There are two keys supplied with the motorcycle. One smart key and one passive key.","To turn the motorcycle on, make sure a key is positioned in range of the LF antenna as described below and press either the Power button or Engine Start button on the Engine Start/Stop switch.","All keys supplied are locked to the keyless ECM. They cannot be used with any other motorcycle or keyless ECM.","If all keys are lost, misplaced or damaged, then the keyless ECM will need to be replaced. ","To avoid unnecessary cost and time, make sure that all spare keys are kept in a secure location. ","An additional smart key can be purchased from your Triumph dealer. However, only three keys can be programmed to the motorcycle. This can be a combination of smart keys and passive keys. ","Smart Key Operation","The smart key has two modes, active mode and passive mode.","A short press on the smart key button shows the current status of the key. The smart key LED will flash:","Green when the key is in active mode.","Red when the key is in passive mode.","To switch modes, press and hold the smart key button until the LED changes colour from green to red or vice versa.","In active mode, the smart key must be within (one metre/three feet) of the LF antenna to allow the motorcycle to be powered on and started. If the smart key is out of range of the LF antenna then it will be unresponsive and the keyless ignition cannot be activated.","In passive mode (or if the smart key battery is flat) the smart key must be held against the rear LF antenna to allow the motorcycle to be powered on and started (see ","Keyless Ignition and Immobiliser Components Location",").","Smart Key","Passive Key Operation","Passive keys must be held against the rear LF antenna to allow the motorcycle to be powered on and started.","Passive Key"],"viewCount":0,"infoType":"InfoType02","createdAt":"2024-07-10T09:02:53.696Z","updatedAt":"2024-07-10T09:02:53.696Z","__v":0}