{"_id":"6666f0b4bfd27a35c501ca26","createdBy":"6099504c693d8c00155df91f","deleted":false,"parentDocument":{"_id":"6666f0a9bfd27a35c501a18b","metadata":{"userGroup":[],"docType":{"showInFluidsPortal":false,"showInTyrePortal":false,"_id":"613771844b25a79f6947d0d8","showInHandbookPortal":false},"reference":"","validFrom":"2024-06-09T23:00:00.000Z","applicabilities":[{"vinRanges":[{"start":"731919","end":"917475"}],"engineNumberRanges":[],"modelYears":[{"start":2016,"end":2019}],"products":["DP"],"markets":[]}],"negativeApplicabilities":[]}},"id":"408674699","title":"Rear Brake Pads - Removal","content":[{"node":"title","body":[{"node":"text","body":"Rear Brake Pads - Removal"}]},{"node":"textmodule","body":[{"node":"title","body":[{"node":"text","body":"Warning - Stabilise Motorcycle"}]},{"node":"safety","body":[{"node":"text","body":"\r\n\r\n\r\n\r\n"},{"node":"consequence","body":[{"node":"text","body":"Before starting work, ensure the motorcycle is stabilised and adequately supported. This will help prevent it from falling and causing injury to the operator or damage to the motorcycle."}]},{"node":"text","body":"\r\n\r\n\r\n"}],"severity":"warning","type":"general"}],"metadata":{"MarketsTaxonomyLink":"All"},"type":"TextModule"},{"node":"textmodule","body":[{"node":"title","body":[{"node":"text","body":"Right hand side panels remove all D Series except DC and DV"}]},{"node":"text","body":"\r\n"},{"node":"ul","body":[{"node":"li","body":[{"node":"p","body":[{"node":"text","body":"Remove the right hand side panel (see "},{"node":"link","body":[{"node":"text","body":"Side Panels"}],"target-id":"27021601366611339-1","target-base-id":"3602388363"},{"node":"text","body":")."}]}]}],"type":"dash"},{"node":"text","body":" "}],"metadata":{"ModelsTaxonomyLink":"DP4; D92; DU3; DT3; DP2; DP3; DZ; DBX; DB; DE2; DE; DUY; DU; DPA; DP","MarketsTaxonomyLink":"All"},"type":"TextModule"},{"node":"procedural-instructions","body":[{"node":"instructions","body":[{"node":"instruction","body":[{"node":"text","body":"Loosen the brake pad retaining pins."}]},{"node":"text","body":"\r\n"},{"node":"instruction","body":[{"node":"text","body":"Remove the rear brake caliper mounting fixings and slide the caliper off the brake disc."}]},{"node":"text","body":"\r\n"},{"node":"image-container","body":[{"node":"img","body":[],"href":"18014399380974987__Web.svg","id":"18014399380974987","name":"Rear brake caliper fixings cjff","type":"svg"},{"node":"text","body":"\r\n"},{"node":"table-container","body":[{"node":"table","body":[{"node":"tbody","body":[{"node":"text","body":"\r\n"},{"node":"tr","body":[{"node":"text","body":"\r\n"},{"node":"td","body":[{"node":"ol","body":[{"node":"li","body":[{"node":"p","body":[{"node":"text","body":"Brake pad retaining pins"}],"type":"p_table_l"}]},{"node":"text","body":"\r\n"},{"node":"li","body":[{"node":"p","body":[{"node":"text","body":"Brake caliper mounting fixings"}],"type":"p_table_l"}]}],"type":"1"}]},{"node":"text","body":"\r\n"}]},{"node":"text","body":"\r\n"}]}],"widths":"100","widthType":"fixed","type":"fixed"}],"type":"noframe"}],"type":"img_fixed_column"},{"node":"text","body":"\r\n"},{"node":"instruction","body":[{"node":"text","body":"Remove the brake pad retaining pins."}]},{"node":"text","body":"\r\n"},{"node":"instruction","body":[{"node":"text","body":"Remove the brake pads and the anti-rattle spring."}]},{"node":"text","body":"\r\n"},{"node":"image-container","body":[{"node":"img","body":[],"href":"9007200126239627__Web.svg","id":"9007200126239627","name":"Rear brake pads cjfg","type":"svg"},{"node":"text","body":"\r\n"},{"node":"table-container","body":[{"node":"table","body":[{"node":"tbody","body":[{"node":"text","body":"\r\n"},{"node":"tr","body":[{"node":"text","body":"\r\n"},{"node":"td","body":[{"node":"ol","body":[{"node":"li","body":[{"node":"p","body":[{"node":"text","body":"Brake pad retaining pins"}],"type":"p_table_l"}]},{"node":"text","body":"\r\n"},{"node":"li","body":[{"node":"p","body":[{"node":"text","body":"Brake pads"}],"type":"p_table_l"}]},{"node":"text","body":"\r\n"},{"node":"li","body":[{"node":"p","body":[{"node":"text","body":"Anti-rattle spring"}],"type":"p_table_l"}]}],"type":"1"}]},{"node":"text","body":"\r\n"}]},{"node":"text","body":"\r\n"}]}],"widths":"100","widthType":"fixed","type":"fixed"}],"type":"noframe"}],"type":"img_fixed_column"}]}]},{"node":"image","body":[],"type":"svg"},{"node":"image","body":[],"type":"svg"}],"ancestors":["1342492939","1342898443"],"parent":"1342898443","lastUpdate":"2018-11-22T15:40:43.000Z","metadata":{"products":"DU3; DT3; DP3; DC3; DP2; DC; DPA; DZ; DBX; DB; DUY; DU; DP","markets":["All"],"_id":"6666f0b4bfd27a35c501ca27"},"search":["Rear Brake Pads - Removal","Before starting work, ensure the motorcycle is stabilised and adequately supported. This will help prevent it from falling and causing injury to the operator or damage to the motorcycle.","Remove the right hand side panel (see ","Side Panels",").","Loosen the brake pad retaining pins.","Remove the rear brake caliper mounting fixings and slide the caliper off the brake disc.","Brake pad retaining pins","Brake caliper mounting fixings","Remove the brake pad retaining pins.","Remove the brake pads and the anti-rattle spring.","Brake pad retaining pins","Brake pads","Anti-rattle spring"],"viewCount":0,"infoType":"InfoType05","createdAt":"2024-06-10T12:25:24.524Z","updatedAt":"2024-06-10T12:25:24.524Z","__v":0}