{"_id":"659fe868c48c038732d8b972","createdBy":"6099504c693d8c00155df91f","deleted":false,"metadata":{"userGroup":[],"docType":{"showInFluidsPortal":false,"showInTyrePortal":false,"_id":"61404f5dbb22ca9faa18049e","important":false,"isRecall":false,"active":true,"free":false,"download":false,"print":true,"systemTitle":"Technical Bulletin","title":{"en-GB":"Technical Bulletin","de-DE":"Technical Bulletin","fr-FR":"Bulletin technique","es-ES":"Boletín de novedades técnicas","pt-BR":"Boletim técnico","nl-NL":"Technisch bulletin","sv-SE":"Tekniskt meddelande","fi-FI":"Tekninen tiedote","it-IT":"Bollettino tecnico","en-US":"Technical Bulletin","ar-SA":"النشرة التقنية","cs-CZ":"Technický bulletin","ja-JP":"テクニカルブリテン","th-TH":"จดหมายข่าวทางเทคนิค","zh-CN":"技术通告","es-AR":"Boletín de novedades técnicas"},"showInHandbookPortal":false,"rights":{"print":["6079487d11396806a27a736a","60800a333a3a0272681d6cb8","601db28b756b36c02c98879e","609ba0d5b7e0460015150013"],"download":[]}},"reference":"TB236","validFrom":"2024-01-11T00:00:00.000Z","applicabilities":[{"vinRanges":[],"modelYears":[],"products":["TH1","TD1"],"chassisStart":"","chassisEnd":"","markets":[],"inverse":false,"engineNumberRanges":[]}],"libraryOnly":false,"libraryHidden":false,"negativeApplicabilities":[]},"language":"en-gb","state":"published","toc":[{"title":"Triumph Diagnostic Tool - Autoscan Support","id":"10133803787","children":[],"selectable":true,"metadata":{"custom-meta-ModelsAffected2":"Speed 400, Scrambler 400 X","ModelsTaxonomyLink":"TH1; TD1","MarketsTaxonomyLink":"All"},"key":"10133803787-3","_id":"659fe868c48c038732d8b973"}],"viewCount":551,"title":"Technical Bulletin 236","version":1,"format":"application/json","externalId":"10133801483-en-GB","pending":false,"views":[{"createdAt":"2024-01-12T07:42:24.712Z","createdBy":"65a0c76fc48c038732e697c1","_id":"65a0ed6071f5d4e177058b77"},{"createdAt":"2024-01-12T08:56:13.908Z","createdBy":"65a0fe53c48c038732e8ca07","_id":"65a0fead71f5d4e17707013c"},{"createdAt":"2024-01-12T08:58:14.168Z","createdBy":"65a0fe53c48c038732e8ca07","_id":"65a0ff26a1ab9d9d2260af68"},{"createdAt":"2024-01-12T09:30:45.866Z","createdBy":"65a106bf544c81104f239c47","_id":"65a106c567492b96b32ce008"},{"createdAt":"2024-01-12T09:56:25.774Z","createdBy":"61b21947004d61ee28ee27a4","_id":"65a10cc9a1ab9d9d2262190c"},{"createdAt":"2024-01-12T10:03:55.017Z","createdBy":"61b21947004d61ee28ee27a4","_id":"65a10e8b7db8ed9497654b6d"},{"createdAt":"2024-01-12T10:19:20.720Z","createdBy":"6390844aadf18a9d05554d6c","_id":"65a11228c48c038732ea2296"},{"createdAt":"2024-01-12T10:23:14.147Z","createdBy":"6179697fc61d67deb71952cb","_id":"65a11312c48c038732ea240f"},{"createdAt":"2024-01-12T10:34:11.264Z","createdBy":"65a00e3e7db8ed9497597c2e","_id":"65a115a3c48c038732ea31b6"},{"createdAt":"2024-01-12T11:29:00.368Z","createdBy":"6569defceed410ba1ee84bb7","_id":"65a1227c544c81104f24453c"},{"createdAt":"2024-01-12T12:01:29.680Z","createdBy":"656bbab98e124cc38417a54f","_id":"65a12a1971f5d4e1770a8d7c"},{"createdAt":"2024-01-12T12:07:09.062Z","createdBy":"65a0fe53c48c038732e8ca07","_id":"65a12b6d71f5d4e1770a982e"},{"createdAt":"2024-01-12T12:29:28.047Z","createdBy":"6190ed45fa0527d82131858a","_id":"65a130a8a1ab9d9d2264792b"},{"createdAt":"2024-01-12T12:49:04.018Z","createdBy":"65a134c042a1832687ceeda3","_id":"65a13540c48c038732ec5c08"},{"createdAt":"2024-01-12T13:22:45.699Z","createdBy":"65a13d2171f5d4e1770beee2","_id":"65a13d25d29d587eb7f1d1cd"},{"createdAt":"2024-01-12T13:36:10.553Z","createdBy":"65a13be767492b96b32f0ea6","_id":"65a1404a42a1832687d0b353"},{"createdAt":"2024-01-12T13:36:48.246Z","createdBy":"61a7248cfa0527d82134605d","_id":"65a14070d29d587eb7f1e658"},{"createdAt":"2024-01-12T13:48:44.906Z","createdBy":"6298bda42396ab5dd1419866","_id":"65a1433c67492b96b32f83b3"},{"createdAt":"2024-01-12T14:20:00.423Z","createdBy":"6569defceed410ba1ee84bb7","_id":"65a14a9067492b96b32ff72f"},{"createdAt":"2024-01-12T15:18:09.544Z","createdBy":"65a15817d29d587eb7f420a4","_id":"65a158317db8ed94976a06fe"},{"createdAt":"2024-01-12T15:20:03.775Z","createdBy":"65a1587c544c81104f27c237","_id":"65a158a371f5d4e1770e11ab"},{"createdAt":"2024-01-12T15:21:26.004Z","createdBy":"65a158ee42a1832687d243e9","_id":"65a158f6544c81104f27c5bb"},{"createdAt":"2024-01-12T15:24:44.614Z","createdBy":"637e360f0df94c6c114311bf","_id":"65a159bca1ab9d9d2267808c"},{"createdAt":"2024-01-12T15:25:31.778Z","createdBy":"65a159c242a1832687d25a97","_id":"65a159ebc48c038732efeccc"},{"createdAt":"2024-01-12T15:31:27.020Z","createdBy":"65a15b2071f5d4e1770e5c03","_id":"65a15b4f71f5d4e1770e5c35"},{"createdAt":"2024-01-12T15:31:48.346Z","createdBy":"61925d7013e0ddb05ef21971","_id":"65a15b6467492b96b330a70e"},{"createdAt":"2024-01-12T15:37:15.390Z","createdBy":"61f7b09bd35ee355a3f3e97d","_id":"65a15caba1ab9d9d2267a27b"},{"createdAt":"2024-01-12T15:37:28.782Z","createdBy":"61b07dd573eaedfaf4c4e38a","_id":"65a15cb87db8ed94976b3985"},{"createdAt":"2024-01-12T15:38:58.967Z","createdBy":"618253a7c61d67deb71a0774","_id":"65a15d1267492b96b330ddfb"},{"createdAt":"2024-01-12T15:39:24.763Z","createdBy":"65a01e71544c81104f19c883","_id":"65a15d2ca1ab9d9d2267af33"},{"createdAt":"2024-01-12T15:42:30.868Z","createdBy":"619cdbfbc37675b041b2d7db","_id":"65a15de671f5d4e1770e7e74"},{"createdAt":"2024-01-12T15:44:27.043Z","createdBy":"61925d7013e0ddb05ef21971","_id":"65a15e5bc48c038732f01964"},{"createdAt":"2024-01-12T15:46:13.215Z","createdBy":"65a15ec0d29d587eb7f4f88c","_id":"65a15ec57db8ed94976b5783"},{"createdAt":"2024-01-12T15:47:18.944Z","createdBy":"61925d7013e0ddb05ef21971","_id":"65a15f0671f5d4e1770e8e93"},{"createdAt":"2024-01-12T15:52:53.517Z","createdBy":"64ca52f948044a0422b7e181","_id":"65a16055c48c038732f0b4c8"},{"createdAt":"2024-01-12T15:58:00.526Z","createdBy":"624a9f3bda9535979b500a8c","_id":"65a16188544c81104f28f63f"},{"createdAt":"2024-01-12T15:58:29.529Z","createdBy":"624a9f3bda9535979b500a8c","_id":"65a161a571f5d4e1770ea184"},{"createdAt":"2024-01-12T16:04:23.027Z","createdBy":"65a162d9d29d587eb7f6008f","_id":"65a1630742a1832687d3cdc5"},{"createdAt":"2024-01-12T16:04:32.700Z","createdBy":"618e908934092cb064e5d2bc","_id":"65a1631071f5d4e1770f29c6"},{"createdAt":"2024-01-12T16:14:07.797Z","createdBy":"624ebaa4d85d745cec47e40e","_id":"65a1654fa1ab9d9d2268dafb"},{"createdAt":"2024-01-12T16:15:59.813Z","createdBy":"65a1632bd29d587eb7f6037a","_id":"65a165bfc48c038732f0da4f"},{"createdAt":"2024-01-12T16:18:18.149Z","createdBy":"65a166457db8ed94976ba0b9","_id":"65a1664a71f5d4e1770f31a8"},{"createdAt":"2024-01-12T16:18:28.430Z","createdBy":"65a1628242a1832687d3ca07","_id":"65a16654544c81104f291034"},{"createdAt":"2024-01-12T16:18:56.892Z","createdBy":"65a109cfd29d587eb7ee7042","_id":"65a1667067492b96b33121ce"},{"createdAt":"2024-01-12T16:19:04.725Z","createdBy":"65a16630d29d587eb7f6128d","_id":"65a166787db8ed94976ba132"},{"createdAt":"2024-01-12T16:32:21.206Z","createdBy":"65a167cb544c81104f2982a5","_id":"65a1699571f5d4e1770fd663"},{"createdAt":"2024-01-12T16:37:15.831Z","createdBy":"65a166457db8ed94976ba0b9","_id":"65a16abb42a1832687d40f52"},{"createdAt":"2024-01-12T16:43:58.422Z","createdBy":"617956691255b34289cf368b","_id":"65a16c4e67492b96b3315ce3"},{"createdAt":"2024-01-12T16:45:28.988Z","createdBy":"65a16ae6d29d587eb7f6c1fb","_id":"65a16ca87db8ed94976bd916"},{"createdAt":"2024-01-13T05:03:25.760Z","createdBy":"65a218aca1ab9d9d226dca27","_id":"65a2199dd29d587eb7fb685c"},{"createdAt":"2024-01-13T06:24:56.016Z","createdBy":"624bac727d0365977fd09bdd","_id":"65a22cb8a1ab9d9d226e196f"},{"createdAt":"2024-01-13T06:57:40.529Z","createdBy":"65a00e3e7db8ed9497597c2e","_id":"65a23464d29d587eb7fbd258"},{"createdAt":"2024-01-13T07:39:29.437Z","createdBy":"65a23d8e71f5d4e177141e87","_id":"65a23e31d29d587eb7fbe87b"},{"createdAt":"2024-01-13T07:50:21.297Z","createdBy":"65a24089d29d587eb7fc09d5","_id":"65a240bd71f5d4e17714b49e"},{"createdAt":"2024-01-13T07:56:57.711Z","createdBy":"65a13d2171f5d4e1770beee2","_id":"65a2424971f5d4e17714b621"},{"createdAt":"2024-01-13T07:57:52.407Z","createdBy":"65a24265c48c038732f5dca2","_id":"65a24280a1ab9d9d226e8455"},{"createdAt":"2024-01-13T08:10:50.121Z","createdBy":"65a24536a1ab9d9d226e89b8","_id":"65a2458a42a1832687d94f34"},{"createdAt":"2024-01-13T08:11:35.714Z","createdBy":"61d94ab000fcfe7a9914f44d","_id":"65a245b77db8ed949771f4e8"},{"createdAt":"2024-01-13T08:13:25.622Z","createdBy":"65a11dc4d29d587eb7f01cfd","_id":"65a24625a1ab9d9d226e8b45"},{"createdAt":"2024-01-13T08:34:26.516Z","createdBy":"65a24ae871f5d4e17714fa06","_id":"65a24b12a1ab9d9d226e985a"},{"createdAt":"2024-01-13T08:35:13.301Z","createdBy":"65a015c0d29d587eb7e45f27","_id":"65a24b4171f5d4e17714fc12"},{"createdAt":"2024-01-13T08:39:18.661Z","createdBy":"65a24b1542a1832687d96eff","_id":"65a24c3667492b96b33622dd"},{"createdAt":"2024-01-13T08:56:34.279Z","createdBy":"62c421365a0ba23dbb560d66","_id":"65a25042544c81104f2f7855"},{"createdAt":"2024-01-13T09:09:30.027Z","createdBy":"65a252b267492b96b3362b2c","_id":"65a2534aa1ab9d9d226ea360"},{"createdAt":"2024-01-13T09:12:32.468Z","createdBy":"65a253cc71f5d4e1771522c2","_id":"65a2540067492b96b3362ded"},{"createdAt":"2024-01-13T09:14:14.020Z","createdBy":"63f4b5587729fab457dd3f1c","_id":"65a25466d29d587eb7fc793d"},{"createdAt":"2024-01-13T09:15:00.472Z","createdBy":"61fab1703a14e5f213d10184","_id":"65a25494544c81104f2f884d"},{"createdAt":"2024-01-13T09:15:00.689Z","createdBy":"61fab1703a14e5f213d10184","_id":"65a2549471f5d4e1771523ec"},{"createdAt":"2024-01-13T09:15:13.840Z","createdBy":"61795948f09a7f42823294b0","_id":"65a254a167492b96b3362f3d"},{"createdAt":"2024-01-13T09:30:24.601Z","createdBy":"619cec0813e0ddb05ef3a313","_id":"65a258307db8ed9497722465"},{"createdAt":"2024-01-13T09:34:36.950Z","createdBy":"617fad6ea68281d7bceb4262","_id":"65a2592c7db8ed94977225ee"},{"createdAt":"2024-01-13T09:54:18.837Z","createdBy":"621e0bbada75ad5fd5c5929b","_id":"65a25dca71f5d4e17715e046"},{"createdAt":"2024-01-13T10:01:13.103Z","createdBy":"618d030ef9a5c1d81bdf61db","_id":"65a25f69544c81104f2fd30d"},{"createdAt":"2024-01-13T10:11:46.135Z","createdBy":"65a0f3fa544c81104f228939","_id":"65a261e27db8ed949772523a"},{"createdAt":"2024-01-13T10:14:27.703Z","createdBy":"617bded3a68281d7bceb2126","_id":"65a26283544c81104f2fea6b"},{"createdAt":"2024-01-13T10:29:54.903Z","createdBy":"65a106bf544c81104f239c47","_id":"65a26622d29d587eb7fce851"},{"createdAt":"2024-01-13T10:36:46.501Z","createdBy":"617bdee7de4bc1dea1293aa6","_id":"65a267bea1ab9d9d226fdf88"},{"createdAt":"2024-01-13T11:17:15.957Z","createdBy":"625eb9715274f2cda27c6977","_id":"65a2713b42a1832687da6656"},{"createdAt":"2024-01-13T13:46:41.558Z","createdBy":"64c2cae7101cc2215ca2087e","_id":"65a2944167492b96b33a9dcc"},{"createdAt":"2024-01-13T14:13:23.842Z","createdBy":"65a2984e544c81104f32d16a","_id":"65a29a83c48c038732f812a0"},{"createdAt":"2024-01-13T14:23:53.297Z","createdBy":"63c67a780ba00074512c609a","_id":"65a29cf9c48c038732f82d70"},{"createdAt":"2024-01-13T15:13:52.750Z","createdBy":"617ac9a10e457bdeb859de42","_id":"65a2a8b067492b96b33b31e3"},{"createdAt":"2024-01-13T16:16:37.658Z","createdBy":"6331ab1068352991e48e88bb","_id":"65a2b76571f5d4e17718b1b7"},{"createdAt":"2024-01-13T16:17:28.406Z","createdBy":"6182c67dbc37e0d7a1376dce","_id":"65a2b79871f5d4e17718b244"},{"createdAt":"2024-01-14T09:07:21.964Z","createdBy":"63edfe3af1eaedabcbb9c647","_id":"65a3a4497db8ed94977a0020"},{"createdAt":"2024-01-14T10:16:45.502Z","createdBy":"65a3b4507db8ed94977a2f42","_id":"65a3b48dc48c038732ff3586"},{"createdAt":"2024-01-14T10:58:35.745Z","createdBy":"65a3be3071f5d4e1771e65ce","_id":"65a3be5b71f5d4e1771e6705"},{"createdAt":"2024-01-14T15:08:15.629Z","createdBy":"617944824e05333afc8cfffc","_id":"65a3f8dfa1ab9d9d227a9de6"},{"createdAt":"2024-01-14T22:03:53.334Z","createdBy":"65a459aa544c81104f3b31bb","_id":"65a45a49544c81104f3b3279"},{"createdAt":"2024-01-15T06:22:17.107Z","createdBy":"656dd47feed410ba1eff62e5","_id":"65a4cf19d29d587eb708f355"},{"createdAt":"2024-01-15T06:28:45.146Z","createdBy":"61838031a68281d7bcebeb38","_id":"65a4d09d42a1832687e8ac68"},{"createdAt":"2024-01-15T06:43:39.905Z","createdBy":"628d3620c4a72565add5772d","_id":"65a4d41bc48c03873206940c"},{"createdAt":"2024-01-15T07:02:14.637Z","createdBy":"619badaad1cb3db047cc1199","_id":"65a4d876c48c03873206a20c"},{"createdAt":"2024-01-15T07:09:16.471Z","createdBy":"65a4d9e767492b96b343f46d","_id":"65a4da1ca1ab9d9d227d7978"},{"createdAt":"2024-01-15T07:11:47.742Z","createdBy":"65a153f6a1ab9d9d22674a80","_id":"65a4dab3c48c03873206ad89"},{"createdAt":"2024-01-15T07:50:58.434Z","createdBy":"619375d9e06019d7fe3d7389","_id":"65a4e3e267492b96b3441a94"},{"createdAt":"2024-01-15T07:52:27.568Z","createdBy":"65a4e421a1ab9d9d227da88d","_id":"65a4e43bd29d587eb709aa9c"},{"createdAt":"2024-01-15T07:57:12.690Z","createdBy":"65a4e54ed29d587eb709b26c","_id":"65a4e558d29d587eb709b27f"},{"createdAt":"2024-01-15T08:11:30.869Z","createdBy":"65a166457db8ed94976ba0b9","_id":"65a4e8b242a1832687e93864"},{"createdAt":"2024-01-15T08:32:48.384Z","createdBy":"618b9034cc3f777e1973d139","_id":"65a4edb071f5d4e177238f09"},{"createdAt":"2024-01-15T08:37:02.981Z","createdBy":"65a0f263c48c038732e7fc69","_id":"65a4eeaed29d587eb70a3689"},{"createdAt":"2024-01-15T08:40:14.756Z","createdBy":"65a0f263c48c038732e7fc69","_id":"65a4ef6e71f5d4e1772418a3"},{"createdAt":"2024-01-15T08:42:04.320Z","createdBy":"617fa68cbcde0ad7b72d794b","_id":"65a4efdc71f5d4e1772419de"},{"createdAt":"2024-01-15T08:44:27.360Z","createdBy":"65a1619aa1ab9d9d2267d26c","_id":"65a4f06b71f5d4e177241bad"},{"createdAt":"2024-01-15T08:52:42.230Z","createdBy":"61af125e73eaedfaf4c4aa1d","_id":"65a4f25aa1ab9d9d227ddfa6"},{"createdAt":"2024-01-15T08:59:43.796Z","createdBy":"619b7944fa0527d82132e2ec","_id":"65a4f3ffa1ab9d9d227deb47"},{"createdAt":"2024-01-15T09:01:11.987Z","createdBy":"65a11770544c81104f241315","_id":"65a4f457c48c0387320731f3"},{"createdAt":"2024-01-15T09:03:17.347Z","createdBy":"65a4f4cf67492b96b3448cb1","_id":"65a4f4d57db8ed949780ba8d"},{"createdAt":"2024-01-15T09:03:46.279Z","createdBy":"62b9b421d42225817898f16c","_id":"65a4f4f27db8ed949780bf30"},{"createdAt":"2024-01-15T09:07:19.153Z","createdBy":"659faff642a1832687b81b6f","_id":"65a4f5c7d29d587eb70a7165"},{"createdAt":"2024-01-15T09:12:54.665Z","createdBy":"619b7944fa0527d82132e2ec","_id":"65a4f71667492b96b344a82e"},{"createdAt":"2024-01-15T09:13:04.401Z","createdBy":"6323ef38f60660165220ad69","_id":"65a4f720c48c038732075153"},{"createdAt":"2024-01-15T09:31:04.998Z","createdBy":"64819bddcb64bb824e505fb6","_id":"65a4fb59d29d587eb70a7c6e"},{"createdAt":"2024-01-15T09:35:43.584Z","createdBy":"657964c29d84fe162a7ec700","_id":"65a4fc6fd29d587eb70aa2cd"},{"createdAt":"2024-01-15T10:02:33.616Z","createdBy":"65a128f542a1832687ce44cb","_id":"65a502b97db8ed9497814a59"},{"createdAt":"2024-01-15T10:02:38.772Z","createdBy":"65a5029ba1ab9d9d227f1583","_id":"65a502bea1ab9d9d227f15b5"},{"createdAt":"2024-01-15T10:17:22.548Z","createdBy":"63b57cb0c623239ce4f978ac","_id":"65a506327db8ed949781eb19"},{"createdAt":"2024-01-15T10:18:10.663Z","createdBy":"6180160c0e457bdeb85a1f5c","_id":"65a50662a1ab9d9d227fb9e7"},{"createdAt":"2024-01-15T10:31:50.119Z","createdBy":"65a50958a1ab9d9d227fdb13","_id":"65a50996c48c03873207df52"},{"createdAt":"2024-01-15T10:36:28.220Z","createdBy":"65a0f035d29d587eb7ec4c68","_id":"65a50aac7db8ed9497820fb0"},{"createdAt":"2024-01-15T10:39:15.382Z","createdBy":"65a50b1f67492b96b34634b5","_id":"65a50b53544c81104f3ef437"},{"createdAt":"2024-01-15T11:06:11.794Z","createdBy":"618b8541ba6c787dfcc6450b","_id":"65a511a3544c81104f3efab5"},{"createdAt":"2024-01-15T12:03:37.409Z","createdBy":"6180f318bc37e0d7a136f893","_id":"65a51f1942a1832687eb363e"},{"createdAt":"2024-01-15T12:10:20.288Z","createdBy":"65a5204242a1832687eb3a52","_id":"65a520ac42a1832687eb3a9e"},{"createdAt":"2024-01-15T12:11:45.218Z","createdBy":"6496a1525401dc224db451fd","_id":"65a52101a1ab9d9d22806ffa"},{"createdAt":"2024-01-15T12:20:29.109Z","createdBy":"6496a1525401dc224db451fd","_id":"65a5230dc48c038732091619"},{"createdAt":"2024-01-15T12:39:47.730Z","createdBy":"61795169942f1f426664a924","_id":"65a5279367492b96b3475de4"},{"createdAt":"2024-01-15T12:41:33.929Z","createdBy":"61813b03bcde0ad7b72daa71","_id":"65a527fdc48c0387320947bb"},{"createdAt":"2024-01-15T12:53:22.320Z","createdBy":"618b8541ba6c787dfcc6450b","_id":"65a52ac271f5d4e177283964"},{"createdAt":"2024-01-15T12:56:52.036Z","createdBy":"61794cce69d7943b12b7cfbf","_id":"65a52b9442a1832687ec0bee"},{"createdAt":"2024-01-15T12:58:45.093Z","createdBy":"6190ed45fa0527d82131858a","_id":"65a52c0542a1832687ec0d5d"},{"createdAt":"2024-01-15T13:11:39.513Z","createdBy":"65a159c242a1832687d25a97","_id":"65a52f0b71f5d4e177284c4d"},{"createdAt":"2024-01-15T13:21:14.371Z","createdBy":"65a5313071f5d4e17728680d","_id":"65a5314a544c81104f406f3a"},{"createdAt":"2024-01-15T13:38:21.946Z","createdBy":"65a5244d67492b96b3473e2f","_id":"65a5354da1ab9d9d2280c7a5"},{"createdAt":"2024-01-15T13:52:11.698Z","createdBy":"659d2bf87db8ed9497300b24","_id":"65a5388b544c81104f40972a"},{"createdAt":"2024-01-15T14:10:53.214Z","createdBy":"623986ad5b05bf5ce50422d6","_id":"65a53ced7db8ed949783ccbc"},{"createdAt":"2024-01-15T15:07:01.405Z","createdBy":"65a5067867492b96b3461810","_id":"65a54a15544c81104f41256b"},{"createdAt":"2024-01-15T15:20:04.252Z","createdBy":"65a4f586c48c038732074319","_id":"65a54d247db8ed94978402f7"},{"createdAt":"2024-01-15T15:25:38.864Z","createdBy":"655ca86e8c9fe460cbee21ea","_id":"65a54e72a1ab9d9d228145fa"},{"createdAt":"2024-01-15T15:33:02.704Z","createdBy":"65a14ef9d29d587eb7f29345","_id":"65a5502e7db8ed94978406e5"},{"createdAt":"2024-01-15T15:46:47.163Z","createdBy":"65a23d8e71f5d4e177141e87","_id":"65a5536742a1832687ee9659"},{"createdAt":"2024-01-16T00:12:43.490Z","createdBy":"620f4cd52716cc53c64ce477","_id":"65a5c9fb71f5d4e1772c6828"},{"createdAt":"2024-01-16T00:17:14.461Z","createdBy":"621c6113c148101752eeed33","_id":"65a5cb0a42a1832687f14165"},{"createdAt":"2024-01-16T01:29:20.310Z","createdBy":"617797b5cf7204680d8a2f4d","_id":"65a5dbf0c48c0387320e4a08"},{"createdAt":"2024-01-16T01:54:14.603Z","createdBy":"65a22140a1ab9d9d226dcc87","_id":"65a5e1c6544c81104f4462b5"},{"createdAt":"2024-01-16T02:27:00.137Z","createdBy":"65a5c809a1ab9d9d228479c6","_id":"65a5e974d29d587eb711842f"},{"createdAt":"2024-01-16T02:36:36.313Z","createdBy":"65a33c0871f5d4e1771ccd5b","_id":"65a5ebb4a1ab9d9d2284ed5b"},{"createdAt":"2024-01-16T02:52:17.240Z","createdBy":"65a5ee9a7db8ed94978843d5","_id":"65a5ef61d29d587eb71189aa"},{"createdAt":"2024-01-16T04:23:13.072Z","createdBy":"65a46c51544c81104f3b92e1","_id":"65a604b171f5d4e1772d0d22"},{"createdAt":"2024-01-16T04:29:45.832Z","createdBy":"6233e18ba73caec8765bf533","_id":"65a6063967492b96b34bb55b"},{"createdAt":"2024-01-16T04:31:56.874Z","createdBy":"65a606ac544c81104f456035","_id":"65a606bcc48c0387320eabf3"},{"createdAt":"2024-01-16T04:34:42.668Z","createdBy":"658ac410a1ab9d9d22935607","_id":"65a6076271f5d4e1772d1150"},{"createdAt":"2024-01-16T05:10:35.608Z","createdBy":"65a0624867492b96b327511d","_id":"65a60fcbc48c0387320eba38"},{"createdAt":"2024-01-16T06:13:57.573Z","createdBy":"65a0f92c42a1832687c95504","_id":"65a61ea567492b96b34c5500"},{"createdAt":"2024-01-16T06:59:03.868Z","createdBy":"63dd3b0ac623239ce40d334c","_id":"65a62937544c81104f4636a0"},{"createdAt":"2024-01-16T06:59:50.758Z","createdBy":"6182483ca68281d7bceb9df9","_id":"65a6296671f5d4e1772db359"},{"createdAt":"2024-01-16T07:00:27.295Z","createdBy":"64af628338990d2235fb7d1d","_id":"65a6298bc48c0387320f1da1"},{"createdAt":"2024-01-16T07:14:52.556Z","createdBy":"65a4feb467492b96b344dafa","_id":"65a62ceca1ab9d9d228638df"},{"createdAt":"2024-01-16T07:15:04.143Z","createdBy":"65a4feb467492b96b344dafa","_id":"65a62cf867492b96b34c97ca"},{"createdAt":"2024-01-16T07:52:38.971Z","createdBy":"65a4feb467492b96b344dafa","_id":"65a635c6d29d587eb712d16f"},{"createdAt":"2024-01-16T07:54:53.614Z","createdBy":"617a3a92de4bc1dea1291641","_id":"65a6364dc48c0387320ff9a8"},{"createdAt":"2024-01-16T07:59:49.740Z","createdBy":"6318644abecc0316662b0ff3","_id":"65a637757db8ed94978aa29a"},{"createdAt":"2024-01-16T08:00:25.725Z","createdBy":"65a144fd544c81104f25cc60","_id":"65a6379967492b96b34d6cac"},{"createdAt":"2024-01-16T08:02:04.762Z","createdBy":"65a144fd544c81104f25cc60","_id":"65a637fcd29d587eb712ed92"},{"createdAt":"2024-01-16T08:02:17.087Z","createdBy":"61794b9d942f1f426664a84a","_id":"65a63809a1ab9d9d2286e74a"},{"createdAt":"2024-01-16T08:02:56.292Z","createdBy":"617c0dd0c61d67deb7198b12","_id":"65a63830d29d587eb712fc7a"},{"createdAt":"2024-01-16T08:04:38.497Z","createdBy":"65a144fd544c81104f25cc60","_id":"65a63896a1ab9d9d2286e98c"},{"createdAt":"2024-01-16T08:04:50.662Z","createdBy":"649adadd3df7906aeea437ea","_id":"65a638a271f5d4e1772efbee"},{"createdAt":"2024-01-16T08:05:07.569Z","createdBy":"65a2494ea1ab9d9d226e95a2","_id":"65a638b342a1832687f363da"},{"createdAt":"2024-01-16T08:08:14.548Z","createdBy":"65a149b87db8ed949769115d","_id":"65a6396e7db8ed94978aa7c3"},{"createdAt":"2024-01-16T08:10:40.286Z","createdBy":"65a4f761c48c038732075200","_id":"65a63a00d29d587eb7130f89"},{"createdAt":"2024-01-16T08:11:30.201Z","createdBy":"65a638ed42a1832687f3662d","_id":"65a63a32544c81104f46c752"},{"createdAt":"2024-01-16T08:12:14.154Z","createdBy":"65a249b471f5d4e17714f34e","_id":"65a63a5ec48c03873210081f"},{"createdAt":"2024-01-16T08:13:58.927Z","createdBy":"65a1152cd29d587eb7ef325a","_id":"65a63ac6d29d587eb7131bc3"},{"createdAt":"2024-01-16T08:14:17.999Z","createdBy":"65a139f97db8ed949768b8fa","_id":"65a63adaa1ab9d9d2287020e"},{"createdAt":"2024-01-16T08:17:34.460Z","createdBy":"648719e503f6e9e0fd8790aa","_id":"65a63b9e7db8ed94978aaef5"},{"createdAt":"2024-01-16T08:18:22.646Z","createdBy":"621f32d5e55477173064f149","_id":"65a63bce544c81104f46d600"},{"createdAt":"2024-01-16T08:23:15.855Z","createdBy":"6561c3e4f6166d9f57b62200","_id":"65a63cf37db8ed94978ab31b"},{"createdAt":"2024-01-16T08:25:47.879Z","createdBy":"65a1384067492b96b32e9906","_id":"65a63d8b7db8ed94978ab6c8"},{"createdAt":"2024-01-16T08:25:53.897Z","createdBy":"65a1384067492b96b32e9906","_id":"65a63d91c48c038732103acd"},{"createdAt":"2024-01-16T08:25:55.863Z","createdBy":"618388afde4bc1dea12a0e9a","_id":"65a63d93544c81104f4714a2"},{"createdAt":"2024-01-16T08:26:28.098Z","createdBy":"621f32d5e55477173064f149","_id":"65a63db4c48c038732103d2e"},{"createdAt":"2024-01-16T08:36:06.751Z","createdBy":"65a1202671f5d4e17709747c","_id":"65a63ff67db8ed94978ac036"},{"createdAt":"2024-01-16T08:36:14.279Z","createdBy":"65a4feb467492b96b344dafa","_id":"65a63ffea1ab9d9d22871d58"},{"createdAt":"2024-01-16T08:36:26.126Z","createdBy":"61840b96a63936d7a7d31afd","_id":"65a6400aa1ab9d9d22871e45"},{"createdAt":"2024-01-16T08:39:17.499Z","createdBy":"65a6406742a1832687f480cb","_id":"65a640b5d29d587eb713d8a2"},{"createdAt":"2024-01-16T08:39:20.299Z","createdBy":"65a64069c48c038732106e39","_id":"65a640b87db8ed94978ac241"},{"createdAt":"2024-01-16T08:46:11.797Z","createdBy":"659d2831c48c038732b018bc","_id":"65a64253c48c038732109d97"},{"createdAt":"2024-01-16T08:46:11.798Z","createdBy":"659d2831c48c038732b018bc","_id":"65a642537db8ed94978b3833"},{"createdAt":"2024-01-16T08:46:23.801Z","createdBy":"61811987bc37e0d7a13702fd","_id":"65a6425fa1ab9d9d22873c6d"},{"createdAt":"2024-01-16T08:47:00.970Z","createdBy":"62163373ce86ff5fdccb9a30","_id":"65a6428471f5d4e177309933"},{"createdAt":"2024-01-16T08:47:01.360Z","createdBy":"62163373ce86ff5fdccb9a30","_id":"65a6428567492b96b34eed16"},{"createdAt":"2024-01-16T08:47:01.659Z","createdBy":"62163373ce86ff5fdccb9a30","_id":"65a64285d29d587eb713e57b"},{"createdAt":"2024-01-16T08:55:36.349Z","createdBy":"618a50dc99051475734d2635","_id":"65a6448867492b96b34f028f"},{"createdAt":"2024-01-16T08:58:17.653Z","createdBy":"6182bef4a68281d7bcebcfd2","_id":"65a64529a1ab9d9d228874a6"},{"createdAt":"2024-01-16T09:06:16.970Z","createdBy":"65a001c767492b96b320b8f7","_id":"65a6470842a1832687f4c1e6"},{"createdAt":"2024-01-16T09:11:46.671Z","createdBy":"6194d541f9a5c1d81be07d00","_id":"65a64852544c81104f476421"},{"createdAt":"2024-01-16T09:22:11.242Z","createdBy":"65a64ab642a1832687f550ce","_id":"65a64ac3a1ab9d9d2288fcea"},{"createdAt":"2024-01-16T09:22:43.195Z","createdBy":"65a64ab642a1832687f550ce","_id":"65a64ae371f5d4e177311e4b"},{"createdAt":"2024-01-16T09:27:26.272Z","createdBy":"617fefdaa68281d7bceb4aea","_id":"65a64bfec48c038732116d2c"},{"createdAt":"2024-01-16T09:30:34.474Z","createdBy":"65a2936171f5d4e177176dba","_id":"65a64cba544c81104f47ea86"},{"createdAt":"2024-01-16T09:32:15.528Z","createdBy":"65a0d061c48c038732e6c34b","_id":"65a64d1fc48c038732117650"},{"createdAt":"2024-01-16T09:35:46.197Z","createdBy":"65a64dd1544c81104f4803ae","_id":"65a64df2c48c038732117c46"},{"createdAt":"2024-01-16T09:36:14.987Z","createdBy":"6177bf4b07ef1d40c45f7984","_id":"65a64e0ec48c038732117d34"},{"createdAt":"2024-01-16T09:36:48.863Z","createdBy":"65a64a537db8ed94978bc37e","_id":"65a64e30544c81104f481069"},{"createdAt":"2024-01-16T09:46:38.740Z","createdBy":"64dc9832738a9804594981da","_id":"65a6507e544c81104f481dee"},{"createdAt":"2024-01-16T09:48:05.663Z","createdBy":"65a52a9f7db8ed949782e3bc","_id":"65a650d542a1832687f6063e"},{"createdAt":"2024-01-16T09:50:16.362Z","createdBy":"65a52a9f7db8ed949782e3bc","_id":"65a6515867492b96b35192b3"},{"createdAt":"2024-01-16T09:52:46.665Z","createdBy":"61825f15a68281d7bceba980","_id":"65a651eec48c0387321189bd"},{"createdAt":"2024-01-16T09:53:58.265Z","createdBy":"65a52a9f7db8ed949782e3bc","_id":"65a6523642a1832687f62788"},{"createdAt":"2024-01-16T09:59:21.295Z","createdBy":"65a165aa544c81104f290f76","_id":"65a6537971f5d4e17732194f"},{"createdAt":"2024-01-16T10:07:21.674Z","createdBy":"65a50d49a1ab9d9d227ff8ce","_id":"65a655597db8ed94978c5735"},{"createdAt":"2024-01-16T10:11:22.794Z","createdBy":"65a65644544c81104f487fee","_id":"65a6564ad29d587eb715c27e"},{"createdAt":"2024-01-16T10:12:20.741Z","createdBy":"65a65658544c81104f4889ea","_id":"65a65684c48c03873211d22f"},{"createdAt":"2024-01-16T10:17:11.643Z","createdBy":"65a656c067492b96b352482a","_id":"65a657a7d29d587eb7164937"},{"createdAt":"2024-01-16T10:21:10.687Z","createdBy":"64c14b7fc3e93cbbab1130e2","_id":"65a658967db8ed94978c820a"},{"createdAt":"2024-01-16T10:31:32.529Z","createdBy":"65a02b0342a1832687c0e9f2","_id":"65a65b04c48c0387321214fc"},{"createdAt":"2024-01-16T10:33:15.710Z","createdBy":"65a013bf7db8ed94975a170e","_id":"65a65b6bc48c03873212164b"},{"createdAt":"2024-01-16T10:38:26.952Z","createdBy":"618e2dbcd1cb3db047ca25a4","_id":"65a65ca27db8ed94978cbb67"},{"createdAt":"2024-01-16T10:58:31.167Z","createdBy":"65a638547db8ed94978aa45c","_id":"65a66157d29d587eb71694a6"},{"createdAt":"2024-01-16T11:13:35.471Z","createdBy":"65a66460c48c038732130748","_id":"65a664df71f5d4e177357997"},{"createdAt":"2024-01-16T12:07:05.704Z","createdBy":"61a9fe2c116a5996c0a408a5","_id":"65a6716942a1832687f8ca96"},{"createdAt":"2024-01-16T12:22:59.147Z","createdBy":"65a65c6c71f5d4e17733f5e1","_id":"65a67523c48c038732138d3d"},{"createdAt":"2024-01-16T12:25:04.737Z","createdBy":"65a4e98ba1ab9d9d227dc3fa","_id":"65a675a0a1ab9d9d228d2cfa"},{"createdAt":"2024-01-16T12:39:12.772Z","createdBy":"65a6788471f5d4e17736cdf1","_id":"65a678f067492b96b355639e"},{"createdAt":"2024-01-16T12:48:02.912Z","createdBy":"65a67af9544c81104f4bd562","_id":"65a67b02d29d587eb718d94e"},{"createdAt":"2024-01-16T12:48:50.179Z","createdBy":"65a67af9544c81104f4bd562","_id":"65a67b327db8ed94978f6a94"},{"createdAt":"2024-01-16T12:51:38.272Z","createdBy":"65a4d9c3544c81104f3da7d0","_id":"65a67bdac48c038732142ced"},{"createdAt":"2024-01-16T13:02:13.577Z","createdBy":"65a4f43b67492b96b3447c3e","_id":"65a67e5571f5d4e177386d87"},{"createdAt":"2024-01-16T13:09:05.916Z","createdBy":"65a641b342a1832687f49bdc","_id":"65a67ff1a1ab9d9d228d8fbb"},{"createdAt":"2024-01-16T13:10:41.474Z","createdBy":"61b05aeb755b3dee40311cf9","_id":"65a68051c48c0387321455eb"},{"createdAt":"2024-01-16T13:27:04.140Z","createdBy":"618fbb29e06019d7fe3d112c","_id":"65a684287db8ed94979108fc"},{"createdAt":"2024-01-16T13:50:27.460Z","createdBy":"64d24649738a980459437678","_id":"65a689a342a1832687faa9ce"},{"createdAt":"2024-01-16T14:08:21.498Z","createdBy":"61b05aeb755b3dee40311cf9","_id":"65a68dd5a1ab9d9d228ea5db"},{"createdAt":"2024-01-16T14:22:12.441Z","createdBy":"65a6910b71f5d4e1773add65","_id":"65a69114544c81104f4d84b4"},{"createdAt":"2024-01-16T14:31:19.674Z","createdBy":"65a2463c67492b96b3360865","_id":"65a69337a1ab9d9d228efcb7"},{"createdAt":"2024-01-16T14:33:26.655Z","createdBy":"618b8615ba6c787dfcc64586","_id":"65a693b6d29d587eb71bf69c"},{"createdAt":"2024-01-16T14:34:18.903Z","createdBy":"65a693aec48c03873215ed7c","_id":"65a693ea71f5d4e1773afc8f"},{"createdAt":"2024-01-16T14:45:55.949Z","createdBy":"65a0fb2bc48c038732e86a88","_id":"65a696a37db8ed94979245f0"},{"createdAt":"2024-01-16T14:48:09.054Z","createdBy":"65a68ee342a1832687fae8d0","_id":"65a69729544c81104f4e159e"},{"createdAt":"2024-01-16T14:54:43.070Z","createdBy":"617fcadfa63936d7a7d2385c","_id":"65a698b3544c81104f4e8902"},{"createdAt":"2024-01-16T15:26:05.281Z","createdBy":"65a10255c48c038732e8d183","_id":"65a6a00d42a1832687fb53c9"},{"createdAt":"2024-01-16T15:26:20.325Z","createdBy":"65a69fef544c81104f4ebe0c","_id":"65a6a01c544c81104f4ebe42"},{"createdAt":"2024-01-16T15:27:48.341Z","createdBy":"63edf2c0daec3cbb6f45fca0","_id":"65a6a074544c81104f4ebff2"},{"createdAt":"2024-01-16T15:30:24.773Z","createdBy":"6245923bda9535979b4f42da","_id":"65a6a110d29d587eb71d4cf6"},{"createdAt":"2024-01-16T15:45:13.817Z","createdBy":"65a697b6c48c03873215fd20","_id":"65a6a489c48c0387321730ee"},{"createdAt":"2024-01-16T16:14:33.214Z","createdBy":"65a6ab5f42a1832687fbd9c9","_id":"65a6ab697db8ed949792fb45"},{"createdAt":"2024-01-16T16:24:01.864Z","createdBy":"65a10bf8a1ab9d9d22620fad","_id":"65a6ada1544c81104f4fa373"},{"createdAt":"2024-01-16T16:25:31.086Z","createdBy":"65a6adef42a1832687fbe220","_id":"65a6adfb42a1832687fbe872"},{"createdAt":"2024-01-16T16:41:41.496Z","createdBy":"65a6a7c1544c81104f4f8287","_id":"65a6b1c567492b96b35ab096"},{"createdAt":"2024-01-16T16:43:43.113Z","createdBy":"65a6a7c1544c81104f4f8287","_id":"65a6b23fa1ab9d9d2291d9f1"},{"createdAt":"2024-01-16T19:41:05.738Z","createdBy":"6179a522de4bc1dea1290d80","_id":"65a6dbd167492b96b35c91ec"},{"createdAt":"2024-01-16T21:39:17.150Z","createdBy":"63e25c117c3841f07f4503b6","_id":"65a6f785a1ab9d9d2294def8"},{"createdAt":"2024-01-17T00:06:00.947Z","createdBy":"65a719dba1ab9d9d229593df","_id":"65a719e8a1ab9d9d229593f2"},{"createdAt":"2024-01-17T04:07:05.700Z","createdBy":"6185adf6ec5f3d2216f19f6f","_id":"65a752697db8ed949799ff65"},{"createdAt":"2024-01-17T06:53:23.304Z","createdBy":"6191f5fcc37675b041b13557","_id":"65a7796371f5d4e17742c526"},{"createdAt":"2024-01-17T07:22:10.555Z","createdBy":"6569dd30b3c355bfda50043b","_id":"65a78022544c81104f56305f"},{"createdAt":"2024-01-17T08:16:05.276Z","createdBy":"65a78c7271f5d4e177433009","_id":"65a78cc5a1ab9d9d2296ece4"},{"createdAt":"2024-01-17T09:20:30.961Z","createdBy":"65a6894ad29d587eb71b52b0","_id":"65a79bde42a183268703285d"},{"createdAt":"2024-01-17T09:41:58.868Z","createdBy":"6462ff730d7f017c91fbb1e0","_id":"65a7a0e671f5d4e17744a824"},{"createdAt":"2024-01-17T09:42:35.416Z","createdBy":"6462ff730d7f017c91fbb1e0","_id":"65a7a10bc48c0387321ec4e8"},{"createdAt":"2024-01-17T10:32:47.200Z","createdBy":"65a7ac427db8ed94979ea090","_id":"65a7accf7db8ed94979ea24e"},{"createdAt":"2024-01-17T11:53:29.317Z","createdBy":"65a1662ea1ab9d9d2268dc39","_id":"65a7bfb9544c81104f5cef3e"},{"createdAt":"2024-01-17T11:54:58.485Z","createdBy":"617aabf4de4bc1dea1292783","_id":"65a7c0127db8ed94979f497d"},{"createdAt":"2024-01-17T12:51:43.043Z","createdBy":"6179464769d7943b12b7cecb","_id":"65a7cd5fd29d587eb728a925"},{"createdAt":"2024-01-17T13:34:56.731Z","createdBy":"63778a84ce61c347e5a67919","_id":"65a7d78067492b96b3674874"},{"createdAt":"2024-01-17T13:51:19.998Z","createdBy":"624ebaa4d85d745cec47e40e","_id":"65a7db57a1ab9d9d229ccdf3"},{"createdAt":"2024-01-17T13:56:03.940Z","createdBy":"65a1253e42a1832687ce34a6","_id":"65a7dc73d29d587eb729883c"},{"createdAt":"2024-01-17T13:58:24.569Z","createdBy":"65a1046271f5d4e177079a98","_id":"65a7dd00544c81104f5edcf7"},{"createdAt":"2024-01-17T15:52:41.401Z","createdBy":"65a5244d67492b96b3473e2f","_id":"65a7f7c9a1ab9d9d229efb62"},{"createdAt":"2024-01-17T23:39:32.781Z","createdBy":"617b6c36a63936d7a7d20c3c","_id":"65a86534a1ab9d9d22add28b"},{"createdAt":"2024-01-18T00:43:28.496Z","createdBy":"65a0f92c42a1832687c95504","_id":"65a87430f1d9b256cd2ba5f7"},{"createdAt":"2024-01-18T02:35:47.605Z","createdBy":"6392a3dffaaf769cff2e8cde","_id":"65a88e83544c81104f718774"},{"createdAt":"2024-01-18T03:41:20.815Z","createdBy":"65a894fc67492b96b3769f34","_id":"65a89de07db8ed9497ab9fa3"},{"createdAt":"2024-01-18T05:47:29.683Z","createdBy":"65769d6d860cd52a9f9e6d15","_id":"65a8bb71f1d9b256cd2d018e"},{"createdAt":"2024-01-18T05:47:30.078Z","createdBy":"65769d6d860cd52a9f9e6d15","_id":"65a8bb727db8ed9497ac1bc4"},{"createdAt":"2024-01-18T05:47:30.289Z","createdBy":"65769d6d860cd52a9f9e6d15","_id":"65a8bb72f1d9b256cd2d02a5"},{"createdAt":"2024-01-18T06:18:38.995Z","createdBy":"65769d6d860cd52a9f9e6d15","_id":"65a8c2be67492b96b377e5a0"},{"createdAt":"2024-01-18T06:20:35.772Z","createdBy":"65a22140a1ab9d9d226dcc87","_id":"65a8c33367492b96b377e881"},{"createdAt":"2024-01-18T06:27:47.524Z","createdBy":"65a4314471f5d4e17720103f","_id":"65a8c4e37db8ed9497ac80f3"},{"createdAt":"2024-01-18T06:55:32.057Z","createdBy":"65a8cb14a1e6629c96d1081c","_id":"65a8cb64a1e6629c96d1085a"},{"createdAt":"2024-01-18T06:58:03.229Z","createdBy":"65a51c8c67492b96b3471ed0","_id":"65a8cbfbf1d9b256cd2d3788"},{"createdAt":"2024-01-18T06:58:35.112Z","createdBy":"65a8cb14a1e6629c96d1081c","_id":"65a8cc1b7db8ed9497aca77d"},{"createdAt":"2024-01-18T07:52:11.841Z","createdBy":"61795154f09a7f428232932c","_id":"65a8d8abf1d9b256cd2dd4b9"},{"createdAt":"2024-01-18T07:53:36.026Z","createdBy":"6180e217de4bc1dea1298bf2","_id":"65a8d90042a183268715d782"},{"createdAt":"2024-01-18T07:58:41.119Z","createdBy":"65a64e5bd29d587eb714f28a","_id":"65a8da31a1ab9d9d22b08aa9"},{"createdAt":"2024-01-18T08:13:44.156Z","createdBy":"65a149b87db8ed949769115d","_id":"65a8ddb8f1d9b256cd2df2e4"},{"createdAt":"2024-01-18T08:13:44.226Z","createdBy":"65a149b87db8ed949769115d","_id":"65a8ddb842a1832687164199"},{"createdAt":"2024-01-18T08:13:44.241Z","createdBy":"65a149b87db8ed949769115d","_id":"65a8ddb8c48c038732356432"},{"createdAt":"2024-01-18T08:13:44.407Z","createdBy":"65a149b87db8ed949769115d","_id":"65a8ddb8a1e6629c96d144a0"},{"createdAt":"2024-01-18T08:31:04.592Z","createdBy":"61c04352e452efe9e6fbcc10","_id":"65a8e1c842a183268716e6e2"},{"createdAt":"2024-01-18T09:15:36.625Z","createdBy":"65a65fd767492b96b3533bcc","_id":"65a8ec38f1d9b256cd2fbedd"},{"createdAt":"2024-01-18T09:17:55.972Z","createdBy":"65a8eca7f1d9b256cd2fc0ec","_id":"65a8ecc3544c81104f75c49f"},{"createdAt":"2024-01-18T10:16:49.758Z","createdBy":"6180a880a63936d7a7d26032","_id":"65a8fa91f1d9b256cd30ca14"},{"createdAt":"2024-01-18T10:44:25.349Z","createdBy":"65a697b6c48c03873215fd20","_id":"65a90109abdb1a3127122ab8"},{"createdAt":"2024-01-18T10:53:15.590Z","createdBy":"65a697b6c48c03873215fd20","_id":"65a9031bdd2d497c1eb332cc"},{"createdAt":"2024-01-18T12:53:47.527Z","createdBy":"65a0fe18544c81104f231f67","_id":"65a91f5b60e6486f2b92913f"},{"createdAt":"2024-01-18T12:59:26.285Z","createdBy":"65a92015abdb1a312714e164","_id":"65a920aeabdb1a312714e5ac"},{"createdAt":"2024-01-18T13:25:36.251Z","createdBy":"65a158ee42a1832687d243e9","_id":"65a926d0abdb1a312715a7cb"},{"createdAt":"2024-01-18T14:17:29.676Z","createdBy":"618e918434092cb064e5d31a","_id":"65a932f9414081736adcea9a"},{"createdAt":"2024-01-18T14:20:44.220Z","createdBy":"618e918434092cb064e5d31a","_id":"65a933bc60e6486f2b933f64"},{"createdAt":"2024-01-18T20:08:38.502Z","createdBy":"65957ee3a1ab9d9d22d6c372","_id":"65a985468dab24d43a808823"},{"createdAt":"2024-01-18T23:29:04.370Z","createdBy":"6182e2e8de4bc1dea129fb44","_id":"65a9b4404e7861d9b7b03015"},{"createdAt":"2024-01-19T08:21:00.037Z","createdBy":"61925d7013e0ddb05ef21971","_id":"65aa30ec16b070a55658d0e1"},{"createdAt":"2024-01-19T10:04:25.617Z","createdBy":"65a166997db8ed94976ba185","_id":"65aa492990238cae7d9c09a4"},{"createdAt":"2024-01-19T13:14:41.804Z","createdBy":"65a64a3b71f5d4e1773104ea","_id":"65aa75c1260a48585c8f7083"},{"createdAt":"2024-01-19T14:27:50.583Z","createdBy":"65a92015abdb1a312714e164","_id":"65aa86e65ac2160b6642f0c7"},{"createdAt":"2024-01-19T15:04:43.568Z","createdBy":"65aa8b745ac2160b6642fdbb","_id":"65aa8f8b8dab24d43a95ef56"},{"createdAt":"2024-01-19T16:01:21.677Z","createdBy":"65a4df99d29d587eb709894d","_id":"65aa9cd15ac2160b6644c737"},{"createdAt":"2024-01-19T16:27:40.344Z","createdBy":"617bc5e0a63936d7a7d21319","_id":"65aaa2fc5ac2160b66450c52"},{"createdAt":"2024-01-20T08:37:35.935Z","createdBy":"617a458da68281d7bceafb1b","_id":"65ab864f6cc2da9200d94567"},{"createdAt":"2024-01-20T08:45:23.680Z","createdBy":"65ab86bedf0ba9fe7e695aa9","_id":"65ab8823df0ba9fe7e695cd2"},{"createdAt":"2024-01-20T18:31:34.676Z","createdBy":"65ac116adf0ba9fe7e787d7c","_id":"65ac11868dab24d43aa0fd31"},{"createdAt":"2024-01-21T06:43:24.923Z","createdBy":"65acbc3e6cc2da9200e19df5","_id":"65acbd0c0cf8b13726ea17cd"},{"createdAt":"2024-01-21T17:19:23.829Z","createdBy":"629fa7f37cedd2c00d43b560","_id":"65ad521b4e7861d9b7df9fe8"},{"createdAt":"2024-01-22T00:15:50.923Z","createdBy":"65a9f6574e7861d9b7b196a1","_id":"65adb3b671942f61f92f02f8"},{"createdAt":"2024-01-22T01:52:02.415Z","createdBy":"65adca396cc2da9200e42c1b","_id":"65adca42df0ba9fe7e7f20db"},{"createdAt":"2024-01-22T05:46:22.490Z","createdBy":"65a68655d29d587eb71b499f","_id":"65ae012ec20ee7620748c6dd"},{"createdAt":"2024-01-22T07:01:41.563Z","createdBy":"65a1253e42a1832687ce34a6","_id":"65ae12d50cf8b13726efc495"},{"createdAt":"2024-01-22T09:18:15.287Z","createdBy":"65a07b0c67492b96b329140d","_id":"65ae32d7c20ee762074a5402"},{"createdAt":"2024-01-22T09:57:52.951Z","createdBy":"61815e2bb6b328de9b170695","_id":"65ae3c206cc2da9200e854fa"},{"createdAt":"2024-01-22T10:26:22.463Z","createdBy":"650d67c951de6fa4b39fb209","_id":"65ae42ce0cf8b13726f490b0"},{"createdAt":"2024-01-22T11:51:40.314Z","createdBy":"65a64e5bd29d587eb714f28a","_id":"65ae56ccdf0ba9fe7e83c2aa"},{"createdAt":"2024-01-22T12:00:10.760Z","createdBy":"65a64e5bd29d587eb714f28a","_id":"65ae58ca4e7861d9b7e7edbe"},{"createdAt":"2024-01-22T12:13:40.868Z","createdBy":"618148eba68281d7bceb7621","_id":"65ae5bf48dab24d43aac65ea"},{"createdAt":"2024-01-22T12:28:45.155Z","createdBy":"6183c553c61d67deb71a5704","_id":"65ae5f7d0cf8b13726f65254"},{"createdAt":"2024-01-22T12:44:14.912Z","createdBy":"65a93e9f260a48585c714aa4","_id":"65ae631edf0ba9fe7e844521"},{"createdAt":"2024-01-22T15:26:09.093Z","createdBy":"65a02c6da1ab9d9d2258b1f9","_id":"65ae891171942f61f9368dc0"},{"createdAt":"2024-01-23T01:01:59.331Z","createdBy":"6230f54e6f84959dba863afa","_id":"65af10078dab24d43ab1e708"},{"createdAt":"2024-01-23T03:17:02.207Z","createdBy":"618af9bc7fcd2075c57be61e","_id":"65af2faec20ee7620757efbd"},{"createdAt":"2024-01-23T09:06:55.564Z","createdBy":"6182c67dbc37e0d7a1376dce","_id":"65af81af4e7861d9b7f126fa"},{"createdAt":"2024-01-23T09:25:42.484Z","createdBy":"657342f4b676c32eb87a47b4","_id":"65af86164e7861d9b7f14b60"},{"createdAt":"2024-01-23T11:19:43.171Z","createdBy":"65a5244d67492b96b3473e2f","_id":"65afa0cf5ac2160b6683f80f"},{"createdAt":"2024-01-23T12:03:26.863Z","createdBy":"65a124417db8ed949767acd8","_id":"65afab0e0cf8b137260544f7"},{"createdAt":"2024-01-23T12:09:21.549Z","createdBy":"65a124417db8ed949767acd8","_id":"65afac7171942f61f93e46da"},{"createdAt":"2024-01-23T14:06:08.892Z","createdBy":"618a7dfaa844937e023072e4","_id":"65afc7d04e7861d9b7f6b37d"},{"createdAt":"2024-01-23T16:28:49.150Z","createdBy":"65a124417db8ed949767acd8","_id":"65afe941c20ee762075f1fe1"},{"createdAt":"2024-01-24T09:24:31.208Z","createdBy":"65a24536a1ab9d9d226e89b8","_id":"65b0d74f6cc2da9200fe1211"},{"createdAt":"2024-01-24T09:25:01.334Z","createdBy":"65a24536a1ab9d9d226e89b8","_id":"65b0d76d6cc2da9200fe14fa"},{"createdAt":"2024-01-24T10:22:09.631Z","createdBy":"65a4314471f5d4e17720103f","_id":"65b0e4d171942f61f94e7bfc"},{"createdAt":"2024-01-24T15:49:38.349Z","createdBy":"65a8eff37db8ed9497ae7162","_id":"65b131926cc2da92000c1d1b"},{"createdAt":"2024-01-24T16:33:21.597Z","createdBy":"65afe7290cf8b1372608bd1a","_id":"65b13bd1df0ba9fe7e9ec773"},{"createdAt":"2024-01-24T16:58:44.339Z","createdBy":"6183c553c61d67deb71a5704","_id":"65b141c45ac2160b6698f1ef"},{"createdAt":"2024-01-24T18:53:55.697Z","createdBy":"65affb595ac2160b66892965","_id":"65b15cc35ac2160b669a9a56"},{"createdAt":"2024-01-24T23:03:08.645Z","createdBy":"65b19712c20ee762076fef99","_id":"65b1972c0cf8b137261c4d33"},{"createdAt":"2024-01-25T05:46:52.374Z","createdBy":"61b6f722743fd4fad82ee7ee","_id":"65b1f5cc71942f61f959ee57"},{"createdAt":"2024-01-25T06:17:11.560Z","createdBy":"6256af4928fbc033f31ca225","_id":"65b1fce70cf8b137261e593a"},{"createdAt":"2024-01-25T06:18:03.293Z","createdBy":"6256af4928fbc033f31ca225","_id":"65b1fd1b71942f61f959f4a0"},{"createdAt":"2024-01-25T06:19:11.332Z","createdBy":"615460b99677ee244036ad03","_id":"65b1fd5f6cc2da9200141ff7"},{"createdAt":"2024-01-25T08:13:12.858Z","createdBy":"6180e217de4bc1dea1298bf2","_id":"65b218184e7861d9b70aa85b"},{"createdAt":"2024-01-25T09:30:46.944Z","createdBy":"65b22a3671942f61f95ba7a2","_id":"65b22a460cf8b13726206fdd"},{"createdAt":"2024-01-25T10:23:52.913Z","createdBy":"6543b83023bebf8d79710711","_id":"65b236b85ac2160b66a39d99"},{"createdAt":"2024-01-25T22:01:17.365Z","createdBy":"65b01bd171942f61f9447014","_id":"65b2da2dc20ee762077b85c7"},{"createdAt":"2024-01-26T10:24:18.173Z","createdBy":"6388664017b2aed68a1ae599","_id":"65b3885271942f61f96a7c03"},{"createdAt":"2024-01-26T12:56:38.097Z","createdBy":"65a7a12f67492b96b363b184","_id":"65b3ac06c20ee762077f62b3"},{"createdAt":"2024-01-26T14:48:29.178Z","createdBy":"65ac116adf0ba9fe7e787d7c","_id":"65b3c63d71942f61f96ec75e"},{"createdAt":"2024-01-26T16:30:42.968Z","createdBy":"65a02d71d29d587eb7e601e6","_id":"65b3de328dab24d43adf4ac7"},{"createdAt":"2024-01-26T17:53:15.720Z","createdBy":"65a2ac9871f5d4e177181dba","_id":"65b3f18b5ac2160b66b67494"},{"createdAt":"2024-01-27T02:07:39.696Z","createdBy":"64c9b35348231ffb0a006351","_id":"65b4656b0cf8b1372635c745"},{"createdAt":"2024-01-27T04:42:44.475Z","createdBy":"65b383f4c20ee762077d6e4e","_id":"65b489c46cc2da92002b960c"},{"createdAt":"2024-01-27T15:40:41.328Z","createdBy":"65b13815df0ba9fe7e9ebb40","_id":"65b523f9c20ee7620787d523"},{"createdAt":"2024-01-28T22:29:40.289Z","createdBy":"6303054bbdaa724cf61bf70a","_id":"65b6d554df0ba9fe7ec902eb"},{"createdAt":"2024-01-29T04:38:16.448Z","createdBy":"65a4c4bac48c038732066ba8","_id":"65b72bb80cf8b13726412c39"},{"createdAt":"2024-01-29T14:09:56.379Z","createdBy":"659faff642a1832687b81b6f","_id":"65b7b1b4df0ba9fe7ed00adb"},{"createdAt":"2024-01-29T15:51:34.463Z","createdBy":"65b7c9748dab24d43af89bde","_id":"65b7c9868dab24d43af89c13"},{"createdAt":"2024-01-29T16:37:15.920Z","createdBy":"61c237313e841fea1aa68921","_id":"65b7d43b4e7861d9b7376fc8"},{"createdAt":"2024-01-29T16:55:24.718Z","createdBy":"65ae3f0f5ac2160b66763f96","_id":"65b7d87cc20ee76207968522"},{"createdAt":"2024-01-30T00:34:01.617Z","createdBy":"6238f2f3da9535979b4cc6f5","_id":"65b843f90cf8b137264cf61b"},{"createdAt":"2024-01-30T08:19:22.116Z","createdBy":"61d2c87d1e6674e9cd5318cd","_id":"65b8b10a71942f61f990b845"},{"createdAt":"2024-01-30T09:04:02.952Z","createdBy":"65b8bb375ac2160b66d1202c","_id":"65b8bb82df0ba9fe7ed85e64"},{"createdAt":"2024-01-30T20:01:40.310Z","createdBy":"65b157fd0cf8b137261ae41a","_id":"65b955a45ac2160b66d94f6a"},{"createdAt":"2024-01-30T22:02:47.646Z","createdBy":"65b971fe6cc2da92004fb187","_id":"65b972075ac2160b66da440f"},{"createdAt":"2024-01-31T14:31:19.643Z","createdBy":"65ba59925ac2160b66e549c5","_id":"65ba59b78dab24d43a1119d9"},{"createdAt":"2024-01-31T15:26:23.831Z","createdBy":"65ba59925ac2160b66e549c5","_id":"65ba669f4e7861d9b74fc5e1"},{"createdAt":"2024-01-31T16:40:49.708Z","createdBy":"65b13d08df0ba9fe7e9f4a55","_id":"65ba78116cc2da92005e5120"},{"createdAt":"2024-01-31T20:45:48.245Z","createdBy":"65b13d08df0ba9fe7e9f4a55","_id":"65bab17c4e7861d9b751825c"},{"createdAt":"2024-01-31T22:57:04.528Z","createdBy":"65b73aa5df0ba9fe7eca323e","_id":"65bad040df0ba9fe7ef57ce8"},{"createdAt":"2024-02-02T05:46:19.970Z","createdBy":"65a223e77db8ed949770e9d5","_id":"65bc81ab0cf8b13726819d3d"},{"createdAt":"2024-02-02T12:04:25.094Z","createdBy":"645e0530ae5cae1188c2df9e","_id":"65bcda49c20ee76207cf4ab0"},{"createdAt":"2024-02-02T16:51:04.427Z","createdBy":"65bd1d1171942f61f9c3e7fc","_id":"65bd1d784e7861d9b76ddf0a"},{"createdAt":"2024-02-02T21:01:08.668Z","createdBy":"65b2ad9a71942f61f9653c38","_id":"65bd5814c20ee76207d58295"},{"createdAt":"2024-02-03T09:27:29.526Z","createdBy":"65be06d04e7861d9b7732d51","_id":"65be07015ac2160b660d47fe"},{"createdAt":"2024-02-03T17:59:42.030Z","createdBy":"65a957fb4e7861d9b7ab0e75","_id":"65be7f0e0cf8b137269469a1"},{"createdAt":"2024-02-05T12:04:15.098Z","createdBy":"65c0c7555ac2160b661e011e","_id":"65c0cebfc20ee76207e896da"},{"createdAt":"2024-02-05T12:04:17.079Z","createdBy":"65c0c7555ac2160b661e011e","_id":"65c0cec1df0ba9fe7e1f15da"},{"createdAt":"2024-02-05T19:32:30.673Z","createdBy":"65a6b1b9d29d587eb71dcd2e","_id":"65c137ce6cc2da92009e837c"},{"createdAt":"2024-02-06T03:22:06.274Z","createdBy":"6183373b0e457bdeb85aa79c","_id":"65c1a5de0cf8b13726a9187a"},{"createdAt":"2024-02-06T10:49:34.539Z","createdBy":"63734ff53f378b6c0610166e","_id":"65c20ebe3baf3f488521dc3a"},{"createdAt":"2024-02-06T12:43:36.140Z","createdBy":"65a1253e42a1832687ce34a6","_id":"65c22978df0ba9fe7e280473"},{"createdAt":"2024-02-06T12:57:55.948Z","createdBy":"65c22c433baf3f488522da47","_id":"65c22cd36cc2da9200a9e129"},{"createdAt":"2024-02-06T12:58:57.343Z","createdBy":"65c22c433baf3f488522da47","_id":"65c22d116cc2da9200a9e2f1"},{"createdAt":"2024-02-06T16:02:02.631Z","createdBy":"65b761f671942f61f983457a","_id":"65c257fa6cc2da9200ad3683"},{"createdAt":"2024-02-07T15:30:06.481Z","createdBy":"65a7906dc48c0387321d609a","_id":"65c3a1fe0cf8b13726c2c5b9"},{"createdAt":"2024-02-07T16:09:18.015Z","createdBy":"617954011255b34289cf3629","_id":"65c3ab2e3baf3f4885368a85"},{"createdAt":"2024-02-07T19:04:43.672Z","createdBy":"6568ce51b9b21b6e6306d571","_id":"65c3d44bc20ee7620704ab34"},{"createdAt":"2024-02-07T22:12:25.040Z","createdBy":"65b13d08df0ba9fe7e9f4a55","_id":"65c4004971942f61f90217f6"},{"createdAt":"2024-02-08T07:46:45.554Z","createdBy":"617fcadfa63936d7a7d2385c","_id":"65c486e50cf8b13726cb66ff"},{"createdAt":"2024-02-08T07:55:18.488Z","createdBy":"65a64e5bd29d587eb714f28a","_id":"65c488e68dab24d43a75af81"},{"createdAt":"2024-02-08T08:53:31.674Z","createdBy":"65a65e3571f5d4e17733f7be","_id":"65c4968b0cf8b13726cd0a01"},{"createdAt":"2024-02-08T23:18:55.337Z","createdBy":"65b19712c20ee762076fef99","_id":"65c5615f3baf3f4885491b09"},{"createdAt":"2024-02-11T08:59:03.962Z","createdBy":"65c88bf48dab24d43aa51f77","_id":"65c88c573baf3f488568f9a8"},{"createdAt":"2024-02-11T21:04:35.369Z","createdBy":"65a07fd97db8ed94975fb5b6","_id":"65c93663df0ba9fe7e66ea74"},{"createdAt":"2024-02-13T01:51:57.601Z","createdBy":"65a0624867492b96b327511d","_id":"65cacb3d71942f61f94244a1"},{"createdAt":"2024-02-13T13:06:26.809Z","createdBy":"65bba8a68dab24d43a1e9b7b","_id":"65cb69528dab24d43ac26d73"},{"createdAt":"2024-02-13T14:57:24.423Z","createdBy":"61d488247bfbeae9e5ee769b","_id":"65cb83546cc2da92001809e8"},{"createdAt":"2024-02-13T15:19:53.329Z","createdBy":"65a000f67db8ed949758a6a8","_id":"65cb889971942f61f94d2046"},{"createdAt":"2024-02-14T02:40:18.029Z","createdBy":"65cc27566cc2da92001cef96","_id":"65cc28123baf3f488591f897"},{"createdAt":"2024-02-14T07:01:20.352Z","createdBy":"65cc64114e7861d9b7f42c23","_id":"65cc65408dab24d43acc325a"},{"createdAt":"2024-02-14T18:15:00.322Z","createdBy":"65a00b1b67492b96b321aa11","_id":"65cd032471942f61f965588b"},{"createdAt":"2024-02-14T21:59:50.805Z","createdBy":"65cb9e854e7861d9b7ebf6f3","_id":"65cd37d63baf3f4885a0c53e"},{"createdAt":"2024-02-15T03:36:50.894Z","createdBy":"65a22140a1ab9d9d226dcc87","_id":"65cd86d24e7861d9b7015ea2"},{"createdAt":"2024-02-15T15:21:39.394Z","createdBy":"65b18ccc71942f61f9584cc7","_id":"65ce2c03c85ec2286f528f6b"},{"createdAt":"2024-02-15T17:45:48.754Z","createdBy":"65b03de8df0ba9fe7e93845b","_id":"65ce4dccc20ee762077729f9"},{"createdAt":"2024-02-15T22:35:15.762Z","createdBy":"65a9d6f990238cae7d92aafd","_id":"65ce91a36cc2da9200401938"},{"createdAt":"2024-02-15T22:37:52.152Z","createdBy":"65a9d6f990238cae7d92aafd","_id":"65ce9240e919dffe568179a2"},{"createdAt":"2024-02-16T08:22:51.209Z","createdBy":"65a93e9f260a48585c714aa4","_id":"65cf1b5bc85ec2286f5bbfd4"},{"createdAt":"2024-02-16T08:41:35.162Z","createdBy":"65cde3058dab24d43adcdb8a","_id":"65cf1fbfdf0ba9fe7eafcb42"},{"createdAt":"2024-02-16T10:10:12.449Z","createdBy":"65c487423baf3f48853d4999","_id":"65cf3484c85ec2286f605a93"},{"createdAt":"2024-02-16T15:42:43.337Z","createdBy":"61963e9613e0ddb05ef2d320","_id":"65cf82738dab24d43af238cb"},{"createdAt":"2024-02-16T15:53:45.812Z","createdBy":"65cdda72e919dffe5675c8fd","_id":"65cf8509e919dffe56908109"},{"createdAt":"2024-02-17T16:21:41.577Z","createdBy":"65d0dcfc8dab24d43affea8f","_id":"65d0dd154e7861d9b728ccb0"},{"createdAt":"2024-02-17T23:55:23.517Z","createdBy":"65b19712c20ee762076fef99","_id":"65d1476b8dab24d43a03dd3d"},{"createdAt":"2024-02-18T10:35:20.266Z","createdBy":"65b98368df0ba9fe7ee3ca41","_id":"65d1dd684e7861d9b7306441"},{"createdAt":"2024-02-19T01:53:14.809Z","createdBy":"65a07fd97db8ed94975fb5b6","_id":"65d2b48ac20ee762079a9df5"},{"createdAt":"2024-02-19T07:55:10.222Z","createdBy":"65ae970b4e7861d9b7eaffa8","_id":"65d3095ee919dffe56af32d8"},{"createdAt":"2024-02-19T08:45:03.672Z","createdBy":"65a9bbf716b070a55653bd64","_id":"65d3150f6cc2da92006b4c7a"},{"createdAt":"2024-02-19T10:03:38.455Z","createdBy":"65bb72866cc2da920069be26","_id":"65d3277a6cc2da92006cae58"},{"createdAt":"2024-02-19T10:04:53.239Z","createdBy":"65a7a12f67492b96b363b184","_id":"65d327c5c85ec2286f8669be"},{"createdAt":"2024-02-19T14:16:43.174Z","createdBy":"65a15817d29d587eb7f420a4","_id":"65d362cbc85ec2286f899990"},{"createdAt":"2024-02-19T14:16:51.330Z","createdBy":"65a15817d29d587eb7f420a4","_id":"65d362d3c85ec2286f899b4f"},{"createdAt":"2024-02-19T17:40:40.349Z","createdBy":"65a972690cf8b13726c70785","_id":"65d39298c85ec2286f8c48d2"},{"createdAt":"2024-02-19T17:51:42.057Z","createdBy":"65bdf85371942f61f9c9efc3","_id":"65d3952ec85ec2286f8c4c2f"},{"createdAt":"2024-02-20T00:23:51.512Z","createdBy":"65d3edec4e7861d9b73fd69f","_id":"65d3f117df0ba9fe7ed8d5ec"},{"createdAt":"2024-02-20T01:18:08.854Z","createdBy":"65d31e1a8dab24d43a0a26ae","_id":"65d3fdd0df0ba9fe7ed8dad8"},{"createdAt":"2024-02-20T07:12:55.379Z","createdBy":"65ae39bc4e7861d9b7e565c9","_id":"65d450f73baf3f4885eef76c"},{"createdAt":"2024-02-20T08:22:26.432Z","createdBy":"617a5696b6b328de9b168847","_id":"65d46142e919dffe56becdba"},{"createdAt":"2024-02-20T21:37:43.238Z","createdBy":"64a58ec19c231387e114d068","_id":"65d51ba7c85ec2286fa1539c"},{"createdAt":"2024-02-21T14:06:48.664Z","createdBy":"65b13815df0ba9fe7e9ebb40","_id":"65d603784e7861d9b7572c0e"},{"createdAt":"2024-02-21T20:22:38.523Z","createdBy":"65a147d571f5d4e1770c2b6b","_id":"65d65b8e4e7861d9b75bded2"},{"createdAt":"2024-02-21T21:45:40.270Z","createdBy":"64089c1d986b3858a5c9de5e","_id":"65d66f04c20ee76207c4d70a"},{"createdAt":"2024-02-21T21:46:52.823Z","createdBy":"64089c1d986b3858a5c9de5e","_id":"65d66f4c8dab24d43a3511a9"},{"createdAt":"2024-02-21T22:19:07.296Z","createdBy":"657ac915aa6ec4620ecbad14","_id":"65d676dbe919dffe56d91438"},{"createdAt":"2024-02-22T01:36:52.808Z","createdBy":"65a6d60a67492b96b35bc6ed","_id":"65d6a534c20ee76207c668f0"},{"createdAt":"2024-02-22T11:21:24.513Z","createdBy":"65a7efd97db8ed9497a3356d","_id":"65d72e34e919dffe56e1e764"},{"createdAt":"2024-02-22T11:43:35.530Z","createdBy":"65ae39bc4e7861d9b7e565c9","_id":"65d73367c85ec2286fbb88a5"},{"createdAt":"2024-02-22T16:45:22.686Z","createdBy":"65cbb4fa4e7861d9b7ec90bb","_id":"65d77a223baf3f48851bf0f3"},{"createdAt":"2024-02-22T17:50:50.809Z","createdBy":"64e6904b80a3a09378491886","_id":"65d7897ae919dffe56e9f86f"},{"createdAt":"2024-02-23T09:19:05.507Z","createdBy":"65d862f2e919dffe56f30d0d","_id":"65d863093baf3f4885240c3e"},{"createdAt":"2024-02-23T14:52:13.025Z","createdBy":"65cb96bb0cf8b137261b9f77","_id":"65d8b11dc85ec2286fd542e9"},{"createdAt":"2024-02-23T19:33:51.037Z","createdBy":"65c1ff1fdf0ba9fe7e25f844","_id":"65d8f31fc20ee76207e18454"},{"createdAt":"2024-02-24T15:47:14.318Z","createdBy":"65aaafc28dab24d43a97d43f","_id":"65da0f82c85ec2286fe897e0"},{"createdAt":"2024-02-24T17:37:17.626Z","createdBy":"65b52b0adf0ba9fe7ec2b44f","_id":"65da294d4e7861d9b780ad14"},{"createdAt":"2024-02-25T10:05:36.631Z","createdBy":"658ac410a1ab9d9d22935607","_id":"65db10f0c20ee76207ef1bfc"},{"createdAt":"2024-02-25T10:05:36.638Z","createdBy":"658ac410a1ab9d9d22935607","_id":"65db10f06cc2da9200d0298c"},{"createdAt":"2024-02-26T03:50:44.634Z","createdBy":"65adc32d0cf8b13726edfb21","_id":"65dc0a94c85ec2286ff30e42"},{"createdAt":"2024-02-26T04:01:08.804Z","createdBy":"63684725d24fd29726d2d168","_id":"65dc0d048dab24d43a6a55a5"},{"createdAt":"2024-02-26T09:24:27.066Z","createdBy":"6183373b0e457bdeb85aa79c","_id":"65dc58cbc85ec2286ff4e9aa"},{"createdAt":"2024-02-26T10:45:56.344Z","createdBy":"65ae344c5ac2160b66758f89","_id":"65dc6be46cc2da9200d83398"},{"createdAt":"2024-02-26T11:14:03.212Z","createdBy":"65b3c1dadf0ba9fe7eb6f778","_id":"65dc727bc20ee76207f749b9"},{"createdAt":"2024-02-26T13:27:57.726Z","createdBy":"65c4b3ef6cc2da9200ce03a8","_id":"65dc91ddc85ec2286ff7fb80"},{"createdAt":"2024-02-26T13:55:19.194Z","createdBy":"65b7c9748dab24d43af89bde","_id":"65dc98476cc2da9200dab244"},{"createdAt":"2024-02-26T19:29:07.802Z","createdBy":"65a9807216b070a55650d3a3","_id":"65dce6836cc2da9200dc8b24"},{"createdAt":"2024-02-27T00:37:13.173Z","createdBy":"65c0c7555ac2160b661e011e","_id":"65dd2eb98dab24d43a737889"},{"createdAt":"2024-02-27T06:53:42.282Z","createdBy":"65a65fd767492b96b3533bcc","_id":"65dd86f6e919dffe5624092f"},{"createdAt":"2024-02-27T09:56:02.859Z","createdBy":"65a6894ad29d587eb71b52b0","_id":"65ddb1b2c85ec2286f04ba76"},{"createdAt":"2024-02-27T12:31:04.991Z","createdBy":"65b8e12c0cf8b1372653c36c","_id":"65ddd608c85ec2286f074632"},{"createdAt":"2024-02-27T13:49:49.361Z","createdBy":"65c5fbc66cc2da9200df138f","_id":"65dde87d8dab24d43a7cddab"},{"createdAt":"2024-02-27T22:02:30.359Z","createdBy":"65aa870816b070a55662732d","_id":"65de5bf63baf3f48855d6af9"},{"createdAt":"2024-02-27T22:12:14.673Z","createdBy":"65aa870816b070a55662732d","_id":"65de5e3e6cc2da9200f0b20d"},{"createdAt":"2024-02-28T08:58:31.363Z","createdBy":"65a64e5bd29d587eb714f28a","_id":"65def5b7c20ee762070c908d"},{"createdAt":"2024-02-28T09:07:55.404Z","createdBy":"65a124417db8ed949767acd8","_id":"65def7eb6cc2da9200f556bc"},{"createdAt":"2024-02-28T10:48:22.708Z","createdBy":"65a65fd767492b96b3533bcc","_id":"65df0f76e919dffe563af19b"},{"createdAt":"2024-02-28T14:49:43.495Z","createdBy":"65deee2b6cc2da9200f50e8b","_id":"65df48076cc2da9200fbe022"},{"createdAt":"2024-02-28T15:14:55.194Z","createdBy":"65de4e534e7861d9b7a9f549","_id":"65df4def4e7861d9b7be2485"},{"createdAt":"2024-02-28T16:05:24.031Z","createdBy":"65a9807216b070a55650d3a3","_id":"65df59c48dab24d43a94b4c7"},{"createdAt":"2024-02-28T17:18:28.406Z","createdBy":"65ac116adf0ba9fe7e787d7c","_id":"65df6ae4c85ec2286f229c7a"},{"createdAt":"2024-02-28T17:18:28.503Z","createdBy":"65ac116adf0ba9fe7e787d7c","_id":"65df6ae4c20ee76207137b45"},{"createdAt":"2024-02-28T17:22:58.551Z","createdBy":"65df6be1c85ec2286f22af3e","_id":"65df6bf2e919dffe564190f9"},{"createdAt":"2024-02-28T18:09:21.076Z","createdBy":"65b94f7d4e7861d9b744057a","_id":"65df76d18dab24d43a9666b3"},{"createdAt":"2024-02-28T19:17:08.971Z","createdBy":"63176b10eed07516673234a2","_id":"65df86b4e919dffe56424905"},{"createdAt":"2024-02-29T00:49:18.344Z","createdBy":"65a85f1142a1832687137100","_id":"65dfd48ee919dffe5645a4eb"},{"createdAt":"2024-02-29T01:45:12.229Z","createdBy":"65a22140a1ab9d9d226dcc87","_id":"65dfe1a8c85ec2286f275a24"},{"createdAt":"2024-02-29T07:01:33.889Z","createdBy":"65a4eba3a1ab9d9d227dc444","_id":"65e02bcd6cc2da92000b2cb7"},{"createdAt":"2024-02-29T15:08:29.182Z","createdBy":"65b7c9748dab24d43af89bde","_id":"65e09dedc85ec2286f3672ab"},{"createdAt":"2024-02-29T15:17:38.562Z","createdBy":"65dcf4128dab24d43a728893","_id":"65e0a012e919dffe565277ac"},{"createdAt":"2024-02-29T15:51:24.218Z","createdBy":"65cb9e854e7861d9b7ebf6f3","_id":"65e0a7fc8dab24d43aa789e3"},{"createdAt":"2024-02-29T17:21:01.098Z","createdBy":"65a2dca2a1ab9d9d22759646","_id":"65e0bcfd3baf3f48858374df"},{"createdAt":"2024-03-01T14:13:27.007Z","createdBy":"65a649b5a1ab9d9d2288fa56","_id":"65e1e287df0ba9fe7e79de1e"},{"createdAt":"2024-03-01T19:16:20.298Z","createdBy":"65a9a0c30cf8b13726c863bf","_id":"65e229846cc2da9200303143"},{"createdAt":"2024-03-01T20:03:14.442Z","createdBy":"65b52b0adf0ba9fe7ec2b44f","_id":"65e23482df0ba9fe7e7e300a"},{"createdAt":"2024-03-01T22:27:20.268Z","createdBy":"659705b8544c81104fbfc6b2","_id":"65e256486cc2da9200328849"},{"createdAt":"2024-03-01T22:53:58.099Z","createdBy":"65e1f41dc20ee762073bfd71","_id":"65e25c863baf3f48859a6d7d"},{"createdAt":"2024-03-02T13:34:37.352Z","createdBy":"65affb595ac2160b66892965","_id":"65e32aedc20ee76207469444"},{"createdAt":"2024-03-03T23:10:49.273Z","createdBy":"65a83ed1a1ab9d9d22a86743","_id":"65e503798dab24d43acf3152"},{"createdAt":"2024-03-04T11:17:37.300Z","createdBy":"65a8137c7db8ed9497a6a32f","_id":"65e5add18dab24d43ad6e4dd"},{"createdAt":"2024-03-04T11:23:14.376Z","createdBy":"65a14f4c71f5d4e1770ce5b8","_id":"65e5af22c20ee7620756a78a"},{"createdAt":"2024-03-04T23:39:59.213Z","createdBy":"65a4d1a6a1ab9d9d227d73aa","_id":"65e65bcf3baf3f4885bfeaa0"},{"createdAt":"2024-03-05T07:17:43.520Z","createdBy":"65d49c6ce919dffe56c4613b","_id":"65e6c7173baf3f4885c1d47d"},{"createdAt":"2024-03-05T08:28:03.706Z","createdBy":"65a12c8d544c81104f24eb4a","_id":"65e6d793c20ee76207613456"},{"createdAt":"2024-03-05T08:50:11.709Z","createdBy":"65a7a12f67492b96b363b184","_id":"65e6dcc36cc2da92005ad144"},{"createdAt":"2024-03-05T09:15:10.808Z","createdBy":"65a2ae607db8ed949775c990","_id":"65e6e29e6cc2da92005b3e23"},{"createdAt":"2024-03-05T16:44:36.635Z","createdBy":"65aaa6ba5ac2160b664673fd","_id":"65e74bf4df0ba9fe7eb02f57"},{"createdAt":"2024-03-05T17:46:57.725Z","createdBy":"65a8eff37db8ed9497ae7162","_id":"65e75a918dab24d43af058c1"},{"createdAt":"2024-03-05T21:04:28.784Z","createdBy":"65ae823b71942f61f9364c28","_id":"65e788dce919dffe56a35e5a"},{"createdAt":"2024-03-06T02:04:23.582Z","createdBy":"65e7cf04c20ee7620775da06","_id":"65e7cf27c20ee7620775da26"},{"createdAt":"2024-03-06T07:49:49.707Z","createdBy":"65a7a288544c81104f5ab011","_id":"65e8201de919dffe56aa6ef7"},{"createdAt":"2024-03-06T14:45:00.742Z","createdBy":"65e88141c85ec2286f96147e","_id":"65e8816c8dab24d43a05a9b7"},{"createdAt":"2024-03-06T19:36:59.403Z","createdBy":"65a2ece467492b96b33cbc3d","_id":"65e8c5db3baf3f4885f05a71"},{"createdAt":"2024-03-06T22:56:10.119Z","createdBy":"65d6726d3baf3f48850c70b4","_id":"65e8f48ac85ec2286fa09814"},{"createdAt":"2024-03-07T00:39:25.136Z","createdBy":"65d6726d3baf3f48850c70b4","_id":"65e90cbd3baf3f4885f36b46"},{"createdAt":"2024-03-07T03:15:57.846Z","createdBy":"65cbc9b76cc2da92001aa176","_id":"65e9316d6cc2da9200824a2e"},{"createdAt":"2024-03-07T18:39:48.848Z","createdBy":"65b145ba0cf8b13726184dd0","_id":"65ea09f41de51b84d4e0bbeb"},{"createdAt":"2024-03-07T19:03:23.728Z","createdBy":"65ae823b71942f61f9364c28","_id":"65ea0f7b673a4618e7f75e91"},{"createdAt":"2024-03-08T03:14:44.770Z","createdBy":"65adc32d0cf8b13726edfb21","_id":"65ea82a41de51b84d4e3b7ea"},{"createdAt":"2024-03-08T10:47:46.403Z","createdBy":"65a65fd767492b96b3533bcc","_id":"65eaecd226355118f55d2699"},{"createdAt":"2024-03-08T11:26:44.470Z","createdBy":"6268fd56efb6e650011e633f","_id":"65eaf5f43766ec7273c2231c"},{"createdAt":"2024-03-08T16:38:45.756Z","createdBy":"65b3c09571942f61f96e8204","_id":"65eb3f15fb41b50912549a46"},{"createdAt":"2024-03-08T20:21:17.964Z","createdBy":"65a6d60a67492b96b35bc6ed","_id":"65eb733d80382e44e49ab3b1"},{"createdAt":"2024-03-08T20:58:51.468Z","createdBy":"65a183d3a1ab9d9d226a27e0","_id":"65eb7c0b1de51b84d4f4e289"},{"createdAt":"2024-03-09T01:32:57.455Z","createdBy":"65b572778dab24d43aeb696c","_id":"65ebbc4926355118f56fe270"},{"createdAt":"2024-03-11T12:26:50.390Z","createdBy":"65ba09426cc2da920057c335","_id":"65eef88a26355118f587e1ea"},{"createdAt":"2024-03-11T14:41:21.855Z","createdBy":"65a3be3071f5d4e1771e65ce","_id":"65ef181126355118f58a812d"},{"createdAt":"2024-03-12T08:12:10.029Z","createdBy":"65ab244871942f61f91f62c2","_id":"65f00e5a128aa1fbe155333d"},{"createdAt":"2024-03-12T08:56:17.938Z","createdBy":"65a0f92c42a1832687c95504","_id":"65f018b180382e44e4cebfa5"},{"createdAt":"2024-03-12T13:48:24.352Z","createdBy":"65a65fd767492b96b3533bcc","_id":"65f05d28673a4618e7446782"},{"createdAt":"2024-03-12T15:37:26.289Z","createdBy":"65a9807216b070a55650d3a3","_id":"65f076b6673a4618e746e702"},{"createdAt":"2024-03-12T15:44:42.085Z","createdBy":"65b19712c20ee762076fef99","_id":"65f0786a3766ec727304101e"},{"createdAt":"2024-03-12T16:12:41.052Z","createdBy":"659c14c0c48c038732a528c2","_id":"65f07ef91de51b84d423c946"},{"createdAt":"2024-03-12T16:12:41.406Z","createdBy":"659c14c0c48c038732a528c2","_id":"65f07ef93766ec72730447ba"},{"createdAt":"2024-03-12T16:12:41.528Z","createdBy":"659c14c0c48c038732a528c2","_id":"65f07ef9fb41b5091284e3bb"},{"createdAt":"2024-03-12T16:12:59.518Z","createdBy":"6447ef5eae5cae1188b6bc87","_id":"65f07f0b128aa1fbe1603c81"},{"createdAt":"2024-03-13T02:21:08.559Z","createdBy":"65c6671a4e7861d9b7c6cca5","_id":"65f10d943766ec72730b11be"},{"createdAt":"2024-03-13T14:14:01.749Z","createdBy":"65f1b448673a4618e7564d61","_id":"65f1b4a989f1841e6a291408"},{"createdAt":"2024-03-13T14:40:47.279Z","createdBy":"65ba853471942f61f9a99b34","_id":"65f1baef673a4618e756ef48"},{"createdAt":"2024-03-13T15:06:19.263Z","createdBy":"65a6dca0c48c0387321955b1","_id":"65f1c0eb1de51b84d43a6978"},{"createdAt":"2024-03-13T19:48:48.952Z","createdBy":"6581ee1dbbc653e035044be6","_id":"65f203201de51b84d43d1a24"},{"createdAt":"2024-03-14T06:29:56.640Z","createdBy":"65d0461fc20ee762078cf8d5","_id":"65f2996426355118f5bf3e5c"},{"createdAt":"2024-03-14T09:15:30.801Z","createdBy":"65a67af9544c81104f4bd562","_id":"65f2c03289f1841e6a345d5d"},{"createdAt":"2024-03-14T09:17:43.925Z","createdBy":"65a67af9544c81104f4bd562","_id":"65f2c0b7fb41b509129e861d"},{"createdAt":"2024-03-14T09:24:58.987Z","createdBy":"6409d59a0845515c144bd209","_id":"65f2c26afb41b509129eb43f"},{"createdAt":"2024-03-14T12:30:13.807Z","createdBy":"65a697b6c48c03873215fd20","_id":"65f2edd5128aa1fbe1840008"},{"createdAt":"2024-03-14T18:34:33.770Z","createdBy":"65a81e8342a18326870ce1c2","_id":"65f343391de51b84d44fd80a"},{"createdAt":"2024-03-14T18:36:19.849Z","createdBy":"65a81e8342a18326870ce1c2","_id":"65f343a389f1841e6a41dc21"},{"createdAt":"2024-03-15T13:31:27.335Z","createdBy":"65a00141a1ab9d9d22541a6d","_id":"65f44daf1de51b84d45eefb1"},{"createdAt":"2024-03-15T13:38:24.555Z","createdBy":"65b13b24c20ee762076d14b7","_id":"65f44f50673a4618e781e372"},{"createdAt":"2024-03-16T17:03:26.387Z","createdBy":"659705b8544c81104fbfc6b2","_id":"65f5d0defb41b50912cdf507"},{"createdAt":"2024-03-18T02:24:54.448Z","createdBy":"65a223e77db8ed949770e9d5","_id":"65f7a5f61de51b84d47ae532"},{"createdAt":"2024-03-18T12:12:42.788Z","createdBy":"65b77e1c0cf8b13726439273","_id":"65f82fba3766ec72736f6f1c"},{"createdAt":"2024-03-19T02:42:25.276Z","createdBy":"65a22140a1ab9d9d226dcc87","_id":"65f8fb913766ec727377ba5d"},{"createdAt":"2024-03-19T03:35:16.388Z","createdBy":"65a07b0c67492b96b329140d","_id":"65f907f4128aa1fbe1befa8b"},{"createdAt":"2024-03-19T09:26:52.995Z","createdBy":"65a02c6da1ab9d9d2258b1f9","_id":"65f95a5c80382e44e4620930"}],"createdAt":"2024-01-11T13:08:56.758Z","updatedAt":"2024-03-19T09:26:52.996Z","__v":0,"updatedBy":"65a02c6da1ab9d9d2258b1f9"}