{"_id":"65a9ab868dab24d43a825b52","createdBy":"6099504c693d8c00155df91f","deleted":false,"parentDocument":{"_id":"65a9ab7a8dab24d43a82379d","metadata":{"userGroup":[],"docType":{"showInFluidsPortal":false,"showInTyrePortal":false,"_id":"613771844b25a79f6947d0d8","showInHandbookPortal":false},"reference":"","validFrom":"2024-01-18T22:51:38.303Z","applicabilities":[{"vinRanges":[{"start":"966534","end":"BF1182"}],"modelYears":[{"start":2020,"end":2023}],"products":["HJ7"],"chassisStart":"","chassisEnd":"","markets":[],"inverse":false,"engineNumberRanges":[]}],"negativeApplicabilities":[]}},"id":"1605797131","title":"Cylinder Head","content":[{"node":"title","body":[{"node":"text","body":"Cylinder Head"}]},{"node":"textmodule","body":[{"node":"title","body":[{"node":"text","body":"Cylinder head torques"}]},{"node":"text","body":"\r\n"},{"node":"table-container","body":[{"node":"text","body":" \r\n"},{"node":"table","body":[{"node":"thead","body":[{"node":"tr","body":[{"node":"th","body":[{"node":"p","body":[{"node":"text","body":"Application"}],"type":"p_table_lb"}]},{"node":"text","body":" \r\n"},{"node":"th","body":[{"node":"p","body":[{"node":"text","body":"Torque (Nm)"}],"type":"p_table_lb"}]},{"node":"text","body":" \r\n"},{"node":"th","body":[{"node":"p","body":[{"node":"text","body":"Notes"}],"type":"p_table_lb"}]},{"node":"text","body":" "}]},{"node":"text","body":" "}]},{"node":"tbody","body":[{"node":"tr","body":[{"node":"td","body":[{"node":"p","body":[{"node":"text","body":"Camshaft cover to cylinder head"}],"type":"p_table_l"}]},{"node":"text","body":" \r\n"},{"node":"td","body":[{"node":"p","body":[{"node":"text","body":"*"}],"type":"p_table_c"}]},{"node":"text","body":" \r\n"},{"node":"td","body":[{"node":"p","body":[{"node":"text","body":"See "},{"node":"link","body":[{"node":"text","body":"Camshaft Cover - Installation"}],"target-id":"54043197065148299-2","target-base-id":"1536702347"}],"type":"p_table_l"},{"node":"text","body":" \r\n"},{"node":"p","body":[{"node":"variable","body":[{"node":"text","body":"Apply clean engine oil to the seal(s)"}]}],"type":"p_table_l"}]},{"node":"text","body":" "}]},{"node":"text","body":" \r\n"},{"node":"tr","body":[{"node":"td","body":[{"node":"p","body":[{"node":"text","body":"Camshaft drive chain tensioner to cylinder barrel"}],"type":"p_table_l"}]},{"node":"text","body":" \r\n"},{"node":"td","body":[{"node":"p","body":[{"node":"variable","body":[{"node":"text","body":"9 Nm"}]}],"type":"p_table_c"}]},{"node":"text","body":" \r\n"},{"node":"td","body":[]},{"node":"text","body":" "}]},{"node":"text","body":" \r\n"},{"node":"tr","body":[{"node":"td","body":[{"node":"p","body":[{"node":"text","body":"Secondary air injection valve covers to camshaft cover"}],"type":"p_table_l"}]},{"node":"text","body":" \r\n"},{"node":"td","body":[{"node":"p","body":[{"node":"variable","body":[{"node":"text","body":"9 Nm"}]}],"type":"p_table_c"}]},{"node":"text","body":" \r\n"},{"node":"td","body":[]},{"node":"text","body":" "}]},{"node":"text","body":" \r\n"},{"node":"tr","body":[{"node":"td","body":[{"node":"p","body":[{"node":"text","body":"Camshaft ladder to cylinder head"}],"type":"p_table_l"}]},{"node":"text","body":" \r\n"},{"node":"td","body":[{"node":"p","body":[{"node":"variable","body":[{"node":"text","body":"*"}]}],"type":"p_table_c"}]},{"node":"text","body":" \r\n"},{"node":"td","body":[{"node":"p","body":[{"node":"text","body":"See "},{"node":"link","body":[{"node":"text","body":"Camshaft - Installation and Timing"}],"target-id":"36028798555719819-2","target-base-id":"1536755851"}],"type":"p_table_l"}]},{"node":"text","body":" "}]},{"node":"text","body":" \r\n"},{"node":"tr","body":[{"node":"td","body":[{"node":"p","body":[{"node":"text","body":"Camshaft sprocket to camshaft"}],"type":"p_table_l"}]},{"node":"text","body":" \r\n"},{"node":"td","body":[{"node":"p","body":[{"node":"variable","body":[{"node":"text","body":"16 Nm"}]}],"type":"p_table_c"}]},{"node":"text","body":" \r\n"},{"node":"td","body":[]},{"node":"text","body":" "}]},{"node":"text","body":" \r\n"},{"node":"tr","body":[{"node":"td","body":[{"node":"p","body":[{"node":"text","body":"Cylinder head nuts"}],"type":"p_table_l"}]},{"node":"text","body":" \r\n"},{"node":"td","body":[{"node":"p","body":[{"node":"variable","body":[{"node":"text","body":"*"}]}],"type":"p_table_c"}]},{"node":"text","body":" \r\n"},{"node":"td","body":[{"node":"p","body":[{"node":"text","body":"See "},{"node":"link","body":[{"node":"text","body":"Cylinder Head - Installation"}],"target-id":"45035997810529163-2","target-base-id":"1536824203"}],"type":"p_table_l"}]},{"node":"text","body":" "}]},{"node":"text","body":" \r\n"},{"node":"tr","body":[{"node":"td","body":[{"node":"p","body":[{"node":"text","body":"Cylinder head M6 x 88 mm fixings"}],"type":"p_table_l"}]},{"node":"text","body":" \r\n"},{"node":"td","body":[{"node":"p","body":[{"node":"variable","body":[{"node":"text","body":"10 Nm"}]}],"type":"p_table_c"}]},{"node":"text","body":" \r\n"},{"node":"td","body":[]},{"node":"text","body":" "}]},{"node":"text","body":" \r\n"},{"node":"tr","body":[{"node":"td","body":[{"node":"p","body":[{"node":"text","body":"Spark plugs"}],"type":"p_table_l"}]},{"node":"text","body":" \r\n"},{"node":"td","body":[{"node":"p","body":[{"node":"variable","body":[{"node":"text","body":"12 Nm"}]}],"type":"p_table_c"}]},{"node":"text","body":" \r\n"},{"node":"td","body":[]},{"node":"text","body":" "}]},{"node":"text","body":" \r\n"},{"node":"tr","body":[{"node":"td","body":[{"node":"p","body":[{"node":"text","body":"Exhaust stud to cylinder head"}],"type":"p_table_l"}]},{"node":"text","body":" \r\n"},{"node":"td","body":[{"node":"p","body":[{"node":"variable","body":[{"node":"text","body":"10 Nm"}]}],"type":"p_table_c"}]},{"node":"text","body":" \r\n"},{"node":"td","body":[{"node":"p","body":[{"node":"variable","body":[{"node":"text","body":"Fit new fixing(s) if loosened or removed"}]}],"type":"p_table_l"}]},{"node":"text","body":" "}]},{"node":"text","body":" \r\n"},{"node":"tr","body":[{"node":"td","body":[{"node":"p","body":[{"node":"text","body":"Timing torque limiter"}],"type":"p_table_l"}]},{"node":"text","body":" \r\n"},{"node":"td","body":[{"node":"p","body":[{"node":"variable","body":[{"node":"text","body":"0.6 Nm"}]}],"type":"p_table_c"}]},{"node":"text","body":" \r\n"},{"node":"td","body":[]},{"node":"text","body":" "}]},{"node":"text","body":" \r\n"},{"node":"tr","body":[{"node":"td","body":[{"node":"p","body":[{"node":"text","body":"Cylinder head bypass spigot"}],"type":"p_table_l"}]},{"node":"text","body":" \r\n"},{"node":"td","body":[{"node":"p","body":[{"node":"variable","body":[{"node":"text","body":"15 Nm"}]}],"type":"p_table_c"}]},{"node":"text","body":" \r\n"},{"node":"td","body":[{"node":"p","body":[{"node":"variable","body":[{"node":"text","body":"Fit new fixing(s) if loosened or removed"}]}],"type":"p_table_l"}]},{"node":"text","body":" "}]},{"node":"text","body":" \r\n"},{"node":"tr","body":[{"node":"td","body":[{"node":"p","body":[{"node":"text","body":"Cylinder head blanking plug"}],"type":"p_table_l"}]},{"node":"text","body":" \r\n"},{"node":"td","body":[{"node":"p","body":[{"node":"variable","body":[{"node":"text","body":"25 Nm"}]}],"type":"p_table_c"}]},{"node":"text","body":" \r\n"},{"node":"td","body":[{"node":"p","body":[{"node":"variable","body":[{"node":"text","body":"Fit new fixing(s) if loosened or removed"}]}],"type":"p_table_l"}]},{"node":"text","body":" "}]},{"node":"text","body":" \r\n"},{"node":"tr","body":[{"node":"td","body":[{"node":"p","body":[{"node":"text","body":"Sound suppression bolt"}],"type":"p_table_l"}]},{"node":"text","body":" \r\n"},{"node":"td","body":[{"node":"p","body":[{"node":"variable","body":[{"node":"text","body":"12 Nm"}]}],"type":"p_table_c"}]},{"node":"text","body":" \r\n"},{"node":"td","body":[]},{"node":"text","body":" "}]},{"node":"text","body":" "}]}],"widths":"9.499600000000001 2.49936 5.4991","type":"scaled"}],"type":"header"},{"node":"text","body":" "}],"metadata":{"ModelsTaxonomyLink":"HJ7; HH7; HG7; HD7 (do not use - delete if found in use); HD6; HD5; HD2; HD","MarketsTaxonomyLink":"All"},"type":"TextModule"}],"ancestors":["1342111883"],"parent":"1342111883","lastUpdate":"2023-11-13T11:03:01.000Z","metadata":{"markets":["All"],"_id":"65a9ab868dab24d43a825b53"},"search":["Cylinder Head","Application","Torque (Nm)","Notes","Camshaft cover to cylinder head","*","See ","Camshaft Cover - Installation","Apply clean engine oil to the seal(s)","Camshaft drive chain tensioner to cylinder barrel","9 Nm","Secondary air injection valve covers to camshaft cover","9 Nm","Camshaft ladder to cylinder head","*","See ","Camshaft - Installation and Timing","Camshaft sprocket to camshaft","16 Nm","Cylinder head nuts","*","See ","Cylinder Head - Installation","Cylinder head M6 x 88 mm fixings","10 Nm","Spark plugs","12 Nm","Exhaust stud to cylinder head","10 Nm","Fit new fixing(s) if loosened or removed","Timing torque limiter","0.6 Nm","Cylinder head bypass spigot","15 Nm","Fit new fixing(s) if loosened or removed","Cylinder head blanking plug","25 Nm","Fit new fixing(s) if loosened or removed","Sound suppression bolt","12 Nm"],"viewCount":19,"infoType":"InfoType07","views":[{"createdBy":"65a649b5a1ab9d9d2288fa56","createdAt":"2024-01-19T17:36:36.155Z","_id":"65afeb39df0ba9fe7e90ddba"},{"createdBy":"65a649b5a1ab9d9d2288fa56","createdAt":"2024-01-18T14:47:25.427Z","_id":"65b0e7db8dab24d43ac16f60"},{"createdBy":"65a4db347db8ed94977f912c","createdAt":"2024-01-18T14:47:25.427Z","_id":"65b365de8dab24d43ad811ac"},{"createdBy":"65280038cfb8c4ac0d87750f","createdAt":"2024-01-18T14:47:25.427Z","_id":"65bbb2478dab24d43a1fd992"},{"createdBy":"65280038cfb8c4ac0d87750f","createdAt":"2024-01-18T23:18:14.877Z","_id":"65bbb2ebc20ee76207c1ad97"},{"createdBy":"65280038cfb8c4ac0d87750f","createdAt":"2024-01-18T14:46:30.166Z","_id":"65bbb4010cf8b1372677d65f"},{"createdBy":"61838f7cde4bc1dea12a0fe9","createdAt":"2024-01-18T14:46:30.166Z","_id":"65bd43060cf8b137268b486c"},{"createdBy":"65a5ed43544c81104f44c74f","createdAt":"2024-01-19T19:38:49.590Z","_id":"65c3280371942f61f9f45be6"},{"createdBy":"657d0c58860cd52a9fddc029","createdAt":"2024-01-19T19:38:49.590Z","_id":"65c4466871942f61f9039e6c"},{"createdBy":"61838f7cde4bc1dea12a0fe9","createdAt":"2024-02-05T17:31:52.169Z","_id":"65c8ffdc3baf3f48856aefea"},{"createdBy":"65b1a1305ac2160b669c9eea","createdAt":"2024-01-18T14:47:25.059Z","_id":"65d8eb574e7861d9b7779836"},{"createdBy":"63851ac88776a76bf287e00b","createdAt":"2024-01-18T23:18:14.877Z","_id":"65e504dec20ee7620750295a"},{"createdBy":"65e50a248dab24d43acf926e","createdAt":"2024-01-18T14:47:25.059Z","_id":"65e515284e7861d9b7fb23aa"},{"createdBy":"65a540b4c48c0387320b2044","createdAt":"2024-03-07T11:20:57.650Z","_id":"65ec4d7a05c55dfddbc5c603"},{"createdBy":"65eb0af8128aa1fbe12bfbed","createdAt":"2024-03-07T11:20:06.571Z","_id":"65eec58626355118f585740d"},{"createdBy":"65aaafc28dab24d43a97d43f","createdAt":"2024-03-07T11:20:57.537Z","_id":"65f1f74b1de51b84d43ce55a"},{"createdBy":"65a78c7271f5d4e177433009","createdAt":"2024-03-12T08:37:42.171Z","_id":"65f5ad0389f1841e6a5bc5c1"},{"createdBy":"65a78c7271f5d4e177433009","createdAt":"2024-03-07T11:20:06.306Z","_id":"65f5ad2d80382e44e43d9c59"},{"createdBy":"65a78c7271f5d4e177433009","createdAt":"2024-03-07T11:20:06.359Z","_id":"65f5ad533766ec7273568ee2"}],"createdAt":"2024-01-18T22:51:50.162Z","updatedAt":"2024-03-16T14:31:47.012Z","__v":0,"updatedBy":"65a78c7271f5d4e177433009"}