{"_id":"661e5923ceb1ab226a9a588a","createdBy":"6099504c693d8c00155df91f","deleted":false,"parentDocument":{"_id":"661e591fceb1ab226a9a4cc3","metadata":{"userGroup":[],"docType":{"showInFluidsPortal":false,"showInTyrePortal":false,"_id":"613771844b25a79f6947d0d8","showInHandbookPortal":false},"reference":"","validFrom":"2024-04-15T23:00:00.000Z","applicabilities":[{"vinRanges":[{"start":"AC6898","end":"zzzzzz"}],"engineNumberRanges":[],"modelYears":[{"start":2021,"end":9999}],"products":["LG1"],"markets":[]}],"negativeApplicabilities":[]}},"id":"3080158475","title":"Brake Master Cylinders - Inspection","content":[{"node":"title","body":[{"node":"text","body":"Brake Master Cylinders - Inspection"}]},{"node":"textmodule","body":[{"node":"title","body":[{"node":"text","body":"Warning - General - Stabilise Motorcycle - including DO NOT support on non integral parts"}]},{"node":"text","body":"\r\n"},{"node":"safety","body":[{"node":"text","body":"\r\n"},{"node":"consequence","body":[{"node":"text","body":"Make sure the motorcycle is stabilised and adequately supported."}]},{"node":"text","body":" \r\n"},{"node":"consequence","body":[{"node":"text","body":"Do not support the motorcycle on any ancillary component, the exhaust system or any other non structural parts of the motorcycle frame."}]},{"node":"text","body":" \r\n"},{"node":"consequence","body":[{"node":"text","body":"A correctly supported motorcycle will help prevent it from falling."}]},{"node":"text","body":" \r\n"},{"node":"consequence","body":[{"node":"variable","body":[{"node":"text","body":"Failure to follow the advice above could result in serious injury or death."}]}]}],"severity":"warning","type":"general"}],"metadata":{"MarketsTaxonomyLink":"All"},"type":"TextModule"},{"node":"p","body":[{"node":"text","body":"Inspect both the front and rear master cylinders for fluid leaks. Rectify as necessary."}]}],"ancestors":["1342166155"],"parent":"1342166155","lastUpdate":"2024-03-08T09:37:51.000Z","metadata":{"markets":["All"],"_id":"661e5923ceb1ab226a9a588b"},"search":["Brake Master Cylinders - Inspection","Make sure the motorcycle is stabilised and adequately supported.","Do not support the motorcycle on any ancillary component, the exhaust system or any other non structural parts of the motorcycle frame.","A correctly supported motorcycle will help prevent it from falling.","Failure to follow the advice above could result in serious injury or death.","Inspect both the front and rear master cylinders for fluid leaks. Rectify as necessary."],"viewCount":0,"infoType":"InfoType04","createdAt":"2024-04-16T10:55:31.136Z","updatedAt":"2024-04-16T10:55:31.136Z","__v":0}