{"_id":"661e592bceb1ab226a9a6b5b","createdBy":"6099504c693d8c00155df91f","deleted":false,"parentDocument":{"_id":"661e591fceb1ab226a9a4cc3","metadata":{"userGroup":[],"docType":{"showInFluidsPortal":false,"showInTyrePortal":false,"_id":"613771844b25a79f6947d0d8","showInHandbookPortal":false},"reference":"","validFrom":"2024-04-15T23:00:00.000Z","applicabilities":[{"vinRanges":[{"start":"AC6898","end":"zzzzzz"}],"engineNumberRanges":[],"modelYears":[{"start":2021,"end":9999}],"products":["LG1"],"markets":[]}],"negativeApplicabilities":[]}},"id":"5894984715","title":"Exploded View - Front Mudguard","content":[{"node":"title","body":[{"node":"text","body":"Exploded View - Front Mudguard"}]},{"node":"image-container","body":[{"node":"img","body":[],"href":"27021603659214347__en__Original.svg","id":"27021603659214347","name":"Exploded View - Front Mudguard","type":"st4-svg"}],"type":"img_fixed_textarea"},{"node":"image","body":[],"type":"st4-svg"}],"ancestors":["1342547211"],"parent":"1342547211","lastUpdate":"2021-12-06T09:28:52.000Z","metadata":{"markets":["All"],"_id":"661e592bceb1ab226a9a6b5c"},"search":["Exploded View - Front Mudguard"],"viewCount":0,"infoType":"InfoType03","createdAt":"2024-04-16T10:55:39.006Z","updatedAt":"2024-04-16T10:55:39.006Z","__v":0}